Workbook

Sheet 1. Share_Price_Analysis
B1: Sheet 1: Share Price Analysis
B3: General Information | D3: Market Stats
B4: General Information | D4: Market Stats
B5: Analysis Company | C5: Vulcan Materials (VMC) | D5: Current Price | E5: ='[1]Sheet9_Financial Data'!C755 -> 295.98 | L5: =2/(50+1) -> 0.039215686
B6: Ticker | C6: VMC.N | D6: Market Cap | E6: 37,510,000,000
B7: Benchmark | C7: SPY500 | D7: 52W High | E7: =MAX('[1]Sheet9_Financial Data'!C503:C754) -> 330.37
B8: Sector Benchmark | C8: XLB | D8: 52W Low | E8: =MIN('[1]Sheet9_Financial Data'!C504:C755) -> 220.9
B9: End date | C9: ='[1]Sheet9_Financial Data'!B4 -> 44991 | D9: Average Daily Return | E9: =AVERAGE('[1]Sheet9_Financial Data'!F5:F755) -> 0.0007791693
B10: Start date | C10: ='[1]Sheet9_Financial Data'!B755 -> 46085 | D10: Risk Free Rate | E10: 0.04
B11: Trading days | C11: 252 | D11: Alpha | E11: =2/(200+1) -> 0.0099502488
B13: Metrics | C13: VMC | D13: SPY | E13: XLB
B14: Annualized Return | C14: {=GEOMEAN(1+'[1]Sheet9_Financial Data'!F$5:F$755)^$C$11-1} -> 0.18207784 | D14: {=GEOMEAN(1+'[1]Sheet9_Financial Data'!G$5:G$755)^$C$11-1} -> 0.19344804 | E14: {=GEOMEAN(1+'[1]Sheet9_Financial Data'!H$5:H$755)^$C$11-1} -> 0.077063972
B15: Annualized Volatility | C15: =_xlfn.STDEV.S('[1]Sheet9_Financial Data'!F5:F755)*SQRT($C$11) -> 0.24100121 | D15: =_xlfn.STDEV.S('[1]Sheet9_Financial Data'!G5:G755)*SQRT($C$11) -> 0.15160814 | E15: =_xlfn.STDEV.S('[1]Sheet9_Financial Data'!H5:H755)*SQRT($C$11) -> 0.1707121
B16: Total Return | C16: ='[1]Sheet9_Financial Data'!C755/'[1]Sheet9_Financial Data'!C4 - 1 -> 0.64625396 | D16: ='[1]Sheet9_Financial Data'!D755/'[1]Sheet9_Financial Data'!D4 - 1 -> 0.69389572 | E16: ='[1]Sheet9_Financial Data'!E755/'[1]Sheet9_Financial Data'!E4 - 1 -> 0.24762706
B17: Beta vs SPY | C17: =SLOPE('[1]Sheet9_Financial Data'!$F$5:$F$755,'[1]Sheet9_Financial Data'!G5:G755) -> 0.82769326
B18: Beta vs XLB | C18: =SLOPE('[1]Sheet9_Financial Data'!$F$5:$F$755,'[1]Sheet9_Financial Data'!H5:H755) -> 0.79887867
B19: Sharpe Ratio | C19: =(C14-E10)/C15 -> 0.58953163
B20: Max Drawdown | C20: =MIN('[1]Sheet9_Financial Data'!T4:T755) -> -0.24429544
B63: Date | C63: VMC Adj Close | D63: SPY Adj Close | E63: XLB Adj Close | F63: VMC % Change | G63: SPY & Change | H63: XLB % Change | I63: Cummulative Return VMC | J63: Cummulative SPY return | K63: Cummulative Return XLB | L63: VMC Normalized | M63: SPY Normalized | N63: XLB Normalized | O63: VMC Relative vs SPY | P63: VMC Relative vs XLB | Q63: VMC Wealth Index | R63: VMC Running Peak | S63: VMC Drawdown | T63: VMC EMA200 | U63: VMC EMA50
B64: 44991 | C64: 179.79 | D64: 404.47 | E64: 41.615 | I64: 0 | J64: 0 | K64: 0 | L64: =(C64/$C$64)*100 -> 100 | M64: =(D64/$D$64)*100 -> 100 | N64: =(E64/$E$64)*100 -> 100 | O64: =(1+I64)/(1+J64)-1 -> 0 | P64: =(1+I64)/(1+K64)-1 -> 0 | Q64: 1 | R64: 1 | S64: 0 | T64: =C64 -> 179.79 | U64: =C64 -> 179.79
B65: 44992 | C65: 177.23 | D65: 398.27 | E65: 40.795 | F65: =C65/C64-1 -> -0.014238834 | G65: =D65/D64 - 1 -> -0.015328702 | H65: =E65/E64 - 1 -> -0.019704433 | I65: =(1+F65)*(1+I64)-1 -> -0.014238834 | J65: =(1+G65)*(1+J64)-1 -> -0.015328702 | K65: =(1+H65)*(1+K64)-1 -> -0.019704433 | L65: =(C65/$C$64)*100 -> 98.576117 | M65: =(D65/$D$64)*100 -> 98.46713 | N65: =(E65/$E$64)*100 -> 98.029557 | O65: =(1+I65)/(1+J65)-1 -> 0.0011068339 | P65: =(1+I65)/(1+K65)-1 -> 0.0055754606 | Q65: =Q64*(1+F65) -> 0.98576117 | R65: =MAX(Q65,R64) -> 1 | S65: =Q65/R65-1 -> -0.014238834 | T65: =C65*'1. Share_Price_Analysis'!$E$11+T64*(1-'1. Share_Price_Analysis'!$E$11) -> 179.76453 | U65: =C65*$L$5+U64*(1-$L$5) -> 179.68961
B66: 44993 | C66: 178.92 | D66: 398.92 | E66: 40.995 | F66: =C66/C65-1 -> 0.0095356317 | G66: =D66/D65 - 1 -> 0.0016320587 | H66: =E66/E65 - 1 -> 0.0049025616 | I66: =(1+F66)*(1+I65)-1 -> -0.0048389788 | J66: =(1+G66)*(1+J65)-1 -> -0.01372166 | K66: =(1+H66)*(1+K65)-1 -> -0.014898474 | L66: =(C66/$C$64)*100 -> 99.516102 | M66: =(D66/$D$64)*100 -> 98.627834 | N66: =(E66/$E$64)*100 -> 98.510153 | O66: =(1+I66)/(1+J66)-1 -> 0.0090062625 | P66: =(1+I66)/(1+K66)-1 -> 0.010211633 | Q66: =Q65*(1+F66) -> 0.99516102 | R66: =MAX(Q66,R65) -> 1 | S66: =Q66/R66-1 -> -0.0048389788 | T66: =C66*'1. Share_Price_Analysis'!$E$11+T65*(1-'1. Share_Price_Analysis'!$E$11) -> 179.75612 | U66: =C66*$L$5+U65*(1-$L$5) -> 179.65943
B67: 44994 | C67: 174.07 | D67: 391.56 | E67: 39.94 | F67: =C67/C66-1 -> -0.027107087 | G67: =D67/D66 - 1 -> -0.018449814 | H67: =E67/E66 - 1 -> -0.025734846 | I67: =(1+F67)*(1+I66)-1 -> -0.031814895 | J67: =(1+G67)*(1+J66)-1 -> -0.031918313 | K67: =(1+H67)*(1+K66)-1 -> -0.04024991 | L67: =(C67/$C$64)*100 -> 96.81851 | M67: =(D67/$D$64)*100 -> 96.808169 | N67: =(E67/$E$64)*100 -> 95.975009 | O67: =(1+I67)/(1+J67)-1 -> 0.00010682745 | P67: =(1+I67)/(1+K67)-1 -> 0.0087887616 | Q67: =Q66*(1+F67) -> 0.9681851 | R67: =MAX(Q67,R66) -> 1 | S67: =Q67/R67-1 -> -0.031814895 | T67: =C67*'1. Share_Price_Analysis'!$E$11+T66*(1-'1. Share_Price_Analysis'!$E$11) -> 179.69955 | U67: =C67*$L$5+U66*(1-$L$5) -> 179.44023
B68: 44995 | C68: 169.29 | D68: 385.91 | E68: 39.09 | F68: =C68/C67-1 -> -0.027460217 | G68: =D68/D67 - 1 -> -0.014429462 | H68: =E68/E67 - 1 -> -0.021281923 | I68: =(1+F68)*(1+I67)-1 -> -0.058401468 | J68: =(1+G68)*(1+J67)-1 -> -0.04588721 | K68: =(1+H68)*(1+K67)-1 -> -0.060675237 | L68: =(C68/$C$64)*100 -> 94.159853 | M68: =(D68/$D$64)*100 -> 95.411279 | N68: =(E68/$E$64)*100 -> 93.932476 | O68: =(1+I68)/(1+J68)-1 -> -0.01311612 | P68: =(1+I68)/(1+K68)-1 -> 0.0024206419 | Q68: =Q67*(1+F68) -> 0.94159853 | R68: =MAX(Q68,R67) -> 1 | S68: =Q68/R68-1 -> -0.058401468 | T68: =C68*'1. Share_Price_Analysis'!$E$11+T67*(1-'1. Share_Price_Analysis'!$E$11) -> 179.59597 | U68: =C68*$L$5+U67*(1-$L$5) -> 179.04219
B69: 44998 | C69: 165.98 | D69: 385.36 | E69: 38.69 | F69: =C69/C68-1 -> -0.019552248 | G69: =D69/D68 - 1 -> -0.0014252028 | H69: =E69/E68 - 1 -> -0.010232796 | I69: =(1+F69)*(1+I68)-1 -> -0.076811836 | J69: =(1+G69)*(1+J68)-1 -> -0.047247015 | K69: =(1+H69)*(1+K68)-1 -> -0.070287156 | L69: =(C69/$C$64)*100 -> 92.318816 | M69: =(D69/$D$64)*100 -> 95.275299 | N69: =(E69/$E$64)*100 -> 92.971284 | O69: =(1+I69)/(1+J69)-1 -> -0.031030941 | P69: =(1+I69)/(1+K69)-1 -> -0.0070179518 | Q69: =Q68*(1+F69) -> 0.92318816 | R69: =MAX(Q69,R68) -> 1 | S69: =Q69/R69-1 -> -0.076811836 | T69: =C69*'1. Share_Price_Analysis'!$E$11+T68*(1-'1. Share_Price_Analysis'!$E$11) -> 179.46049 | U69: =C69*$L$5+U68*(1-$L$5) -> 178.52994
B70: 44999 | C70: 167.51 | D70: 391.73 | E70: 39.185 | F70: =C70/C69-1 -> 0.0092179781 | G70: =D70/D69 - 1 -> 0.016529998 | H70: =E70/E69 - 1 -> 0.012794004 | I70: =(1+F70)*(1+I69)-1 -> -0.068301908 | J70: =(1+G70)*(1+J69)-1 -> -0.03149801 | K70: =(1+H70)*(1+K69)-1 -> -0.058392407 | L70: =(C70/$C$64)*100 -> 93.169809 | M70: =(D70/$D$64)*100 -> 96.850199 | N70: =(E70/$E$64)*100 -> 94.160759 | O70: =(1+I70)/(1+J70)-1 -> -0.038000849 | P70: =(1+I70)/(1+K70)-1 -> -0.010524024 | Q70: =Q69*(1+F70) -> 0.93169809 | R70: =MAX(Q70,R69) -> 1 | S70: =Q70/R70-1 -> -0.068301908 | T70: =C70*'1. Share_Price_Analysis'!$E$11+T69*(1-'1. Share_Price_Analysis'!$E$11) -> 179.34158 | U70: =C70*$L$5+U69*(1-$L$5) -> 178.09779
B71: 45000 | C71: 162.81 | D71: 389.28 | E71: 37.915 | F71: =C71/C70-1 -> -0.028058026 | G71: =D71/D70 - 1 -> -0.0062543078 | H71: =E71/E70 - 1 -> -0.032410361 | I71: =(1+F71)*(1+I70)-1 -> -0.094443517 | J71: =(1+G71)*(1+J70)-1 -> -0.037555319 | K71: =(1+H71)*(1+K70)-1 -> -0.088910249 | L71: =(C71/$C$64)*100 -> 90.555648 | M71: =(D71/$D$64)*100 -> 96.244468 | N71: =(E71/$E$64)*100 -> 91.108975 | O71: =(1+I71)/(1+J71)-1 -> -0.059108019 | P71: =(1+I71)/(1+K71)-1 -> -0.0060732422 | Q71: =Q70*(1+F71) -> 0.90555648 | R71: =MAX(Q71,R70) -> 1 | S71: =Q71/R71-1 -> -0.094443517 | T71: =C71*'1. Share_Price_Analysis'!$E$11+T70*(1-'1. Share_Price_Analysis'!$E$11) -> 179.17708 | U71: =C71*$L$5+U70*(1-$L$5) -> 177.49827
B72: 45001 | C72: 166.21 | D72: 396.11 | E72: 38.35 | F72: =C72/C71-1 -> 0.020883238 | G72: =D72/D71 - 1 -> 0.017545212 | H72: =E72/E71 - 1 -> 0.011473032 | I72: =(1+F72)*(1+I71)-1 -> -0.075532566 | J72: =(1+G72)*(1+J71)-1 -> -0.020669024 | K72: =(1+H72)*(1+K71)-1 -> -0.078457287 | L72: =(C72/$C$64)*100 -> 92.446743 | M72: =(D72/$D$64)*100 -> 97.933098 | N72: =(E72/$E$64)*100 -> 92.154271 | O72: =(1+I72)/(1+J72)-1 -> -0.056021451 | P72: =(1+I72)/(1+K72)-1 -> 0.003173723 | Q72: =Q71*(1+F72) -> 0.92446743 | R72: =MAX(Q72,R71) -> 1 | S72: =Q72/R72-1 -> -0.075532566 | T72: =C72*'1. Share_Price_Analysis'!$E$11+T71*(1-'1. Share_Price_Analysis'!$E$11) -> 179.04806 | U72: =C72*$L$5+U71*(1-$L$5) -> 177.05559
B73: 45002 | C73: 161.02 | D73: 389.99 | E73: 37.755 | F73: =C73/C72-1 -> -0.031225558 | G73: =D73/D72 - 1 -> -0.015450254 | H73: =E73/E72 - 1 -> -0.015514993 | I73: =(1+F73)*(1+I72)-1 -> -0.10439958 | J73: =(1+G73)*(1+J72)-1 -> -0.035799936 | K73: =(1+H73)*(1+K72)-1 -> -0.092755016 | L73: =(C73/$C$64)*100 -> 89.560042 | M73: =(D73/$D$64)*100 -> 96.420006 | N73: =(E73/$E$64)*100 -> 90.724498 | O73: =(1+I73)/(1+J73)-1 -> -0.071146688 | P73: =(1+I73)/(1+K73)-1 -> -0.012835079 | Q73: =Q72*(1+F73) -> 0.89560042 | R73: =MAX(Q73,R72) -> 1 | S73: =Q73/R73-1 -> -0.10439958 | T73: =C73*'1. Share_Price_Analysis'!$E$11+T72*(1-'1. Share_Price_Analysis'!$E$11) -> 178.86867 | U73: =C73*$L$5+U72*(1-$L$5) -> 176.42674
B74: 45005 | C74: 163.27 | D74: 393.74 | E74: 38.365 | F74: =C74/C73-1 -> 0.013973419 | G74: =D74/D73 - 1 -> 0.0096156312 | H74: =E74/E73 - 1 -> 0.0161568 | I74: =(1+F74)*(1+I73)-1 -> -0.091884977 | J74: =(1+G74)*(1+J73)-1 -> -0.026528544 | K74: =(1+H74)*(1+K73)-1 -> -0.07809684 | L74: =(C74/$C$64)*100 -> 90.811502 | M74: =(D74/$D$64)*100 -> 97.347146 | N74: =(E74/$E$64)*100 -> 92.190316 | O74: =(1+I74)/(1+J74)-1 -> -0.067137493 | P74: =(1+I74)/(1+K74)-1 -> -0.014956166 | Q74: =Q73*(1+F74) -> 0.90811502 | R74: =MAX(Q74,R73) -> 1 | S74: =Q74/R74-1 -> -0.091884977 | T74: =C74*'1. Share_Price_Analysis'!$E$11+T73*(1-'1. Share_Price_Analysis'!$E$11) -> 178.71346 | U74: =C74*$L$5+U73*(1-$L$5) -> 175.91079
B75: 45006 | C75: 166.14 | D75: 398.91 | E75: 38.83 | F75: =C75/C74-1 -> 0.017578245 | G75: =D75/D74 - 1 -> 0.013130492 | H75: =E75/E74 - 1 -> 0.012120422 | I75: =(1+F75)*(1+I74)-1 -> -0.075921909 | J75: =(1+G75)*(1+J74)-1 -> -0.013746384 | K75: =(1+H75)*(1+K74)-1 -> -0.066922985 | L75: =(C75/$C$64)*100 -> 92.407809 | M75: =(D75/$D$64)*100 -> 98.625362 | N75: =(E75/$E$64)*100 -> 93.307702 | O75: =(1+I75)/(1+J75)-1 -> -0.063042126 | P75: =(1+I75)/(1+K75)-1 -> -0.0096443533 | Q75: =Q74*(1+F75) -> 0.92407809 | R75: =MAX(Q75,R74) -> 1 | S75: =Q75/R75-1 -> -0.075921909 | T75: =C75*'1. Share_Price_Analysis'!$E$11+T74*(1-'1. Share_Price_Analysis'!$E$11) -> 178.58835 | U75: =C75*$L$5+U74*(1-$L$5) -> 175.52762
B76: 45007 | C76: 163.71 | D76: 392.11 | E76: 38.14 | F76: =C76/C75-1 -> -0.014626219 | G76: =D76/D75 - 1 -> -0.017046452 | H76: =E76/E75 - 1 -> -0.017769766 | I76: =(1+F76)*(1+I75)-1 -> -0.089437677 | J76: =(1+G76)*(1+J75)-1 -> -0.030558509 | K76: =(1+H76)*(1+K75)-1 -> -0.083503544 | L76: =(C76/$C$64)*100 -> 91.056232 | M76: =(D76/$D$64)*100 -> 96.944149 | N76: =(E76/$E$64)*100 -> 91.649646 | O76: =(1+I76)/(1+J76)-1 -> -0.060735144 | P76: =(1+I76)/(1+K76)-1 -> -0.0064748018 | Q76: =Q75*(1+F76) -> 0.91056232 | R76: =MAX(Q76,R75) -> 1 | S76: =Q76/R76-1 -> -0.089437677 | T76: =C76*'1. Share_Price_Analysis'!$E$11+T75*(1-'1. Share_Price_Analysis'!$E$11) -> 178.44031 | U76: =C76*$L$5+U75*(1-$L$5) -> 175.06419
... B814: 46084 | C814: 300 | D814: 680.33 | E814: 51.94 | F814: =C814/C813-1 -> -0.020248204 | G814: =D814/D813 - 1 -> -0.0088143594 | H814: =E814/E813 - 1 -> -0.024600939 | I814: =(1+F814)*(1+I813)-1 -> 0.66861338 | J814: =(1+G814)*(1+J813)-1 -> 0.68202833 | K814: =(1+H814)*(1+K813)-1 -> 0.24810765 | L814: =(C814/$C$64)*100 -> 166.86134 | M814: =(D814/$D$64)*100 -> 168.20283 | N814: =(E814/$E$64)*100 -> 124.81077 | O814: =(1+I814)/(1+J814)-1 -> -0.0079754608 | P814: =(1+I814)/(1+K814)-1 -> 0.33691463 | Q814: =Q813*(1+F814) -> 1.6686134 | R814: =MAX(Q814,R813) -> 1.8375327 | S814: =Q814/R814-1 -> -0.091927233 | T814: =C814*'1. Share_Price_Analysis'!$E$11+T813*(1-'1. Share_Price_Analysis'!$E$11) -> 289.80305 | U814: =C814*$L$5+U813*(1-$L$5) -> 305.05759
B815: 46085 | C815: 295.98 | D815: 685.13 | E815: 51.92 | F815: =C815/C814-1 -> -0.0134 | G815: =D815/D814 - 1 -> 0.0070553996 | H815: =E815/E814 - 1 -> -0.00038505968 | I815: =(1+F815)*(1+I814)-1 -> 0.64625396 | J815: =(1+G815)*(1+J814)-1 -> 0.69389572 | K815: =(1+H815)*(1+K814)-1 -> 0.24762706 | L815: =(C815/$C$64)*100 -> 164.6254 | M815: =(D815/$D$64)*100 -> 169.38957 | N815: =(E815/$E$64)*100 -> 124.76271 | O815: =(1+I815)/(1+J815)-1 -> -0.028125552 | P815: =(1+I815)/(1+K815)-1 -> 0.31950806 | Q815: =Q814*(1+F815) -> 1.646254 | R815: =MAX(Q815,R814) -> 1.8375327 | S815: =Q815/R815-1 -> -0.10409541

Sheet 2. Financial_Analyst
B1: Sheet2_Financial_Analyst
B2: Horizental Analysis
B3: Year | C3: 2021 | D3: 2022 | E3: 2023 | F3: 2024 | G3: 2025 | H3: 2022 YoY | I3: 2023 YoY | J3: 2024 YoY | K3: 2025 YoY | L3: 4Y CAGR
B4: Income Statement | U4: Company | V4: MLM | W4: EXP | X4: VMC | Y4: CRH | Z4: KNF | AA4: CX
B5: Revenue | C5: ='9. Standardlized_Income'!H34 -> 5552.2 | D5: ='9. Standardlized_Income'!G34 -> 7315.2 | E5: ='9. Standardlized_Income'!F34 -> 7781.9 | F5: ='9. Standardlized_Income'!E34 -> 7417.7 | G5: ='9. Standardlized_Income'!D34 -> 7941.1 | H5: =D5/C5-1 -> 0.31753179 | I5: =E5/D5-1 -> 0.063798666 | J5: =F5/E5-1 -> -0.04680091 | K5: =G5/F5-1 -> 0.070560956 | L5: =(G5/C5)^(1/4)-1 -> 0.09358839 | U5: EBITDA Margin | V5: ='9. Standardlized_Income'!J46/'9. Standardlized_Income'!J34 -> 0.34634146 | W5: ='9. Standardlized_Income'!R46/'9. Standardlized_Income'!R34 -> 0.33820686 | X5: ='9. Standardlized_Income'!D46/'9. Standardlized_Income'!D34 -> 0.28659757 | Y5: ='9. Standardlized_Income'!N46/'9. Standardlized_Income'!N34 -> 0.19972227 | Z5: ='9. Standardlized_Income'!L46/'9. Standardlized_Income'!L34 -> 0.15613746 | AA5: ='9. Standardlized_Income'!P46/'9. Standardlized_Income'!P34 -> 0.14231323
B6: Cost of Revenues | C6: ='9. Standardlized_Income'!H35 -> 4178.8 | D6: ='9. Standardlized_Income'!G35 -> 5757.5 | E6: ='9. Standardlized_Income'!F35 -> 5833.4 | F6: ='9. Standardlized_Income'!E35 -> 5418.1 | G6: ='9. Standardlized_Income'!D35 -> 5766.5 | H6: =D6/C6-1 -> 0.37778788 | I6: =E6/D6-1 -> 0.013182805 | J6: =F6/E6-1 -> -0.071193472 | K6: =G6/F6-1 -> 0.064302984 | L6: =(G6/C6)^(1/4)-1 -> 0.083840007
B7: Gross Profit | C7: =C5-C6 -> 1373.4 | D7: =D5-D6 -> 1557.7 | E7: =E5-E6 -> 1948.5 | F7: =F5-F6 -> 1999.6 | G7: =G5-G6 -> 2174.6 | H7: =D7/C7-1 -> 0.13419251 | I7: =E7/D7-1 -> 0.25088271 | J7: =F7/E7-1 -> 0.026225302 | K7: =G7/F7-1 -> 0.087517504 | L7: =(G7/C7)^(1/4)-1 -> 0.12174873 | U7: Metric | V7: MLM | W7: EXP | X7: VMC | Y7: CRH | Z7: KNF | AA7: CX
B8: SG&A | C8: ='9. Standardlized_Income'!H37 -> 417.6 | D8: ='9. Standardlized_Income'!G37 -> 515.1 | E8: ='9. Standardlized_Income'!F37 -> 542.8 | F8: ='9. Standardlized_Income'!E37 -> 531.1 | G8: ='9. Standardlized_Income'!D37 -> 564.1 | H8: =D8/C8-1 -> 0.23347701 | I8: =E8/D8-1 -> 0.053775966 | J8: =F8/E8-1 -> -0.021554901 | K8: =G8/F8-1 -> 0.062135191 | L8: =(G8/C8)^(1/4)-1 -> 0.07807482 | U8: EBITDA Margin | V8: ='9. Standardlized_Income'!J46/'9. Standardlized_Income'!J34 -> 0.34634146 | W8: ='9. Standardlized_Income'!R46/'9. Standardlized_Income'!R34 -> 0.33820686 | X8: ='9. Standardlized_Income'!D46/'9. Standardlized_Income'!D34 -> 0.28659757 | Y8: ='9. Standardlized_Income'!N46/'9. Standardlized_Income'!N34 -> 0.19972227 | Z8: ='9. Standardlized_Income'!L46/'9. Standardlized_Income'!L34 -> 0.15613746 | AA8: ='9. Standardlized_Income'!P46/'9. Standardlized_Income'!P34 -> 0.14231323
B9: Other Operating (Income) / Expense | C9: ='9. Standardlized_Income'!H38 -> -15.9 | D9: ='9. Standardlized_Income'!G38 -> 13.1 | E9: ='9. Standardlized_Income'!F38 -> 83.5 | F9: ='9. Standardlized_Income'!E38 -> 72.4 | G9: ='9. Standardlized_Income'!D38 -> 83.1 | H9: =D9/C9-1 -> -1.8238994 | I9: =E9/D9-1 -> 5.3740458 | J9: =F9/E9-1 -> -0.13293413 | K9: =G9/F9-1 -> 0.14779006 | L9: Not Meaningful | U9: EBIT Margin | V9: ='9. Standardlized_Income'!J39/'9. Standardlized_Income'!J34 -> 0.24276423 | W9: ='9. Standardlized_Income'!R39/'9. Standardlized_Income'!R34 -> 0.26791299 | X9: ='9. Standardlized_Income'!D39/'9. Standardlized_Income'!D34 -> 0.19234111 | Y9: ='9. Standardlized_Income'!N39/'9. Standardlized_Income'!N34 -> 0.14214757 | Z9: ='9. Standardlized_Income'!L39/'9. Standardlized_Income'!L34 -> 0.09455469 | AA9: ='9. Standardlized_Income'!P39/'9. Standardlized_Income'!P34 -> 0.062289702
B10: EBITDA | C10: =C11+'9. Standardlized_Income'!H47 -> 1434.7 | D10: =D11+'9. Standardlized_Income'!G47 -> 1617 | E10: =E11+'9. Standardlized_Income'!F47 -> 1939.2 | F10: =F11+'9. Standardlized_Income'!E47 -> 2028.3 | G10: =G11+'9. Standardlized_Income'!D47 -> 2275.9 | H10: =D10/C10-1 -> 0.12706489 | I10: =E10/D10-1 -> 0.19925788 | J10: =F10/E10-1 -> 0.045946782 | K10: =G10/F10-1 -> 0.12207267 | L10: =(G10/C10)^(1/4)-1 -> 0.12227172 | U10: Net Margin | V10: ='9. Standardlized_Income'!J44/'9. Standardlized_Income'!J34 -> 0.18487805 | W10: ='9. Standardlized_Income'!R44/'9. Standardlized_Income'!R34 -> 0.20500683 | X10: ='9. Standardlized_Income'!D44/'9. Standardlized_Income'!D34 -> 0.13558575 | Y10: ='9. Standardlized_Income'!N44/'9. Standardlized_Income'!N34 -> 0.10022165 | Z10: ='9. Standardlized_Income'!L44/'9. Standardlized_Income'!L34 -> 0.049926733 | AA10: ='9. Standardlized_Income'!P44/'9. Standardlized_Income'!P34 -> 0.059519411
B11: EBIT | C11: =C7-C8-C9 -> 971.7 | D11: =D7-D8-D9 -> 1029.5 | E11: =E7-E8-E9 -> 1322.2 | F11: =F7-F8-F9 -> 1396.1 | G11: =G7-G8-G9 -> 1527.4 | H11: =D11/C11-1 -> 0.05948338 | I11: =E11/D11-1 -> 0.28431277 | J11: =F11/E11-1 -> 0.055891696 | K11: =G11/F11-1 -> 0.094047704 | L11: =(G11/C11)^(1/4)-1 -> 0.11970894
B12: Net Income | C12: ='9. Standardlized_Income'!H44 -> 670.8 | D12: ='9. Standardlized_Income'!G44 -> 575.6 | E12: ='9. Standardlized_Income'!F44 -> 933.2 | F12: ='9. Standardlized_Income'!E44 -> 911.9 | G12: ='9. Standardlized_Income'!D44 -> 1076.7 | H12: =D12/C12-1 -> -0.1419201 | I12: =E12/D12-1 -> 0.62126477 | J12: =F12/E12-1 -> -0.022824689 | K12: =G12/F12-1 -> 0.18072157 | L12: =(G12/C12)^(1/4)-1 -> 0.12557753 | N12: =C12/C11 -> 0.69033652 | U12: Metric | V12: MLM | W12: EXP | X12: VMC | Y12: CRH | Z12: KNF | AA12: CX
U13: Debt/Equity | V13: ='9. Standardlized_Income'!J31/'9. Standardlized_Income'!J30 -> 0.56059398 | W13: ='9. Standardlized_Income'!R31/'9. Standardlized_Income'!R30 -> 0.85008581 | X13: ='9. Standardlized_Income'!D31/'9. Standardlized_Income'!D30 -> 0.5115161 | Y13: ='9. Standardlized_Income'!N31/'9. Standardlized_Income'!N30 -> 0.72608592 | Z13: ='9. Standardlized_Income'!L31/'9. Standardlized_Income'!L30 -> 0.71028801 | AA13: ='9. Standardlized_Income'!P31/'9. Standardlized_Income'!P30 -> 0.49773523
B14: Balance Sheet | U14: Debt/Assets | V14: ='9. Standardlized_Income'!J31/'9. Standardlized_Income'!J17 -> 0.3006253 | W14: ='9. Standardlized_Income'!R31/'9. Standardlized_Income'!R17 -> 0.37931869 | X14: ='9. Standardlized_Income'!D31/'9. Standardlized_Income'!D17 -> 0.26184403 | Y14: ='9. Standardlized_Income'!N31/'9. Standardlized_Income'!N17 -> 0.31180031 | Z14: ='9. Standardlized_Income'!L31/'9. Standardlized_Income'!L17 -> 0.3193164 | AA14: ='9. Standardlized_Income'!P31/'9. Standardlized_Income'!P17 -> 0.23407114
B15: Cash & ST Investments | C15: ='9. Standardlized_Income'!H8 -> 235 | D15: ='9. Standardlized_Income'!G8 -> 161.4 | E15: ='9. Standardlized_Income'!F8 -> 931.1 | F15: ='9. Standardlized_Income'!E8 -> 559.7 | G15: ='9. Standardlized_Income'!D8 -> 183.3 | H15: =D15/C15-1 -> -0.31319149 | I15: =E15/D15-1 -> 4.7688971 | J15: =F15/E15-1 -> -0.39888304 | K15: =G15/F15-1 -> -0.67250313 | L15: =(G15/C15)^(1/4)-1 -> -0.060225513 | U15: Interest Coverage | V15: ='9. Standardlized_Income'!J39/'9. Standardlized_Income'!J40 -> 6.4913043 | W15: ='9. Standardlized_Income'!R39/'9. Standardlized_Income'!R40 -> 15.050199 | X15: ='9. Standardlized_Income'!D39/'9. Standardlized_Income'!D40 -> 6.3721318 | Y15: ='9. Standardlized_Income'!N39/'9. Standardlized_Income'!N40 -> 6.5716049 | Z15: ='9. Standardlized_Income'!L39/'9. Standardlized_Income'!L40 -> 3.6303393 | AA15: ='9. Standardlized_Income'!P39/'9. Standardlized_Income'!P40 -> 3.3408139
B16: Receivables | C16: ='9. Standardlized_Income'!H9 -> 783.2 | D16: ='9. Standardlized_Income'!G9 -> 845.6 | E16: ='9. Standardlized_Income'!F9 -> 889.7 | F16: ='9. Standardlized_Income'!E9 -> 892.3 | G16: ='9. Standardlized_Income'!D9 -> 887.7 | H16: =D16/C16-1 -> 0.079673136 | I16: =E16/D16-1 -> 0.052152318 | J16: =F16/E16-1 -> 0.0029223334 | K16: =G16/F16-1 -> -0.0051552169 | L16: =(G16/C16)^(1/4)-1 -> 0.031806799
B17: Inventory | C17: ='9. Standardlized_Income'!H10 -> 521.3 | D17: ='9. Standardlized_Income'!G10 -> 579.3 | E17: ='9. Standardlized_Income'!F10 -> 615.6 | F17: ='9. Standardlized_Income'!E10 -> 681.8 | G17: ='9. Standardlized_Income'!D10 -> 680.5 | H17: =D17/C17-1 -> 0.11126031 | I17: =E17/D17-1 -> 0.062661833 | J17: =F17/E17-1 -> 0.10753736 | K17: =G17/F17-1 -> -0.0019067175 | L17: =(G17/C17)^(1/4)-1 -> 0.068895137
B18: Current Assets | C18: ='9. Standardlized_Income'!H12 -> 1696.6 | D18: ='9. Standardlized_Income'!G12 -> 1902 | E18: ='9. Standardlized_Income'!F12 -> 2524.9 | F18: ='9. Standardlized_Income'!E12 -> 2265.7 | G18: ='9. Standardlized_Income'!D12 -> 2567.9 | H18: =D18/C18-1 -> 0.12106566 | I18: =E18/D18-1 -> 0.32749737 | J18: =F18/E18-1 -> -0.10265753 | K18: =G18/F18-1 -> 0.13338041 | L18: =(G18/C18)^(1/4)-1 -> 0.10917395
B19: PP&E, net | C19: ='9. Standardlized_Income'!H13 -> 6238.2 | D19: ='9. Standardlized_Income'!G13 -> 6623.9 | E19: ='9. Standardlized_Income'!F13 -> 6729.4 | F19: ='9. Standardlized_Income'!E13 -> 8987.9 | G19: ='9. Standardlized_Income'!D13 -> 8670.1 | H19: =D19/C19-1 -> 0.061828733 | I19: =E19/D19-1 -> 0.015927173 | J19: =F19/E19-1 -> 0.33561685 | K19: =G19/F19-1 -> -0.035358649 | L19: =(G19/C19)^(1/4)-1 -> 0.085778413
B20: Total Assets | C20: ='9. Standardlized_Income'!H17 -> 13682.6 | D20: ='9. Standardlized_Income'!G17 -> 14234.6 | E20: ='9. Standardlized_Income'!F17 -> 14545.7 | F20: ='9. Standardlized_Income'!E17 -> 17104.8 | G20: ='9. Standardlized_Income'!D17 -> 16700.4 | H20: =D20/C20-1 -> 0.04034321 | I20: =E20/D20-1 -> 0.021855198 | J20: =F20/E20-1 -> 0.17593516 | K20: =G20/F20-1 -> -0.023642486 | L20: =(G20/C20)^(1/4)-1 -> 0.051089168
B21: Payables | C21: ='9. Standardlized_Income'!H19 -> 365.5 | D21: ='9. Standardlized_Income'!G19 -> 454.5 | E21: ='9. Standardlized_Income'!F19 -> 390.4 | F21: ='9. Standardlized_Income'!E19 -> 407 | G21: ='9. Standardlized_Income'!D19 -> 438.5 | H21: =D21/C21-1 -> 0.24350205 | I21: =E21/D21-1 -> -0.1410341 | J21: =F21/E21-1 -> 0.042520492 | K21: =G21/F21-1 -> 0.077395577 | L21: =(G21/C21)^(1/4)-1 -> 0.046575477
B22: Current Liabilities | C22: ='9. Standardlized_Income'!H22 -> 769.3 | D22: ='9. Standardlized_Income'!G22 -> 956.6 | E22: ='9. Standardlized_Income'!F22 -> 797.6 | F22: ='9. Standardlized_Income'!E22 -> 1239.1 | G22: ='9. Standardlized_Income'!D22 -> 956.1 | H22: =D22/C22-1 -> 0.24346809 | I22: =E22/D22-1 -> -0.16621367 | J22: =F22/E22-1 -> 0.55353561 | K22: =G22/F22-1 -> -0.22839157 | L22: =(G22/C22)^(1/4)-1 -> 0.055849203
B23: Total Liabilities | C23: ='9. Standardlized_Income'!H26 -> 7114.9 | D23: ='9. Standardlized_Income'!G26 -> 7282.4 | E23: ='9. Standardlized_Income'!F26 -> 7037.8 | F23: ='9. Standardlized_Income'!E26 -> 8962.3 | G23: ='9. Standardlized_Income'!D26 -> 8151.5 | H23: =D23/C23-1 -> 0.023542144 | I23: =E23/D23-1 -> -0.033587828 | J23: =F23/E23-1 -> 0.27345193 | K23: =G23/F23-1 -> -0.090467849 | L23: =(G23/C23)^(1/4)-1 -> 0.034587396
B24: Total Debt | C24: ='9. Standardlized_Income'!H31 -> 3975.9 | D24: ='9. Standardlized_Income'!G31 -> 4032.8 | E24: ='9. Standardlized_Income'!F31 -> 3906.9 | F24: ='9. Standardlized_Income'!E31 -> 5327.8 | G24: ='9. Standardlized_Income'!D31 -> 4372.9 | H24: =D24/C24-1 -> 0.014311225 | I24: =E24/D24-1 -> -0.031219004 | J24: =F24/E24-1 -> 0.36368988 | K24: =G24/F24-1 -> -0.1792297 | L24: =(G24/C24)^(1/4)-1 -> 0.024079148
B25: Total Equity | C25: ='9. Standardlized_Income'!H30 -> 6567.7 | D25: ='9. Standardlized_Income'!G30 -> 6952.2 | E25: ='9. Standardlized_Income'!F30 -> 7507.9 | F25: ='9. Standardlized_Income'!E30 -> 8142.5 | G25: ='9. Standardlized_Income'!D30 -> 8548.9 | H25: =D25/C25-1 -> 0.058544087 | I25: =E25/D25-1 -> 0.079931532 | J25: =F25/E25-1 -> 0.084524301 | K25: =G25/F25-1 -> 0.049910961 | L25: =(G25/C25)^(1/4)-1 -> 0.068130294
B26: Working Capital | C26: =C18-C22 -> 927.3 | D26: =D18-D22 -> 945.4 | E26: =E18-E22 -> 1727.3 | F26: =F18-F22 -> 1026.6 | G26: =G18-G22 -> 1611.8 | H26: =D26/C26-1 -> 0.019519034 | I26: =E26/D26-1 -> 0.82705733 | J26: =F26/E26-1 -> -0.40566202 | K26: =G26/F26-1 -> 0.57003702 | L26: =(G26/C26)^(1/4)-1 -> 0.1482137
B28: Cash Flow
B29: Operating Cash Flow | C29: ='9. Standardlized_Income'!H51 -> 1011.9 | D29: ='9. Standardlized_Income'!G51 -> 1148.2 | E29: ='9. Standardlized_Income'!F51 -> 1536.8 | F29: ='9. Standardlized_Income'!E51 -> 1409.6 | G29: ='9. Standardlized_Income'!D51 -> 1813 | H29: =D29/C29-1 -> 0.1346971 | I29: =E29/D29-1 -> 0.33844278 | J29: =F29/E29-1 -> -0.082769391 | K29: =G29/F29-1 -> 0.28618048 | L29: =(G29/C29)^(1/4)-1 -> 0.15695123
B30: Capital Expenditures | C30: ='9. Standardlized_Income'!H52 -> 451.3 | D30: ='9. Standardlized_Income'!G52 -> 612.6 | E30: ='9. Standardlized_Income'!F52 -> 872.6 | F30: ='9. Standardlized_Income'!E52 -> 603.5 | G30: ='9. Standardlized_Income'!D52 -> 677.7 | H30: =D30/C30-1 -> 0.35741192 | I30: =E30/D30-1 -> 0.4244205 | J30: =F30/E30-1 -> -0.30838872 | K30: =G30/F30-1 -> 0.12294946 | L30: =(G30/C30)^(1/4)-1 -> 0.10698832
B31: Free Cash Flow | C31: =C29-C30 -> 560.6 | D31: =D29-D30 -> 535.6 | E31: =E29-E30 -> 664.2 | F31: =F29-F30 -> 806.1 | G31: =G29-G30 -> 1135.3 | H31: =D31/C31-1 -> -0.044595077 | I31: =E31/D31-1 -> 0.24010456 | J31: =F31/E31-1 -> 0.21364047 | K31: =G31/F31-1 -> 0.40838606 | L31: =(G31/C31)^(1/4)-1 -> 0.19292842
B33: Vertical Analysis
B34: Income Staetement ( % of Revenue) | H34: Peer Vertical Analysis (FY2025)
B35: Metrics / Year | C35: 2021 | D35: 2022 | E35: 2023 | F35: 2024 | G35: 2025 | H35: MLM | I35: KNF | J35: CRH | K35: CX | L35: EXP
B36: Revenue | C36: =100% -> 1 | D36: =100% -> 1 | E36: =100% -> 1 | F36: =100% -> 1 | G36: =100% -> 1 | H36: 1 | I36: 1 | J36: 1 | K36: 1 | L36: 1
B37: Cost of Revenues | C37: =C6/$C$5 -> 0.75263859 | D37: =D6/D$5 -> 0.78705982 | E37: =E6/E$5 -> 0.74961128 | F37: =F6/F$5 -> 0.73042857 | G37: =G6/G$5 -> 0.72615884 | H37: ='9. Standardlized_Income'!J35/'9. Standardlized_Income'!J34 -> 0.69284553 | I37: ='9. Standardlized_Income'!L35/'9. Standardlized_Income'!L34 -> 0.81648819 | J37: ='9. Standardlized_Income'!N35/'9. Standardlized_Income'!N34 -> 0.63874276 | K37: ='9. Standardlized_Income'!P35/'9. Standardlized_Income'!P34 -> 0.6708065 | L37: ='9. Standardlized_Income'!R35/'9. Standardlized_Income'!R34 -> 0.70221764
B38: Gross Profit | C38: =C7/$C$5 -> 0.24736141 | D38: =D7/$D$5 -> 0.21294018 | E38: =E7/E$5 -> 0.25038872 | F38: =F7/F$5 -> 0.26957143 | G38: =G7/G$5 -> 0.27384116 | H38: ='9. Standardlized_Income'!J36/'9. Standardlized_Income'!J34 -> 0.30715447 | I38: ='9. Standardlized_Income'!L36/'9. Standardlized_Income'!L34 -> 0.18351181 | J38: ='9. Standardlized_Income'!N36/'9. Standardlized_Income'!N34 -> 0.36125724 | K38: ='9. Standardlized_Income'!P36/'9. Standardlized_Income'!P34 -> 0.3291935 | L38: ='9. Standardlized_Income'!R36/'9. Standardlized_Income'!R34 -> 0.29778236
B39: SG&A | C39: =C8/$C$5 -> 0.075213429 | D39: =D8/$D$5 -> 0.070415026 | E39: =E8/E$5 -> 0.069751603 | F39: =F8/F$5 -> 0.071599013 | G39: =G8/G$5 -> 0.071035499 | H39: ='9. Standardlized_Income'!J37/'9. Standardlized_Income'!J34 -> 0.07203252 | I39: ='9. Standardlized_Income'!L37/'9. Standardlized_Income'!L34 -> 0.089208235 | J39: ='9. Standardlized_Income'!N37/'9. Standardlized_Income'!N34 -> 0.21910968 | K39: ='9. Standardlized_Income'!P37/'9. Standardlized_Income'!P34 -> 0.2182864 | L39: ='9. Standardlized_Income'!R37/'9. Standardlized_Income'!R34 -> 0.032709433
B40: Other Operating (Income) / Expense | C40: =C9/$C$5 -> -0.0028637297 | D40: =D9/$D$5 -> 0.0017907918 | E40: =E9/E$5 -> 0.010730027 | F40: =F9/F$5 -> 0.0097604379 | G40: =G9/G$5 -> 0.010464545 | H40: ='9. Standardlized_Income'!J38/'9. Standardlized_Income'!J34 -> -0.0076422764 | I40: ='9. Standardlized_Income'!L38/'9. Standardlized_Income'!L34 -> -0.00025429036 | J40: ='9. Standardlized_Income'!N38/'9. Standardlized_Income'!N34 -> 0 | K40: ='9. Standardlized_Income'!P38/'9. Standardlized_Income'!P34 -> 0.048617396 | L40: ='9. Standardlized_Income'!R38/'9. Standardlized_Income'!R34 -> -0.0028400671
B41: EBITDA Margin | C41: =C10/$C$5 -> 0.25840207 | D41: =D10/$D$5 -> 0.22104659 | E41: =E10/E$5 -> 0.24919364 | F41: =F10/F$5 -> 0.27344055 | G41: =G10/G$5 -> 0.28659757 | H41: ='9. Standardlized_Income'!J46/'9. Standardlized_Income'!J34 -> 0.34634146 | I41: ='9. Standardlized_Income'!L46/'9. Standardlized_Income'!L34 -> 0.15613746 | J41: ='9. Standardlized_Income'!N46/'9. Standardlized_Income'!N34 -> 0.19972227 | K41: ='9. Standardlized_Income'!P46/'9. Standardlized_Income'!P34 -> 0.14231323 | L41: ='9. Standardlized_Income'!R46/'9. Standardlized_Income'!R34 -> 0.33820686
B42: EBIT Margin | C42: =C11/$C$5 -> 0.17501171 | D42: =D11/$D$5 -> 0.14073436 | E42: =E11/E$5 -> 0.16990709 | F42: =F11/F$5 -> 0.18821198 | G42: =G11/G$5 -> 0.19234111 | H42: ='9. Standardlized_Income'!J39/'9. Standardlized_Income'!J34 -> 0.24276423 | I42: ='9. Standardlized_Income'!L39/'9. Standardlized_Income'!L34 -> 0.09455469 | J42: ='9. Standardlized_Income'!N39/'9. Standardlized_Income'!N34 -> 0.14214757 | K42: ='9. Standardlized_Income'!P39/'9. Standardlized_Income'!P34 -> 0.062289702 | L42: ='9. Standardlized_Income'!R39/'9. Standardlized_Income'!R34 -> 0.26791299
B43: Net Income Margin | C43: =C12/$C$5 -> 0.12081697 | D43: =D12/$D$5 -> 0.078685477 | E43: =E12/E$5 -> 0.1199193 | F43: =F12/F$5 -> 0.12293568 | G43: =G12/G$5 -> 0.13558575 | H43: ='9. Standardlized_Income'!J44/'9. Standardlized_Income'!J34 -> 0.18487805 | I43: ='9. Standardlized_Income'!L44/'9. Standardlized_Income'!L34 -> 0.049926733 | J43: ='9. Standardlized_Income'!N44/'9. Standardlized_Income'!N34 -> 0.10022165 | K43: ='9. Standardlized_Income'!P44/'9. Standardlized_Income'!P34 -> 0.059519411 | L43: ='9. Standardlized_Income'!R44/'9. Standardlized_Income'!R34 -> 0.20500683
B45: Cash & ST Investments | C45: =C15/$C$20 -> 0.017175098 | D45: =D15/D$20 -> 0.011338569 | E45: =E15/E$20 -> 0.064012045 | F45: =F15/F$20 -> 0.032721809 | G45: =G15/G$20 -> 0.010975785 | H45: ='9. Standardlized_Income'!J8/'9. Standardlized_Income'!J17 -> 0.0035807814 | I45: ='9. Standardlized_Income'!L8/'9. Standardlized_Income'!L17 -> 0.03381268 | J45: ='9. Standardlized_Income'!N8/'9. Standardlized_Income'!N17 -> 0.070222359 | K45: ='9. Standardlized_Income'!P8/'9. Standardlized_Income'!P17 -> 0.068221481 | L45: ='9. Standardlized_Income'!R8/'9. Standardlized_Income'!R17 -> 0.0062488705
B46: Receivables | C46: =C16/$C$20 -> 0.057240583 | D46: =D16/D$20 -> 0.059404549 | E46: =E16/E$20 -> 0.061165843 | F46: =F16/F$20 -> 0.052166643 | G46: =G16/G$20 -> 0.053154415 | H46: ='9. Standardlized_Income'!J9/'9. Standardlized_Income'!J17 -> 0.037838705 | I46: ='9. Standardlized_Income'!L9/'9. Standardlized_Income'!L17 -> 0.041272729 | J46: ='9. Standardlized_Income'!N9/'9. Standardlized_Income'!N17 -> 0.088772309 | K46: ='9. Standardlized_Income'!P9/'9. Standardlized_Income'!P17 -> 0.061089896 | L46: ='9. Standardlized_Income'!R9/'9. Standardlized_Income'!R17 -> 0.065040327
B47: Inventory | C47: =C17/$C$20 -> 0.038099484 | D47: =D17/D$20 -> 0.040696612 | E47: =E17/E$20 -> 0.042321786 | F47: =F17/F$20 -> 0.039860156 | G47: =G17/G$20 -> 0.040747527 | H47: ='9. Standardlized_Income'!J10/'9. Standardlized_Income'!J17 -> 0.057613169 | I47: ='9. Standardlized_Income'!L10/'9. Standardlized_Income'!L17 -> 0.11936901 | J47: ='9. Standardlized_Income'!N10/'9. Standardlized_Income'!N17 -> 0.09002383 | K47: ='9. Standardlized_Income'!P10/'9. Standardlized_Income'!P17 -> 0.052557335 | L47: ='9. Standardlized_Income'!R10/'9. Standardlized_Income'!R17 -> 0.12717677
B48: Current Assets | C48: =C18/$C$20 -> 0.1239969 | D48: =D18/D$20 -> 0.13361809 | E48: =E18/E$20 -> 0.17358395 | F48: =F18/F$20 -> 0.13245989 | G48: =G18/G$20 -> 0.15376278 | H48: ='9. Standardlized_Income'!J12/'9. Standardlized_Income'!J17 -> 0.17064828 | I48: ='9. Standardlized_Income'!L12/'9. Standardlized_Income'!L17 -> 0.26325782 | J48: ='9. Standardlized_Income'!N12/'9. Standardlized_Income'!N17 -> 0.26151657 | K48: ='9. Standardlized_Income'!P12/'9. Standardlized_Income'!P17 -> 0.21048378 | L48: ='9. Standardlized_Income'!R12/'9. Standardlized_Income'!R17 -> 0.20482205
B49: PP&E, net | C49: =C19/$C$20 -> 0.45592212 | D49: =D19/D$20 -> 0.46533798 | E49: =E19/E$20 -> 0.46263844 | F49: =F19/F$20 -> 0.52546069 | G49: =G19/G$20 -> 0.51915523 | H49: ='9. Standardlized_Income'!J13/'9. Standardlized_Income'!J17 -> 0.56955801 | I49: ='9. Standardlized_Income'!L13/'9. Standardlized_Income'!L17 -> 0.57026227 | J49: ='9. Standardlized_Income'!N13/'9. Standardlized_Income'!N17 -> 0.4527422 | K49: ='9. Standardlized_Income'!P13/'9. Standardlized_Income'!P17 -> 0.42010274 | L49: ='9. Standardlized_Income'!R13/'9. Standardlized_Income'!R17 -> 0.5582018
B50: Total Assets | C50: 1 | D50: 1 | E50: =E20/E$20 -> 1 | F50: =F20/F$20 -> 1 | G50: =G20/G$20 -> 1 | H50: 1 | I50: 1 | J50: 1 | K50: 1 | L50: 1
B51: Payables | C51: =C21/$C$20 -> 0.026712759 | D51: =D21/D$20 -> 0.031929243 | E51: =E21/E$20 -> 0.026839547 | F51: =F21/F$20 -> 0.02379449 | G51: =G21/G$20 -> 0.026256856 | H51: ='9. Standardlized_Income'!J19/'9. Standardlized_Income'!J17 -> 0.02078991 | I51: ='9. Standardlized_Income'!L19/'9. Standardlized_Income'!L17 -> 0.03988373 | J51: ='9. Standardlized_Income'!N19/'9. Standardlized_Income'!N17 -> 0.055941298 | K51: ='9. Standardlized_Income'!P19/'9. Standardlized_Income'!P17 -> 0.10729623 | L51: ='9. Standardlized_Income'!R19/'9. Standardlized_Income'!R17 -> 0.039790602
B52: Current Liabilities | C52: =C22/$C$20 -> 0.056224694 | D52: =D22/D$20 -> 0.06720245 | E52: =E22/E$20 -> 0.054834075 | F52: =F22/F$20 -> 0.072441654 | G52: =G22/G$20 -> 0.057250126 | H52: ='9. Standardlized_Income'!J22/'9. Standardlized_Income'!J17 -> 0.047832826 | I52: ='9. Standardlized_Income'!L22/'9. Standardlized_Income'!L17 -> 0.10355578 | J52: ='9. Standardlized_Income'!N22/'9. Standardlized_Income'!N17 -> 0.15007972 | K52: ='9. Standardlized_Income'!P22/'9. Standardlized_Income'!P17 -> 0.2549111 | L52: ='9. Standardlized_Income'!R22/'9. Standardlized_Income'!R17 -> 0.075047709
B53: Total Liabilities | C53: =C23/$C$20 -> 0.5199962 | D53: =D23/D$20 -> 0.5115985 | E53: =E23/E$20 -> 0.48384059 | F53: =F23/F$20 -> 0.52396403 | G53: =G23/G$20 -> 0.48810208 | H53: ='9. Standardlized_Income'!J26/'9. Standardlized_Income'!J17 -> 0.46373791 | I53: ='9. Standardlized_Income'!L26/'9. Standardlized_Income'!L17 -> 0.55044095 | J53: ='9. Standardlized_Income'!N26/'9. Standardlized_Income'!N17 -> 0.57057381 | K53: ='9. Standardlized_Income'!P26/'9. Standardlized_Income'!P17 -> 0.5297276 | L53: ='9. Standardlized_Income'!R26/'9. Standardlized_Income'!R17 -> 0.55378777
B54: Total Debt | C54: =C24/$C$20 -> 0.29058074 | D54: =D24/D$20 -> 0.28330968 | E54: =E24/E$20 -> 0.26859484 | F54: =F24/F$20 -> 0.31147982 | G54: =G24/G$20 -> 0.26184403 | H54: ='9. Standardlized_Income'!J31/'9. Standardlized_Income'!J17 -> 0.3006253 | I54: ='9. Standardlized_Income'!L31/'9. Standardlized_Income'!L17 -> 0.3193164 | J54: ='9. Standardlized_Income'!N31/'9. Standardlized_Income'!N17 -> 0.31180031 | K54: ='9. Standardlized_Income'!P31/'9. Standardlized_Income'!P17 -> 0.23407114 | L54: ='9. Standardlized_Income'!R31/'9. Standardlized_Income'!R17 -> 0.37931869
B55: Total Equity | C55: =C25/$C$20 -> 0.4800038 | D55: =D25/D$20 -> 0.4884015 | E55: =E25/E$20 -> 0.51615941 | F55: =F25/F$20 -> 0.47603597 | G55: =G25/G$20 -> 0.51189792 | H55: ='9. Standardlized_Income'!J30/'9. Standardlized_Income'!J17 -> 0.53626209 | I55: ='9. Standardlized_Income'!L30/'9. Standardlized_Income'!L17 -> 0.44955905 | J55: ='9. Standardlized_Income'!N30/'9. Standardlized_Income'!N17 -> 0.42942619 | K55: ='9. Standardlized_Income'!P30/'9. Standardlized_Income'!P17 -> 0.4702724 | L55: ='9. Standardlized_Income'!R30/'9. Standardlized_Income'!R17 -> 0.44621223
B56: Working Capital | C56: =C26/$C$5 -> 0.16701488 | D56: =D26/D$20 -> 0.066415635 | E56: =E26/E$20 -> 0.11874987 | F56: =F26/F$20 -> 0.06001824 | G56: =G26/G$20 -> 0.096512658 | H56: =('9. Standardlized_Income'!J12-'9. Standardlized_Income'!J22)/'9. Standardlized_Income'!J17 -> 0.12281546 | I56: =('9. Standardlized_Income'!L12-'9. Standardlized_Income'!L22)/'9. Standardlized_Income'!L17 -> 0.15970204 | J56: =('9. Standardlized_Income'!N12-'9. Standardlized_Income'!N22)/'9. Standardlized_Income'!N17 -> 0.11143685 | K56: =('9. Standardlized_Income'!P12-'9. Standardlized_Income'!P22)/'9. Standardlized_Income'!P17 -> -0.044427321 | L56: =('9. Standardlized_Income'!R12-'9. Standardlized_Income'!R22)/'9. Standardlized_Income'!R17 -> 0.12977434
B58: Ratio Analysis
B59: Metrics | C59: 2021 | D59: 2022 | E59: 2023 | F59: 2024 | G59: Y2025 | H59: MLM | I59: KNF | J59: CRH | K59: CX | L59: EXP | M59: Median | N59: VMC Rank
B60: Liquidity | H60: FY2025 | I60: FY2025 | J60: FY2025 | K60: FY2025 | L60: FY Mar-25
B61: Current Ratio | C61: =C18/C22 -> 2.2053815 | D61: =D18/D22 -> 1.9882919 | E61: =E18/E22 -> 3.1656219 | F61: =F18/F22 -> 1.8285046 | G61: =G18/G22 -> 2.6858069 | H61: ='9. Standardlized_Income'!J12/'9. Standardlized_Income'!J22 -> 3.5675978 | I61: ='9. Standardlized_Income'!L12/'9. Standardlized_Income'!L22 -> 2.5421837 | J61: ='9. Standardlized_Income'!N12/'9. Standardlized_Income'!N22 -> 1.7425177 | K61: ='9. Standardlized_Income'!P12/'9. Standardlized_Income'!P22 -> 0.82571445 | L61: ='9. Standardlized_Income'!R12/'9. Standardlized_Income'!R22 -> 2.7292245 | M61: =MEDIAN(G61:K61) -> 2.5421837 | N61: =RANK(G61,G61:L61,0) -> 3
B62: Quick Ratio | C62: =(C18-C17)/C22 -> 1.5277525 | D62: =(D18-D17)/D22 -> 1.3827096 | E62: =(E18-E17)/E22 -> 2.3938064 | F62: =(F18-F17)/F22 -> 1.2782665 | G62: =(G18-G17)/G22 -> 1.9740613 | H62: =('9. Standardlized_Income'!J12-'9. Standardlized_Income'!J10)/'9. Standardlized_Income'!J22 -> 2.3631285 | I62: =('9. Standardlized_Income'!L12-'9. Standardlized_Income'!L10)/'9. Standardlized_Income'!L22 -> 1.3894812 | J62: =('9. Standardlized_Income'!N12-'9. Standardlized_Income'!N10)/'9. Standardlized_Income'!N22 -> 1.1426776 | K62: =('9. Standardlized_Income'!P12-'9. Standardlized_Income'!P10)/'9. Standardlized_Income'!P22 -> 0.61953538 | L62: =('9. Standardlized_Income'!R12-'9. Standardlized_Income'!R10)/'9. Standardlized_Income'!R22 -> 1.0346122 | M62: =MEDIAN(G62:K62) -> 1.3894812 | N62: =RANK(G62,G62:L62,0) -> 2
B63: Cash Ratio | C63: =C15/C22 -> 0.30547251 | D63: =D15/D22 -> 0.16872256 | E63: =E15/E22 -> 1.1673771 | F63: =F15/F22 -> 0.45169881 | G63: =G15/G22 -> 0.19171635 | H63: ='9. Standardlized_Income'!J8/'9. Standardlized_Income'!J22 -> 0.074860335 | I63: ='9. Standardlized_Income'!L8/'9. Standardlized_Income'!L22 -> 0.32651657 | J63: ='9. Standardlized_Income'!N8/'9. Standardlized_Income'!N22 -> 0.46790039 | K63: ='9. Standardlized_Income'!P8/'9. Standardlized_Income'!P22 -> 0.26762852 | L63: ='9. Standardlized_Income'!R8/'9. Standardlized_Income'!R22 -> 0.083265306 | M63: =MEDIAN(G63:K63) -> 0.26762852 | N63: =RANK(G63,G63:L63,0) -> 4
B64: Working Capital | C64: =C18-C22 -> 927.3 | D64: =D18-D22 -> 945.4 | E64: =E18-E22 -> 1727.3 | F64: =F18-F22 -> 1026.6 | G64: =G18-G22 -> 1611.8 | H64: ='9. Standardlized_Income'!J12-'9. Standardlized_Income'!J22 -> 2298 | I64: ='9. Standardlized_Income'!L12-'9. Standardlized_Income'!L22 -> 582.93 | J64: ='9. Standardlized_Income'!N12-'9. Standardlized_Income'!N22 -> 6500 | K64: ='9. Standardlized_Income'!P12-'9. Standardlized_Income'!P22 -> -1286.86 | L64: ='9. Standardlized_Income'!R12-'9. Standardlized_Income'!R22 -> 423.66 | M64: =MEDIAN(G64:G64) -> 1611.8 | N64: =RANK(G64,G64:L64,0) -> 3
B65: Operating Cash Flow Ratio | C65: =C29/C22 -> 1.3153516 | D65: =D29/D22 -> 1.2002927 | E65: =E29/E22 -> 1.9267803 | F65: =F29/F22 -> 1.1375999 | G65: =G29/G22 -> 1.8962452 | H65: ='9. Standardlized_Income'!J51/'9. Standardlized_Income'!J22 -> 1.9944134 | I65: ='9. Standardlized_Income'!L51/'9. Standardlized_Income'!L22 -> 0.73673907 | J65: ='9. Standardlized_Income'!N51/'9. Standardlized_Income'!N22 -> 0.6425634 | K65: ='9. Standardlized_Income'!P51/'9. Standardlized_Income'!P22 -> 0.27868271 | L65: ='9. Standardlized_Income'!R51/'9. Standardlized_Income'!R22 -> 2.2389796 | M65: =MEDIAN(G65:G65) -> 1.8962452 | N65: =RANK(G65,G65:L65,0) -> 3
B66: Profitability
B67: EBITDA Margin | C67: =C41 -> 0.25840207 | D67: =D41 -> 0.22104659 | E67: =E41 -> 0.24919364 | F67: =F41 -> 0.27344055 | G67: =G41 -> 0.28659757 | H67: ='9. Standardlized_Income'!J46/'9. Standardlized_Income'!J34 -> 0.34634146 | I67: ='9. Standardlized_Income'!L46/'9. Standardlized_Income'!L34 -> 0.15613746 | J67: ='9. Standardlized_Income'!N46/'9. Standardlized_Income'!N34 -> 0.19972227 | K67: ='9. Standardlized_Income'!P46/'9. Standardlized_Income'!P34 -> 0.14231323 | L67: ='9. Standardlized_Income'!R46/'9. Standardlized_Income'!R34 -> 0.33820686 | M67: =MEDIAN(G67:L67) -> 0.24315992 | N67: =RANK(G67,G67:L67,0) -> 3
B68: Net Profit Margin | C68: =C12/C5 -> 0.12081697 | D68: =D12/D5 -> 0.078685477 | E68: =E12/E5 -> 0.1199193 | F68: =F12/F5 -> 0.12293568 | G68: =G12/G5 -> 0.13558575 | H68: ='9. Standardlized_Income'!J44/'9. Standardlized_Income'!J34 -> 0.18487805 | I68: ='9. Standardlized_Income'!L44/'9. Standardlized_Income'!L34 -> 0.049926733 | J68: ='9. Standardlized_Income'!N44/'9. Standardlized_Income'!N34 -> 0.10022165 | K68: ='9. Standardlized_Income'!P44/'9. Standardlized_Income'!P34 -> 0.059519411 | L68: ='9. Standardlized_Income'!R44/'9. Standardlized_Income'!R34 -> 0.20500683 | M68: =MEDIAN(G68:L68) -> 0.1179037 | N68: =RANK(G68,G68:L68,0) -> 3
B69: Operating Profit Margin | C69: =C11/C5 -> 0.17501171 | D69: =D11/D5 -> 0.14073436 | E69: =E11/E5 -> 0.16990709 | F69: =F11/F5 -> 0.18821198 | G69: =G11/G5 -> 0.19234111 | H69: ='9. Standardlized_Income'!J39/'9. Standardlized_Income'!J34 -> 0.24276423 | I69: ='9. Standardlized_Income'!L39/'9. Standardlized_Income'!L34 -> 0.09455469 | J69: ='9. Standardlized_Income'!N39/'9. Standardlized_Income'!N34 -> 0.14214757 | K69: ='9. Standardlized_Income'!P39/'9. Standardlized_Income'!P34 -> 0.062289702 | L69: ='9. Standardlized_Income'!R39/'9. Standardlized_Income'!R34 -> 0.26791299 | M69: =MEDIAN(G69:L69) -> 0.16724434 | N69: =RANK(G69,G69:L69,0) -> 3
B70: ROIC | C70: =C11*(1-'9. Standardlized_Income'!H43/'9. Standardlized_Income'!H42)/(C24+C25) -> 0.071055514 | D70: =D11*(1-'9. Standardlized_Income'!G43/'9. Standardlized_Income'!G42)/(D24+D25) -> 0.070767673 | E70: =E11*(1-'9. Standardlized_Income'!F43/'9. Standardlized_Income'!F42)/(E24+E25) -> 0.087978794 | F70: =F11*(1-'9. Standardlized_Income'!E43/'9. Standardlized_Income'!E42)/(F24+F25) -> 0.081412808 | G70: =G11*(1-'9. Standardlized_Income'!D43/'9. Standardlized_Income'!D42)/(G24+G25) -> 0.092055926 | H70: ='9. Standardlized_Income'!J39*(1-'9. Standardlized_Income'!J43/'9. Standardlized_Income'!J42)/('9. Standardlized_Income'!J31+'9. Standardlized_Income'!J30) -> 0.076991097 | I70: ='9. Standardlized_Income'!L39*(1-'9. Standardlized_Income'!L43/'9. Standardlized_Income'!L42)/('9. Standardlized_Income'!L31+'9. Standardlized_Income'!L30) -> 0.078084871 | J70: ='9. Standardlized_Income'!N39*(1-'9. Standardlized_Income'!N43/'9. Standardlized_Income'!N42)/('9. Standardlized_Income'!N31+'9. Standardlized_Income'!N30) -> 0.096444447 | K70: ='9. Standardlized_Income'!P39*(1-'9. Standardlized_Income'!P43/'9. Standardlized_Income'!P42)/('9. Standardlized_Income'!P31+'9. Standardlized_Income'!P30) -> 0.025229731 | L70: ='9. Standardlized_Income'!R39*(1-'9. Standardlized_Income'!R43/'9. Standardlized_Income'!R42)/('9. Standardlized_Income'!R31+'9. Standardlized_Income'!R30) -> 0.17606198 | M70: =MEDIAN(G70:L70) -> 0.085070398 | N70: =RANK(G70,G70:L70,0) -> 3
B71: ROA | C71: =C12/C20 -> 0.04902577 | D71: =D12/D20 -> 0.040436682 | E71: =E12/E20 -> 0.064156417 | F71: =F12/F20 -> 0.05331252 | G71: =G12/G20 -> 0.06447151 | H71: ='9. Standardlized_Income'!J44/'9. Standardlized_Income'!J17 -> 0.060766394 | I71: ='9. Standardlized_Income'!L44/'9. Standardlized_Income'!L17 -> 0.04303158 | J71: ='9. Standardlized_Income'!N44/'9. Standardlized_Income'!N17 -> 0.064341923 | K71: ='9. Standardlized_Income'!P44/'9. Standardlized_Income'!P17 -> 0.033148389 | L71: ='9. Standardlized_Income'!R44/'9. Standardlized_Income'!R17 -> 0.14195351 | M71: =MEDIAN(G71:L71) -> 0.062554158 | N71: =RANK(G71,G71:L71,0) -> 2
B72: ROE | C72: =C12/C25 -> 0.10213621 | D72: =D12/D25 -> 0.082793936 | E72: =E12/E25 -> 0.12429574 | F72: =F12/F25 -> 0.11199263 | G72: =G12/G25 -> 0.12594603 | H72: ='9. Standardlized_Income'!J44/'9. Standardlized_Income'!J30 -> 0.11331473 | I72: ='9. Standardlized_Income'!L44/'9. Standardlized_Income'!L30 -> 0.095719527 | J72: ='9. Standardlized_Income'!N44/'9. Standardlized_Income'!N30 -> 0.14983232 | K72: ='9. Standardlized_Income'!P44/'9. Standardlized_Income'!P30 -> 0.070487634 | L72: ='9. Standardlized_Income'!R44/'9. Standardlized_Income'!R30 -> 0.31813002 | M72: =MEDIAN(G72:L72) -> 0.11963038 | N72: =RANK(G72,G72:L72,0) -> 3
B73: Solvency
B74: Debt-to-Equity Ratio | C74: =C24/C25 -> 0.60537174 | D74: =D24/D25 -> 0.58007537 | E74: =E24/E25 -> 0.52037187 | F74: =F24/F25 -> 0.65431993 | G74: =G24/G25 -> 0.5115161 | H74: ='9. Standardlized_Income'!J31/'9. Standardlized_Income'!J30 -> 0.56059398 | I74: ='9. Standardlized_Income'!L31/'9. Standardlized_Income'!L30 -> 0.71028801 | J74: ='9. Standardlized_Income'!N31/'9. Standardlized_Income'!N30 -> 0.72608592 | K74: ='9. Standardlized_Income'!P31/'9. Standardlized_Income'!P30 -> 0.49773523 | L74: ='9. Standardlized_Income'!R31/'9. Standardlized_Income'!R30 -> 0.85008581 | M74: =MEDIAN(G74:L74) -> 0.63544099 | N74: =RANK(G74,G74:L74,0) -> 5
B75: Debt-to-Asset Ratio | C75: =C24/C20 -> 0.29058074 | D75: =D24/D20 -> 0.28330968 | E75: =E24/E20 -> 0.26859484 | F75: =F24/F20 -> 0.31147982 | G75: =G24/G20 -> 0.26184403 | H75: ='9. Standardlized_Income'!J31/'9. Standardlized_Income'!J17 -> 0.3006253 | I75: ='9. Standardlized_Income'!L31/'9. Standardlized_Income'!L17 -> 0.3193164 | J75: ='9. Standardlized_Income'!N31/'9. Standardlized_Income'!N17 -> 0.31180031 | K75: ='9. Standardlized_Income'!P31/'9. Standardlized_Income'!P17 -> 0.23407114 | L75: ='9. Standardlized_Income'!R31/'9. Standardlized_Income'!R17 -> 0.37931869 | M75: =MEDIAN(G75:L75) -> 0.3062128 | N75: =RANK(G75,G75:L75,0) -> 5
B76: Debt-to-Capital | C76: =C24/(C24+C25) -> 0.37709132 | D76: =D24/(D24+D25) -> 0.3671188 | E76: =E24/(E24+E25) -> 0.34226618 | F76: =F24/(F24+F25) -> 0.395522 | G76: =G24/(G24+G25) -> 0.33841261 | H76: ='9. Standardlized_Income'!J31/('9. Standardlized_Income'!J31+'9. Standardlized_Income'!J30) -> 0.35921834 | I76: ='9. Standardlized_Income'!L31/('9. Standardlized_Income'!L31+'9. Standardlized_Income'!L30) -> 0.41530316 | J76: ='9. Standardlized_Income'!N31/('9. Standardlized_Income'!N31+'9. Standardlized_Income'!N30) -> 0.42065456 | K76: ='9. Standardlized_Income'!P31/('9. Standardlized_Income'!P31+'9. Standardlized_Income'!P30) -> 0.33232525 | L76: ='9. Standardlized_Income'!R31/('9. Standardlized_Income'!R31+'9. Standardlized_Income'!R30) -> 0.45948453 | M76: =MEDIAN(G76:L76) -> 0.38726075 | N76: =RANK(G76,G76:L76,0) -> 5
B77: Interest Coverage Ratio | C77: =C11/'9. Standardlized_Income'!H40 -> 6.5083724 | D77: =D11/'9. Standardlized_Income'!G40 -> 6.0845154 | E77: =E11/'9. Standardlized_Income'!F40 -> 6.7424783 | F77: =F11/'9. Standardlized_Income'!E40 -> 7.3017782 | G77: =G11/'9. Standardlized_Income'!D40 -> 6.3721318 | H77: ='9. Standardlized_Income'!J39/'9. Standardlized_Income'!J40 -> 6.4913043 | I77: ='9. Standardlized_Income'!L39/'9. Standardlized_Income'!L40 -> 3.6303393 | J77: ='9. Standardlized_Income'!N39/'9. Standardlized_Income'!N40 -> 6.5716049 | K77: ='9. Standardlized_Income'!P39/'9. Standardlized_Income'!P40 -> 3.3408139 | L77: ='9. Standardlized_Income'!R39/'9. Standardlized_Income'!R40 -> 15.050199 | M77: =MEDIAN(G77:L77) -> 6.4317181 | N77: =RANK(G77,G77:L77,0) -> 4
B78: Efficiency
B79: Asset Turnover | C79: =C5/C20 -> 0.40578545 | D79: =D5/D20 -> 0.51390274 | E79: =E5/E20 -> 0.5349966 | F79: =F5/F20 -> 0.4336619 | G79: =G5/G20 -> 0.47550358 | H79: ='9. Standardlized_Income'!J34/'9. Standardlized_Income'!J17 -> 0.32868366 | I79: ='9. Standardlized_Income'!L34/'9. Standardlized_Income'!L17 -> 0.86189457 | J79: ='9. Standardlized_Income'!N34/'9. Standardlized_Income'!N17 -> 0.64199626 | K79: ='9. Standardlized_Income'!P34/'9. Standardlized_Income'!P17 -> 0.55693409 | L79: ='9. Standardlized_Income'!R34/'9. Standardlized_Income'!R17 -> 0.69243305 | M79: =MEDIAN(G79:L79) -> 0.59946518 | N79: =RANK(G79,G79:L79,0) -> 5
B80: Fixed Asset Turnover | C80: =C5/C19 -> 0.89003238 | D80: =D5/D19 -> 1.1043645 | E80: =E5/E19 -> 1.1564032 | F80: =F5/F19 -> 0.82529846 | G80: =G5/G19 -> 0.91591792 | H80: ='9. Standardlized_Income'!J34/'9. Standardlized_Income'!J13 -> 0.57708548 | I80: ='9. Standardlized_Income'!L34/'9. Standardlized_Income'!L13 -> 1.5114003 | J80: ='9. Standardlized_Income'!N34/'9. Standardlized_Income'!N13 -> 1.4180173 | K80: ='9. Standardlized_Income'!P34/'9. Standardlized_Income'!P13 -> 1.3257093 | L80: ='9. Standardlized_Income'!R34/'9. Standardlized_Income'!R13 -> 1.2404708 | M80: =MEDIAN(G80:L80) -> 1.2830901 | N80: =RANK(G80,G80:L80,0) -> 5
B81: Receivables Days | C81: =C16/C5*365 -> 51.487338 | D81: =D16/D5*365 -> 42.192148 | E81: =E16/E5*365 -> 41.730233 | F81: =F16/F5*365 -> 43.907074 | G81: =G16/G5*365 -> 40.801715 | H81: ='9. Standardlized_Income'!J9/'9. Standardlized_Income'!J34*365 -> 42.019512 | I81: ='9. Standardlized_Income'!L9/'9. Standardlized_Income'!L34*365 -> 17.478409 | J81: ='9. Standardlized_Income'!N9/'9. Standardlized_Income'!N34*365 -> 50.470532 | K81: ='9. Standardlized_Income'!P9/'9. Standardlized_Income'!P34*365 -> 40.036716 | L81: ='9. Standardlized_Income'!R9/'9. Standardlized_Income'!R34*365 -> 34.284498 | M81: =MEDIAN(G81:L81) -> 40.419216 | N81: =RANK(G81,G81:L81,0) -> 3
B82: Inventory Days | C82: =C16/C6*365 -> 68.409113 | D82: =D16/D6*365 -> 53.607295 | E82: =E16/E6*365 -> 55.669164 | F82: =F16/F6*365 -> 60.111386 | G82: =G16/G6*365 -> 56.188416 | H82: ='9. Standardlized_Income'!J10/'9. Standardlized_Income'!J35*365 -> 92.342173 | I82: ='9. Standardlized_Income'!L10/'9. Standardlized_Income'!L35*365 -> 61.912792 | J82: ='9. Standardlized_Income'!N10/'9. Standardlized_Income'!N35*365 -> 80.129395 | K82: ='9. Standardlized_Income'!P10/'9. Standardlized_Income'!P35*365 -> 51.348189 | L82: ='9. Standardlized_Income'!R10/'9. Standardlized_Income'!R35*365 -> 95.466526 | M82: =MEDIAN(G82:L82) -> 71.021093 | N82: =RANK(G82,G82:L82,0) -> 5
B83: Payable Days | C83: =C21/C6*365 -> 31.924835 | D83: =D21/D6*365 -> 28.813287 | E83: =E21/E6*365 -> 24.427607 | F83: =F21/F6*365 -> 27.418283 | G83: =G21/G6*365 -> 27.755571 | H83: ='9. Standardlized_Income'!J19/'9. Standardlized_Income'!J35*365 -> 33.32199 | I83: ='9. Standardlized_Income'!L19/'9. Standardlized_Income'!L35*365 -> 20.686384 | J83: ='9. Standardlized_Income'!N19/'9. Standardlized_Income'!N35*365 -> 49.792843 | K83: ='9. Standardlized_Income'!P19/'9. Standardlized_Income'!P35*365 -> 104.82775 | L83: ='9. Standardlized_Income'!R19/'9. Standardlized_Income'!R35*365 -> 29.869218 | M83: =MEDIAN(G83:L83) -> 31.595604 | N83: =RANK(G83,G83:L83,0) -> 5

Sheet 3. Credit_Analysis
B1: Sheet 3 – Credit Analysis | Vulcan Materials Company (VMC)
B3: 1. CREDIT OVERVIEW
B4: Assessment | C4: Rating | D4: Score | E4: Scale | F4: Justification
B5: Business Risk | C5: Low | D5: 2 | E5: 1–5 | F5: Dominant #2 position in US aggregates; irreplaceable, permitted reserves; long asset life; essential-use product with no substitutes
B6: Financial Risk | C6: Low-Moderate | D6: 2 | E6: 1–5 | F6: Debt/EBITDA 1.9x; Net Debt/EBITDA 1.8x; EBITDA/Interest 9.5x; CFO/Debt 41.5% — well within IG thresholds
B7: Liquidity Risk | C7: Strong | D7: 1 | E7: 1–5 | F7: Current Ratio 2.7x; Quick Ratio 2.0x; $183mm cash + $1.6B undrawn revolver; minimal near-term maturities
B8: Cyclicality | C8: Moderate | D8: 3 | E8: 1–5 | F8: Construction-driven demand is cyclical, but mitigated by infrastructure/public spending and pricing power
B9: Industry Position | C9: Strong - #2 US Aggregates | D9: 1 | E9: 1–5 | F9: #2 US aggregates producer; 28.7% EBITDA margin (above median); vertically integrated operations across 25+ states
B10: Overall Credit View | C10: Investment Grade | D10: Avg: 1.8 | E10: IG: ≤ 2.5 | F10: Composite score supports strong Investment Grade profile (BBB+ / Baa1 equivalent)
B12: 2. CAPITAL STRUCTURE SNAPSHOT | I12: Financial Risk - Moderate
B13: ($mm) | C13: 2021 | D13: 2022 | E13: 2023 | F13: 2024 | G13: 2025 | I13: Driver | J13: Evidence | K13: Credit implication
B14: Cash & Equivalents | C14: ='2. Financial_Analyst'!C15 -> 235 | D14: ='2. Financial_Analyst'!D15 -> 161.4 | E14: ='2. Financial_Analyst'!E15 -> 931.1 | F14: ='2. Financial_Analyst'!F15 -> 559.7 | G14: ='2. Financial_Analyst'!G15 -> 183.3 | I14: Leverage | J14: Total Debt / EBITDA fell from 2.8x to 1.9x; Net Debt / EBITDA improved from 2.6x to 1.8x | K14: Manageable leverage profile
B15: Short-Term Debt | C15: ='2. Financial_Analyst'!C24-'[1]Sheet9_Financial Data'!G834 -> 40.6 | D15: ='2. Financial_Analyst'!D24-'[1]Sheet9_Financial Data'!F834 -> 122.8 | E15: ='2. Financial_Analyst'!E24-'[1]Sheet9_Financial Data'!E834 -> 13 | F15: ='2. Financial_Analyst'!F24-'[1]Sheet9_Financial Data'!D834 -> 411.2 | G15: ='2. Financial_Analyst'!G24-'[1]Sheet9_Financial Data'!C834 -> 6.2 | I15: Coverage | J15: EBITDA / Interest remained 9.5x–10.6x; EBIT / Interest 6.1x–7.3x | K15: Strong debt servicing capacity
B16: Long-Term Debt | C16: ='[1]Sheet9_Financial Data'!G834 -> 3935.3 | D16: ='[1]Sheet9_Financial Data'!F834 -> 3910 | E16: ='[1]Sheet9_Financial Data'!E834 -> 3893.9 | F16: ='[1]Sheet9_Financial Data'!D834 -> 4916.6 | G16: ='[1]Sheet9_Financial Data'!C834 -> 4366.7 | I16: Cash Flow | J16: CFO / Total Debt improved to 41.5%; FCF / Total Debt rose to 26.0% | K16: Solid deleveraging and repayment capacity
B17: Total Debt | C17: ='2. Financial_Analyst'!C24 -> 3975.9 | D17: ='2. Financial_Analyst'!D24 -> 4032.8 | E17: ='2. Financial_Analyst'!E24 -> 3906.9 | F17: ='2. Financial_Analyst'!F24 -> 5327.8 | G17: ='2. Financial_Analyst'!G24 -> 4372.9
B18: Net Debt | C18: =C17-C14 -> 3740.9 | D18: =D17-D14 -> 3871.4 | E18: =E17-E14 -> 2975.8 | F18: =F17-F14 -> 4768.1 | G18: =G17-G14 -> 4189.6 | I18: Liquidity Risk - Strong
B19: Total Equity | C19: ='2. Financial_Analyst'!C25 -> 6567.7 | D19: ='2. Financial_Analyst'!D25 -> 6952.2 | E19: ='2. Financial_Analyst'!E25 -> 7507.9 | F19: ='2. Financial_Analyst'!F25 -> 8142.5 | G19: ='2. Financial_Analyst'!G25 -> 8548.9 | I19: Driver | J19: Evidence | K19: Credit implication
B20: Total Capital (Debt + Equity) | C20: =C17+C19 -> 10543.6 | D20: =D17+D19 -> 10985 | E20: =E17+E19 -> 11414.8 | F20: =F17+F19 -> 13470.3 | G20: =G17+G19 -> 12921.8 | I20: Liquidity profile | J20: Current Ratio 1.8x–3.2x; Quick Ratio 1.3x–2.4x | K20: Comfortable short-term coverage
B21: Enterprise Value | G21: =G18+G17-G14 -> 8379.2 | I21: Near-term debt | J21: Short-term debt low in most years; 2025 at $6.2mm | K21: Limited refinancing pressure
B22: Debt / Capital | C22: =C17/C20 -> 0.37709132 | D22: =D17/D20 -> 0.3671188 | E22: =E17/E20 -> 0.34226618 | F22: =F17/F20 -> 0.395522 | G22: =G17/G20 -> 0.33841261 | I22: Cash flow support | J22: CFO / Total Debt up to 41.5% | K22: Strong liquidity support
B23: Equity / Capital | C23: =C19/C20 -> 0.62290868 | D23: =D19/D20 -> 0.6328812 | E23: =E19/E20 -> 0.65773382 | F23: =F19/F20 -> 0.604478 | G23: =G19/G20 -> 0.66158739
I24: Cyclicality - Moderate
B25: 3. HISTORICAL CREDIT METRICS | I25: Driver | J25: Evidence | K25: Implication
B26: Leverage | C26: 2021 | D26: 2022 | E26: 2023 | F26: 2024 | G26: 2025 | I26: End-market exposure | J26: Construction-driven demand; ~60% private / ~40% public mix | K26: Volume sensitive to economic cycle; residential & non-res exposure
B27: Total Debt / EBITDA | C27: ='2. Financial_Analyst'!C24/'2. Financial_Analyst'!C10 -> 2.7712414 | D27: ='2. Financial_Analyst'!D24/'2. Financial_Analyst'!D10 -> 2.4940012 | E27: ='2. Financial_Analyst'!E24/'2. Financial_Analyst'!E10 -> 2.0146968 | F27: ='2. Financial_Analyst'!F24/'2. Financial_Analyst'!F10 -> 2.6267317 | G27: ='2. Financial_Analyst'!G24/'2. Financial_Analyst'!G10 -> 1.9213937 | I27: Demand support | J27: Infrastructure Investment & Jobs Act (IIJA) provides $550B+ in federal spending | K27: Multi-year public demand floor; partial downside buffer in downturns
B28: Net Debt / EBITDA | C28: =C18/'2. Financial_Analyst'!C10 -> 2.6074441 | D28: =D18/'2. Financial_Analyst'!D10 -> 2.3941868 | E28: =E18/'2. Financial_Analyst'!E10 -> 1.5345503 | F28: =F18/'2. Financial_Analyst'!F10 -> 2.3507864 | G28: =G18/'2. Financial_Analyst'!G10 -> 1.8408542 | I28: Earnings resilience | J28: EBITDA margin expanded 280bps (2021–2025) despite volume swings; pricing power intact | K28: Cyclicality moderated by pricing discipline, cost control, and project mix shift
B29: Debt / Equity | C29: =C17/C19 -> 0.60537174 | D29: =D17/D19 -> 0.58007537 | E29: =E17/E19 -> 0.52037187 | F29: =F17/F19 -> 0.65431993 | G29: =G17/G19 -> 0.5115161 | I29: Business Risk - Low
B30: Debt / Capital | C30: =C22 -> 0.37709132 | D30: =D22 -> 0.3671188 | E30: =E22 -> 0.34226618 | F30: =F22 -> 0.395522 | G30: =G22 -> 0.33841261 | I30: Driver | J30: Evidence | K30: Credit implication
I31: Market position | J31: #2 US aggregates producer; operations in 25+ states with irreplaceable, permitted reserves | K31: High barriers to entry; durable competitive advantage
B32: Coverage | I32: Product essentiality | J32: Aggregates are essential inputs for construction with no viable substitutes | K32: Demand is non-discretionary; pricing resilience in downturns
B33: EBITDA / Interest Expense | C33: ='2. Financial_Analyst'!C10/'[1]Sheet9_Financial Data'!G996 -> 9.6095111 | D33: ='2. Financial_Analyst'!D10/'[1]Sheet9_Financial Data'!F996 -> 9.5567376 | E33: ='2. Financial_Analyst'!E10/'[1]Sheet9_Financial Data'!E996 -> 9.8888322 | F33: ='2. Financial_Analyst'!F10/'[1]Sheet9_Financial Data'!D996 -> 10.608264 | G33: ='2. Financial_Analyst'!G10/'[1]Sheet9_Financial Data'!C996 -> 9.4947851 | I33: Margin profile | J33: EBITDA margin expanded from 25.8% (2021) to 28.7% (2025); above peer median | K33: Improving profitability supports cash generation and credit quality
B34: EBIT / Interest Expense | C34: ='2. Financial_Analyst'!C11/'[1]Sheet9_Financial Data'!G996 -> 6.5083724 | D34: ='2. Financial_Analyst'!D11/'[1]Sheet9_Financial Data'!F996 -> 6.0845154 | E34: ='2. Financial_Analyst'!E11/'[1]Sheet9_Financial Data'!E996 -> 6.7424783 | F34: ='2. Financial_Analyst'!F11/'[1]Sheet9_Financial Data'!D996 -> 7.3017782 | G34: ='2. Financial_Analyst'!G11/'[1]Sheet9_Financial Data'!C996 -> 6.3721318 | I34: Geographic diversity | J34: Operations across Sun Belt and high-growth US regions; local market dominance | K34: Reduces concentration risk; benefits from regional growth tailwinds
I35: Revenue visibility | J35: Long-term infrastructure projects (IIJA) provide multi-year demand pipeline | K35: Enhanced earnings predictability and reduced downside volatility
B36: Cash Flow Credit Metrics
B37: CFO / Total Debt | C37: ='2. Financial_Analyst'!C29/'2. Financial_Analyst'!C24 -> 0.25450841 | D37: ='2. Financial_Analyst'!D29/'2. Financial_Analyst'!D24 -> 0.28471533 | E37: ='2. Financial_Analyst'!E29/'2. Financial_Analyst'!E24 -> 0.39335535 | F37: ='2. Financial_Analyst'!F29/'2. Financial_Analyst'!F24 -> 0.2645745 | G37: ='2. Financial_Analyst'!G29/'2. Financial_Analyst'!G24 -> 0.41459901 | I37: Industry Position - Strong
B38: FCF / Total Debt | C38: ='[1]Sheet9_Financial Data'!G1192/'2. Financial_Analyst'!C24 -> 0.14099952 | D38: ='[1]Sheet9_Financial Data'!F1192/'2. Financial_Analyst'!D24 -> 0.13281095 | E38: ='[1]Sheet9_Financial Data'!E1192/'2. Financial_Analyst'!E24 -> 0.17000691 | F38: ='[1]Sheet9_Financial Data'!D1192/'2. Financial_Analyst'!F24 -> 0.15130072 | G38: ='[1]Sheet9_Financial Data'!C1192/'2. Financial_Analyst'!G24 -> 0.25962176 | I38: Driver | J38: Evidence | K38: Credit implication
B39: FCF Yield on Net Debt | C39: ='[1]Sheet9_Financial Data'!G1192/C18 -> 0.14985699 | D39: ='[1]Sheet9_Financial Data'!F1192/D18 -> 0.13834788 | E39: ='[1]Sheet9_Financial Data'!E1192/E18 -> 0.22320048 | F39: ='[1]Sheet9_Financial Data'!D1192/F18 -> 0.16906105 | G39: ='[1]Sheet9_Financial Data'!C1192/G18 -> 0.27098052 | I39: Competitive rank | J39: #2 in US aggregates behind Martin Marietta (MLM); top-3 nationally in asphalt and concrete | K39: Scale advantage enables pricing discipline and cost efficiency
I40: Peer comparison | J40: EBITDA margin 28.7% vs. peer median 24.3%; ROIC 9.2% ranks 3rd of 6 peers | K40: Above-average returns signal superior operational execution
B41: Liquidity | I41: Barriers to entry | J41: Permitting new quarries takes 7–10+ years; proximity to end-markets critical due to high transport cost | K41: Near-unassailable local market positions; limited new entrant threat
B42: Current Ratio | C42: ='2. Financial_Analyst'!C61 -> 2.2053815 | D42: ='2. Financial_Analyst'!D61 -> 1.9882919 | E42: ='2. Financial_Analyst'!E61 -> 3.1656219 | F42: ='2. Financial_Analyst'!F61 -> 1.8285046 | G42: ='2. Financial_Analyst'!G61 -> 2.6858069 | I42: Growth strategy | J42: Disciplined bolt-on M&A (e.g., US Concrete); rapid post-acquisition deleveraging | K42: Accretive growth without compromising credit profile
B43: Quick Ratio | C43: ='2. Financial_Analyst'!C62 -> 1.5277525 | D43: ='2. Financial_Analyst'!D62 -> 1.3827096 | E43: ='2. Financial_Analyst'!E62 -> 2.3938064 | F43: ='2. Financial_Analyst'!F62 -> 1.2782665 | G43: ='2. Financial_Analyst'!G62 -> 1.9740613 | I43: Debt-to-Capital | J43: Debt/Capital 33.8% (2025); 5th lowest among 6 peers — conservative capital structure | K43: Lower leverage supports credit ratings and financial flexibility
B45: 4. DEBT CAPACITY ANALYSIS
B46: ($mm) | G46: LTM 2025
B47: LTM EBITDA | G47: ='2. Financial_Analyst'!G10 -> 2275.9
B48: Target Leverage Multiple (Debt/EBITDA) | G48: 3
B49: Implied Debt Capacity | G49: =G47*G48 -> 6827.7
B50: Current Gross Debt | G50: =G17 -> 4372.9
B51: Incremental Debt Capacity | G51: =G49-G50 -> 2454.8
B53: Pro Forma Debt / EBITDA at Target | G53: =G49/G47 -> 3
B54: Revolver Availability | G54: ='[1]Sheet9_Financial Data'!C905 -> 1576.9
B56: 5. INTEREST RATE SENSITIVITY
B57: ($mm) | E57: Current | F57: +100 bps | G57: +200 bps
B58: LTM EBITDA | E58: =G47 -> 2275.9 | F58: =E58 -> 2275.9 | G58: =E58 -> 2275.9
B59: Current Interest Expense | E59: ='[1]Sheet9_Financial Data'!C996 -> 239.7 | F59: =E59 -> 239.7 | G59: =E59 -> 239.7
B60: Incremental Interest (+bps x Debt) | E60: 0 | F60: =G17*0.01 -> 43.729 | G60: =G17*0.02 -> 87.458
B61: Pro Forma Interest Expense | E61: =E59+E60 -> 239.7 | F61: =F59+F60 -> 283.429 | G61: =G59+G60 -> 327.158
B63: EBITDA / Pro Forma Interest | E63: =E58/E61 -> 9.4947851 | F63: =F58/F61 -> 8.029877 | G63: =G58/G61 -> 6.9565776
B64: EBIT / Pro Forma Interest | E64: ='2. Financial_Analyst'!G11/E61 -> 6.3721318 | F64: ='2. Financial_Analyst'!G11/F61 -> 5.3890039 | G64: ='2. Financial_Analyst'!G11/G61 -> 4.6686922
B65: Change in Coverage vs Current | E65: — | F65: =F63-E63 -> -1.4649082 | G65: =G63-E63 -> -2.5382076
B67: 6. DOWNSIDE STRESS TEST
B68: Scenario Assumptions | E68: Base Case | F68: Downside | G68: Severe
B69: Revenue Shock (%) | E69: 0 | F69: -0.1 | G69: -0.25
B70: EBITDA Margin Change (pp) | E70: 0 | F70: -0.03 | G70: -0.07
B71: Capex Change (%) | E71: 0 | F71: -0.15 | G71: -0.3
B72: Interest Rate Change (bps) | E72: 0 | F72: 100 | G72: 200
B74: Scenario Outputs
B75: Stressed Revenue | E75: ='2. Financial_Analyst'!G5*(1+E69) -> 7941.1 | F75: ='2. Financial_Analyst'!G5*(1+F69) -> 7146.99 | G75: ='2. Financial_Analyst'!G5*(1+G69) -> 5955.825
B76: EBITDA Margin (Stressed) | E76: ='2. Financial_Analyst'!G41+E70 -> 0.28659757 | F76: ='2. Financial_Analyst'!G41+F70 -> 0.25659757 | G76: ='2. Financial_Analyst'!G41+G70 -> 0.21659757
B77: Stressed EBITDA | E77: =E75*E76 -> 2275.9 | F77: =F75*F76 -> 1833.9003 | G77: =G75*G76 -> 1290.0173
B78: Stressed Interest Expense | E78: ='[1]Sheet9_Financial Data'!C996+G17*E72/10000 -> 239.7 | F78: ='[1]Sheet9_Financial Data'!C996+G17*F72/10000 -> 283.429 | G78: ='[1]Sheet9_Financial Data'!C996+G17*G72/10000 -> 327.158
B79: Stressed Capex | E79: ='[1]Sheet9_Financial Data'!C1153*(1+E71) -> 677.7 | F79: ='[1]Sheet9_Financial Data'!C1153*(1+F71) -> 576.045 | G79: ='[1]Sheet9_Financial Data'!C1153*(1+G71) -> 474.39
B81: Net Debt / EBITDA | E81: =G18/E77 -> 1.8408542 | F81: =G18/F77 -> 2.2845299 | G81: =G18/G77 -> 3.2477085
B82: EBITDA / Interest Coverage | E82: =E77/E78 -> 9.4947851 | F82: =F77/F78 -> 6.4704046 | G82: =G77/G78 -> 3.9431017
B83: Free Cash Flow | E83: =E77-E78-E79 -> 1358.5 | F83: =F77-F78-F79 -> 974.4263 | G83: =G77-G78-G79 -> 488.46925
B85: 7. CREDIT CONCLUSION
B86: Assessment | C86: Commentary
B87: Key Strengths | C87: #2 US aggregates producer; low-cost, irreplaceable reserves; strong FCF generation ($1.1B LTM); conservative leverage at 1.9x Net Debt/EBITDA
B88: Key Risks | C88: Cyclical exposure to construction/infrastructure spending; acquisition-driven growth can temporarily elevate leverage; asset-heavy model limits turnover
B89: BS Flexibility | C89: ~$2.5B incremental debt capacity at 3.0x target; $1.6B undrawn revolver; equity cushion at 66% of capital; active deleveraging trend from 2021-2025
B90: Downside Resilience | C90: Even in severe scenario (-25% revenue, -700bp margin), coverage remains 3.9x and FCF stays positive at $488M; no covenant breach risk
B92: Overall Credit Assessment | C92: INVESTMENT GRADE — Strong BBB+ / Baa1 profile
B94: VMC's credit profile is underpinned by dominant market position, essential-use product, expanding margins, and conservative financial policy. The company maintains substantial headroom under stress scenarios.

Sheet 4. ESG_Score
A1: Sheet 4 – ESG Score Analysis | Vulcan Materials Company (VMC) | K1: Pillar | L1: Score
K2: Environmental | L2: 55.17
A3: 1. ESG Conclusion & Investment Implications | K3: Social | L3: 60.99
A4: Mid-quality absolute ESG; strong relative to U.S. construction materials peers. Env. and social acceptable; governance is the clear weak spot. | K4: Governance | L4: 20.99
A6: Finding | B6: Score | C6: Implication | K6: Company | L6: ESG Score | M6: Combined
A7: Overall ESG | B7: 49 (C+) | C7: Neutral to slightly positive for base-case | K7: CRH | L7: 84.18 | M7: 76.18
A8: Governance Risk | B8: 21.0 (D+) | C8: Qualitative discount; monitor board improvements | K8: CX | L8: 81.87 | M8: 81.87
A9: Env. Strength | B9: 55.2 (B-) | C9: Supports carbon transition readiness | K9: VMC | L9: 49 | M9: 49
A10: Social Resilience | B10: 61.0 (B) | C10: Helps social license and permitting | K10: MLM | L10: 42.6 | M10: 42.6
A11: Controversies | B11: 68.2 (B+) | C11: FY24 drop; watch for recurrence | K11: KNF | L11: 32.53 | M11: 32.53
A12: Peer Rank | B12: #3 of 6 | C12: Better than MLM/KNF/EXP; trails CRH, CX | K12: EXP | L12: 27.05 | M12: 27.05
A13: Net Impact | C13: Gov. discount partially offset by social/env strengths
K14: Year | L14: ESG Score | M14: Env. | N14: Social | O14: Gov.
A15: 2. ESG Snapshot | K15: FY2020 | L15: 47.42 | M15: 55 | N15: 46.2 | O15: 34
A16: Metric | B16: Score | C16: Grade | D16: Weight | E16: Read-through | K16: FY2021 | L16: 50 | M16: 63 | N16: 44 | O16: 34
A17: ESG Score | B17: 49 | C17: C+ | E17: Moderate overall profile | K17: FY2022 | L17: 47 | M17: 64 | N17: 38 | O17: 31
A18: Controversies | B18: 68.18 | C18: B+ | E18: Safety event drove FY24 drop | K18: FY2023 | L18: 56.15 | M18: 66 | N18: 64 | O18: 29
A19: ESG Combined | B19: 49 | C19: C+ | E19: Combined = headline ESG | K19: FY2024 | L19: 49 | M19: 55.17 | N19: 60.99 | O19: 20.99
A20: Env. Pillar | B20: 55.17 | C20: B- | D20: 0.421 | E20: Best-performing pillar
A21: Social Pillar | B21: 60.99 | C21: B | D21: 0.34 | E21: Resilient; community 87.7
A22: Gov. Pillar | B22: 20.99 | C22: D+ | D22: 0.238 | E22: Structural weakness; main drag
A24: 3. Historical ESG Scorecard (FY2020–FY2024)
A25: Metric | B25: FY2020 | C25: FY2021 | D25: FY2022 | E25: FY2023 | F25: FY2024 | G25: 5Y Avg | H25: YoY Δ | I25: Trend
A26: ESG Score | B26: 47.42 | C26: 50 | D26: 47 | E26: 56.15 | F26: 49 | G26: =AVERAGE(B26:F26) -> 49.914 | H26: =F26-E26 -> -7.15 | I26: Stable
A27: Controversies | B27: 100 | C27: 100 | D27: 50 | E27: 100 | F27: 68.18 | G27: =AVERAGE(B27:F27) -> 83.636 | H27: =F27-E27 -> -31.82 | I27: Deteriorating
A28: ESG Combined | B28: 47.42 | C28: 50 | D28: 47 | E28: 56.15 | F28: 49 | G28: =AVERAGE(B28:F28) -> 49.914 | H28: =F28-E28 -> -7.15 | I28: Stable
A29: Env. Pillar | B29: 55 | C29: 63 | D29: 64 | E29: 66 | F29: 55.17 | G29: =AVERAGE(B29:F29) -> 60.634 | H29: =F29-E29 -> -10.83 | I29: Stable
A30: Social Pillar | B30: 46.2 | C30: 44 | D30: 38 | E30: 64 | F30: 60.99 | G30: =AVERAGE(B30:F30) -> 50.638 | H30: =F30-E30 -> -3.01 | I30: Improving
A31: Gov. Pillar | B31: 34 | C31: 34 | D31: 31 | E31: 29 | F31: 20.99 | G31: =AVERAGE(B31:F31) -> 29.798 | H31: =F31-E31 -> -8.01 | I31: Deteriorating
A32: Diagnostic: | B32: Strongest: Social | Weakest: Governance | Sharpest decline: Controversies (−31.8) | Current ESG below 5Y avg
A34: 4. FY2024 vs FY2023 Pillar Attribution
A35: Pillar | B35: Category | C35: FY2024 | D35: FY2023 | E35: YoY Δ | F35: Weight | G35: Attribution
A36: ESG | B36: ESG Score | C36: 49 | D36: 56.15 | E36: =C36-D36 -> -7.15 | F36: 1 | G36: =E36*F36 -> -7.15
A37: Env. | B37: Resource Use | C37: 43.28 | D37: 45.73 | E37: =C37-D37 -> -2.45 | F37: 0.151 | G37: =E37*F37 -> -0.36995
A38: Env. | B38: Emissions | C38: 59.92 | D38: 61.76 | E38: =C38-D38 -> -1.84 | F38: 0.151 | G38: =E38*F38 -> -0.27784
A39: Env. | B39: Env. Innovation | C39: 64.2 | D39: 95.78 | E39: =C39-D39 -> -31.58 | F39: 0.119 | G39: =E39*F39 -> -3.75802
A40: Social | B40: Workforce | C40: 31.35 | D40: 33.2 | E40: =C40-D40 -> -1.85 | F40: 0.107 | G40: =E40*F40 -> -0.19795
A41: Social | B41: Human Rights | C41: 74.54 | D41: 79.25 | E41: =C41-D41 -> -4.71 | F41: 0.111 | G41: =E41*F41 -> -0.52281
A42: Social | B42: Community | C42: 87.7 | D42: 86 | E42: =C42-D42 -> 1.7 | F42: 0.079 | G42: =E42*F42 -> 0.1343
A43: Social | B43: Product Resp. | C43: 50.41 | D43: 57.08 | E43: =C43-D43 -> -6.67 | F43: 0.042 | G43: =E43*F43 -> -0.28014
A44: Gov. | B44: Management | C44: 13.75 | D44: 12.68 | E44: =C44-D44 -> 1.07 | F44: 0.159 | G44: =E44*F44 -> 0.17013
A45: Gov. | B45: Shareholders | C45: 24.55 | D45: 67.81 | E45: =C45-D45 -> -43.26 | F45: 0.048 | G45: =E45*F45 -> -2.07648
A46: Gov. | B46: CSR Strategy | C46: 51.9 | D46: 51.04 | E46: =C46-D46 -> 0.86 | F46: 0.032 | G46: =E46*F46 -> 0.02752
A47: Key detractors: | B47: Shareholders (−43.3 YoY, −2.1 attrib.) and Env. Innovation (−31.6 YoY, −3.8 attrib.)
A49: 5. Material ESG Risks & Opportunities
A50: Pillar | B50: Issue | C50: FY24 Score | D50: YoY Δ | E50: Impact | F50: Analyst View
A51: Gov. | B51: Weak Governance Score | C51: 20.99 | D51: -8.01 | E51: Risk premium / capital allocation | F51: Primary ESG constraint; temper premium
A52: Env. | B52: Env. Innovation Decline | C52: 64.2 | D52: -31.58 | E52: Strategic capex / sustainability | F52: Negative for premium-multiple narrative
A53: Social | B53: Safety Controversy | C53: n/a | D53: n/a | E53: Operating cost / downtime | F53: Monitor; not thesis-changing alone
A54: Env. | B54: Strong Emissions Profile | C54: 59.92 | D54: -1.84 | E54: Carbon transition readiness | F54: Supports sustainability narrative
A55: Social | B55: Strong Community Score | C55: 87.7 | D55: 1.7 | E55: Social license to operate | F55: Partially offsets governance discount
A56: Controversies: | B56: No controversial business flags | No UN Global Compact violations | FY24: MSHA safety order | FY22: Mexican mine shutdown
A58: 6. Peer ESG Comparison
A59: Rank | B59: Ticker | C59: Company | D59: ESG | E59: Combined | F59: Controversies | G59: Env. | H59: Social | I59: Gov.
A60: 1 | B60: CRH | C60: CRH PLC | D60: 84.18 | E60: 76.18 | F60: 68.18 | G60: A+ | H60: A | I60: B
A61: 2 | B61: CX | C61: Cemex SAB de CV | D61: 81.87 | E61: 81.87 | F61: 100 | G61: A- | H61: A | I61: A-
A62: 3 | B62: VMC | C62: Vulcan Materials Co | D62: 49 | E62: 49 | F62: 68.18 | G62: B- | H62: B | I62: D+
A63: 4 | B63: MLM | C63: Martin Marietta | D63: 42.6 | E63: 42.6 | F63: 100 | G63: D+ | H63: C | I63: A+
A64: 5 | B64: KNF | C64: Knife River Corp | D64: 32.53 | E64: 32.53 | F64: 100 | G64: D | H64: C+ | I64: B-
A65: 6 | B65: EXP | C65: Eagle Materials Inc | D65: 27.05 | E65: 27.05 | F65: 100 | G65: D | H65: C- | I65: C

Sheet 5. Macro-Economics 
B1: Sheet 5 – Macro-Economics & Industry Analysis | Vulcan Materials Company (VMC)
B3: A. Industry Overview — US Aggregates & Construction Materials
B4: A1. Market Summary | C4: Value | D4: Source
B5: US Aggregates Market Size (2024) | C5: 44.8 | D5: USGS / IBISWorld
B6: Industry Cycle Position (2025) | C6: Mid-Cycle / Recovery | D6: IIJA tailwinds offset residential weakness
B7: 3Y Revenue CAGR (FY2022–FY2025) | C7: =('9. Standardlized_Income'!D34/'9. Standardlized_Income'!G34)^(1/3)-1 -> 0.027743693 | D7: Calculated from 9.1
B8: 5Y Revenue CAGR (FY2021–FY2025) | C8: =('9. Standardlized_Income'!D34/'9. Standardlized_Income'!H34)^(1/5)-1 -> 0.074194966 | D8: Calculated from 9.1
B10: A2. Porter's Five Forces | C10: Score (1–5) | D10: Assessment
B11: Threat of New Entrants | C11: 1 | D11: High capex + 5–10yr permitting; reserve scarcity
B12: Supplier Power | C12: 2 | D12: VMC owns quarries; diesel ~8% COGS is key input
B13: Buyer Power | C13: 3 | D13: Fragmented contractors; public-sector bidding limits pricing
B14: Threat of Substitutes | C14: 1 | D14: No viable substitute for road/bridge base (<5% recycled)
B15: Competitive Rivalry | C15: 3 | D15: Effective duopoly with MLM; rational pricing discipline
B17: A3. Industry Structure | C17: Value | D17: Source
B18: US Aggregate Consumption (2024) | C18: ~2.6 Bt | D18: USGS — 23% below pre-GFC peak
B19: Volume CAGR (2014–2024) | C19: ~1.0–1.4% | D19: Crushed stone 1.4%; Sand 0.7%
B20: Value CAGR (ASP, 2014–2024) | C20: ~5.5% | D20: ASP: $9.26→$15.88/ton (USGS)
B21: Forecast CAGR (2025–2033) | C21: ~3.4–6.4% | D21: Range across research sources
B22: Infrastructure End-Use Share | C22: ~38% | D22: Roads/bridges = ~70% of crushed stone
B23: Non-Residential Share | C23: ~55%+ | D23: Infra + commercial/industrial
B24: Residential Share | C24: ~25% | D24: Smallest; fastest-growing (5.1% CAGR)
B26: B. Growth Drivers & Headwinds — VMC
B27: B1. Growth Drivers | F27: B2. Headwinds / Risks
B28: IIJA & Infrastructure | C28: $550B+ federal program; ~30% VMC volumes | F28: Residential Slowdown | G28: Starts -5% in 2024; ~20% VMC volumes
B29: Pricing Power | C29: ASP +14%/+12%/+6% (2022–24); reserve scarcity | F29: Energy Cost Inflation | G29: Diesel ~8% COGS; $0.10/gal = ~$6M EBITDA hit
B30: Reshoring / CHIPS Act | C30: Record industrial construction; fabs & EV plants | F30: Interest Rate Sensitivity | G30: Municipal bond costs limit project starts
B31: M&A Bolt-ons | C31: ~25 quarry acquisitions 2019–24; Sun Belt focus | F31: Weather & Seasonality | G31: 1 lost workday ≈ $15M revenue
B32: Margin Expansion | C32: EBITDA/ton improving via SAP, AI dispatch, leverage | F32: Permitting / Environmental | G32: Avg permit >7 yrs; limits greenfield response
B34: C. Regulatory & Technology Risk
B35: Risk | C35: Probability | D35: Revenue at Risk | E35: Time Horizon | F35: Mitigation
B36: IIJA Funding Delays | C36: M | D36: ~$0.5–1.0B | E36: 2025–27 | F36: Multi-year highway bill + state match = 2yr buffer
B37: EPA Quarry Discharge Rules | C37: M | D37: ~$0.2–0.4B | E37: 2026–28 | F37: Proactive compliance; NSSGA lobbying
B38: Carbon Pricing / Emissions | C38: L | D38: ~$0.1–0.3B | E38: 2028+ | F38: Low-emission vs cement; net-zero 2050 target
B39: AI / Automation Disruption | C39: L | D39: <$0.1B | E39: 2028+ | F39: VMC investing; reduces costs not revenue
B40: Diesel / Energy Shock | C40: H | D40: ~$0.3–0.5B | E40: Immediate | F40: Fleet electrification; hedging; ASP surcharges
B41: Permitting Reform Reversal | C41: M | D41: ~$0.5–1.0B | E41: 2026+ | F41: Reserve runway 65+ yrs; existing permits sufficient
B43: D. Competitive Landscape
B44: Company | C44: Revenue ($mm) | D44: EBITDA Margin | E44: Net Margin | F44: Debt/Assets | G44: ROIC | H44: Interest Cov. | I44: Competitive Position
B45: VMC (Vulcan Materials) | C45: ='9. Standardlized_Income'!D34 -> 7941.1 | D45: ='9. Standardlized_Income'!D46/'9. Standardlized_Income'!D34 -> 0.28659757 | E45: ='9. Standardlized_Income'!D44/'9. Standardlized_Income'!D34 -> 0.13558575 | F45: ='9. Standardlized_Income'!D31/'9. Standardlized_Income'!D17 -> 0.26184403 | G45: ='9. Standardlized_Income'!D44/'9. Standardlized_Income'!D17 -> 0.06447151 | H45: ='9. Standardlized_Income'!D39/'9. Standardlized_Income'!D40 -> 6.3721318 | I45: No.2 US crushed stone; 25+ states; vertically integrated
B46: MLM (Martin Marietta) | C46: ='9. Standardlized_Income'!J34 -> 6150 | D46: ='9. Standardlized_Income'!J46/'9. Standardlized_Income'!J34 -> 0.34634146 | E46: ='9. Standardlized_Income'!J44/'9. Standardlized_Income'!J34 -> 0.18487805 | F46: ='9. Standardlized_Income'!J31/'9. Standardlized_Income'!J17 -> 0.3006253 | G46: ='9. Standardlized_Income'!J44/'9. Standardlized_Income'!J17 -> 0.060766394 | H46: ='9. Standardlized_Income'!J39/'9. Standardlized_Income'!J40 -> 6.4913043 | I46: No.1 US crushed stone; duopoly with VMC; SE/SW focus
B47: CRH plc | C47: ='9. Standardlized_Income'!N34 -> 37447 | D47: ='9. Standardlized_Income'!N46/'9. Standardlized_Income'!N34 -> 0.19972227 | E47: ='9. Standardlized_Income'!N44/'9. Standardlized_Income'!N34 -> 0.10022165 | F47: ='9. Standardlized_Income'!N31/'9. Standardlized_Income'!N17 -> 0.31180031 | G47: ='9. Standardlized_Income'!N44/'9. Standardlized_Income'!N17 -> 0.064341923 | H47: ='9. Standardlized_Income'!N39/'9. Standardlized_Income'!N40 -> 6.5716049 | I47: Global diversified; US via Oldcastle; strong ESG (A)
B48: CEMEX (CX) | C48: ='9. Standardlized_Income'!P34 -> 16131.88 | D48: ='9. Standardlized_Income'!P46/'9. Standardlized_Income'!P34 -> 0.14231323 | E48: ='9. Standardlized_Income'!P44/'9. Standardlized_Income'!P34 -> 0.059519411 | F48: ='9. Standardlized_Income'!P31/'9. Standardlized_Income'!P17 -> 0.23407114 | G48: ='9. Standardlized_Income'!P44/'9. Standardlized_Income'!P17 -> 0.033148389 | H48: ='9. Standardlized_Income'!P39/'9. Standardlized_Income'!P40 -> 3.3408139 | I48: Global cement/aggregates; Mexico-heavy
B49: EXP (Eagle Materials) | C49: ='9. Standardlized_Income'!R34 -> 2260.51 | D49: ='9. Standardlized_Income'!R46/'9. Standardlized_Income'!R34 -> 0.33820686 | E49: ='9. Standardlized_Income'!R44/'9. Standardlized_Income'!R34 -> 0.20500683 | F49: ='9. Standardlized_Income'!R31/'9. Standardlized_Income'!R17 -> 0.37931869 | G49: ='9. Standardlized_Income'!R44/'9. Standardlized_Income'!R17 -> 0.14195351 | H49: ='9. Standardlized_Income'!R39/'9. Standardlized_Income'!R40 -> 15.050199 | I49: Smaller; cement + gypsum; highest ROIC in group
B50: KNF (Knife River) | C50: ='9. Standardlized_Income'!L34 -> 3146.01 | D50: ='9. Standardlized_Income'!L46/'9. Standardlized_Income'!L34 -> 0.15613746 | E50: ='9. Standardlized_Income'!L44/'9. Standardlized_Income'!L34 -> 0.049926733 | F50: ='9. Standardlized_Income'!L31/'9. Standardlized_Income'!L17 -> 0.3193164 | G50: ='9. Standardlized_Income'!L44/'9. Standardlized_Income'!L17 -> 0.04303158 | H50: ='9. Standardlized_Income'!L39/'9. Standardlized_Income'!L40 -> 3.6303393 | I50: Recently spun-off; NW/Mountain; contracting + aggregates
B52: E. Macro-Economic Correlation Analysis (20-Year, 2005–2024)
B53: E1. Historical Data Panel | L53: Hwy & Street ($B) | M53: VMC Revenue ($mm) | O53: Pvt Nonres ($B) | P53: VMC Revenue ($mm)
B54: Year | C54: VMC Price ($) | D54: VMC Rev ($mm) | E54: Hwy & Street ($B) | F54: Public Constr ($B) | G54: Pvt Nonres ($B) | H54: Hsg Starts (000s) | I54: Mortgage Rate (%) | J54: Diesel ($/gal) | L54: =E55 -> 73.5 | M54: =D55 -> 3127 | O54: =G55 -> 220.5 | P54: =D55 -> 3127
B55: 2005 | C55: 68.6 | D55: 3127 | E55: 73.5 | F55: 240.2 | G55: 220.5 | H55: 2068 | I55: 5.87 | J55: 2.4 | L55: =E56 -> 79.4 | M55: =D56 -> 3342 | O55: =G56 -> 248.3 | P55: =D56 -> 3342
B56: 2006 | C56: 82.08 | D56: 3342 | E56: 79.4 | F56: 263.7 | G56: 248.3 | H56: 1801 | I56: 6.41 | J56: 2.71 | L56: =E57 -> 83 | M56: =D57 -> 3328 | O56: =G57 -> 258.2 | P56: =D57 -> 3328
B57: 2007 | C57: 73.41 | D57: 3328 | E57: 83 | F57: 279.2 | G57: 258.2 | H57: 1355 | I57: 6.34 | J57: 2.88 | L57: =E58 -> 87.2 | M57: =D58 -> 3453 | O57: =G58 -> 248.1 | P57: =D58 -> 3453
B58: 2008 | C58: 50.76 | D58: 3453 | E58: 87.2 | F58: 291 | G58: 248.1 | H58: 906 | I58: 6.03 | J58: 3.8 | L58: =E59 -> 86.5 | M58: =D59 -> 2545 | O58: =G59 -> 195.7 | P58: =D59 -> 2545
B59: 2009 | C59: 43.05 | D59: 2545 | E59: 86.5 | F59: 297.4 | G59: 195.7 | H59: 554 | I59: 5.04 | J59: 2.47 | L59: =E60 -> 86.8 | M59: =D60 -> 2407 | O59: =G60 -> 186.1 | P59: =D60 -> 2407
B60: 2010 | C60: 39.66 | D60: 2407 | E60: 86.8 | F60: 280.9 | G60: 186.1 | H60: 587 | I60: 4.69 | J60: 2.99 | L60: =E61 -> 79.6 | M60: =D61 -> 2422 | O60: =G61 -> 196.4 | P60: =D61 -> 2422
B61: 2011 | C61: 35.46 | D61: 2422 | E61: 79.6 | F61: 259.2 | G61: 196.4 | H61: 609 | I61: 4.45 | J61: 3.84 | L61: =E62 -> 78.7 | M61: =D62 -> 2587 | O61: =G62 -> 212.6 | P61: =D62 -> 2587
B62: 2012 | C62: 53.64 | D62: 2587 | E62: 78.7 | F62: 260.6 | G62: 212.6 | H62: 781 | I62: 3.66 | J62: 3.97 | L62: =E63 -> 81.8 | M62: =D63 -> 2694 | O62: =G63 -> 229.3 | P62: =D63 -> 2694
B63: 2013 | C63: 62.74 | D63: 2694 | E63: 81.8 | F63: 262.3 | G63: 229.3 | H63: 925 | I63: 3.98 | J63: 3.92 | L63: =E64 -> 87.5 | M63: =D64 -> 2966 | O63: =G64 -> 243.7 | P63: =D64 -> 2966
B64: 2014 | C64: 64.72 | D64: 2966 | E64: 87.5 | F64: 274.1 | G64: 243.7 | H64: 1003 | I64: 4.17 | J64: 3.83 | L64: =E65 -> 91.3 | M64: =D65 -> 3273 | O64: =G65 -> 262 | P64: =D65 -> 3273
B65: 2015 | C65: 94.48 | D65: 3273 | E65: 91.3 | F65: 284.4 | G65: 262 | H65: 1112 | I65: 3.85 | J65: 2.71 | L65: =E66 -> 95.5 | M65: =D66 -> 3593 | O65: =G66 -> 268.1 | P65: =D66 -> 3593
B66: 2016 | C66: 119.94 | D66: 3593 | E66: 95.5 | F66: 295.4 | G66: 268.1 | H66: 1174 | I66: 3.65 | J66: 2.31 | L66: =E67 -> 97.7 | M66: =D67 -> 3722 | O66: =G67 -> 274.8 | P66: =D67 -> 3722
... B73: 2023 | C73: 223.99 | D73: 7782 | E73: 127.5 | F73: 408.7 | G73: 369.7 | H73: 1420 | I73: 6.81 | J73: 4.21 | L73: =E74 -> 140.7 | M73: =D74 -> 7418 | O73: =G74 -> 370.6 | P73: =D74 -> 7418
B74: 2024 | C74: 243.17 | D74: 7418 | E74: 140.7 | F74: 498.7 | G74: 370.6 | H74: 1361 | I74: 6.72 | J74: 3.81
B76: E2. Correlation Matrix
B77: Indicator | C77: r vs. Price | D77: r vs. Revenue | E77: R-Squared (Revenue)
B78: Hwy & Street Constr. Spending | C78: =CORREL(C$55:C$74,E$55:E$74) -> 0.92813457 | D78: =CORREL(D$55:D$74,E$55:E$74) -> 0.92335921 | E78: =D78^2 -> 0.85259222
B79: Total Public Constr. Spending | C79: =CORREL(C$55:C$74,F$55:F$74) -> 0.88091601 | D79: =CORREL(D$55:D$74,F$55:F$74) -> 0.89142726 | E79: =D79^2 -> 0.79464256
B80: Private Nonres. Constr. Spending | C80: =CORREL(C$55:C$74,G$55:G$74) -> 0.92464455 | D80: =CORREL(D$55:D$74,G$55:G$74) -> 0.95451987 | E80: =D80^2 -> 0.91110818
B81: Housing Starts | C81: =CORREL(C$55:C$74,H$55:H$74) -> 0.51990267 | D81: =CORREL(D$55:D$74,H$55:H$74) -> 0.4915231 | E81: =D81^2 -> 0.24159496
B82: 30-Year Mortgage Rate | C82: =CORREL(C$55:C$74,I$55:I$74) -> 0.122852 | D82: =CORREL(D$55:D$74,I$55:I$74) -> 0.30813767 | E82: =D82^2 -> 0.094948821
B83: On-Highway Diesel Price | C83: =CORREL(C$55:C$74,J$55:J$74) -> 0.24768209 | D83: =CORREL(D$55:D$74,J$55:J$74) -> 0.44889531 | E83: =D83^2 -> 0.201507
B85: F. Forward-Looking Macro Scenarios & VMC Implications
B86: Scenario | C86: Probability | D86: Public Spend | E86: Pvt Nonres | F86: Housing Starts | G86: VMC Rev Impact | H86: VMC Price Signal
B87: Bull: IIJA Acceleration + Soft Landing | C87: 0,4 | D87: +8–10% YoY | E87: +5–7% YoY | F87: 1,450–1,550k | G87: +6–10% | H87: Upside
B88: Base: Steady Disbursement + Flat Rates | C88: 0.35 | D88: +3–5% YoY | E88: 0–3% YoY | F88: 1,350–1,400k | G88: +2–5% | H88: Stable
B89: Bear: Fiscal Pullback + Rate Overshoot | C89: 0.2 | D89: -2–0% YoY | E89: -5–0% YoY | F89: 1,100–1,200k | G89: -5–0% | H89: Downside
B90: Tail: Recession + Construction Freeze | C90: 0.05 | D90: -5–10% YoY | E90: -10–15% YoY | F90: <1,000k | G90: -10–15% | H90: Downside
B91: Rationale:
B92: Bull: IIJA multi-year highway bill enters peak disbursement 2025–27; reshoring/CHIPS pulls forward industrial capex; Fed rate cuts support housing recovery.
B93: Base: Public infrastructure grows at legislated pace; private nonresidential flat as reshoring tailwind offsets rate drag; housing stuck at 6%+ mortgage rates.
B94: Bear: Federal budget gridlock slows IIJA; rates above 7% choke private construction; housing drops to GFC-recovery levels. VMC's infra tilt limits downside vs. peers.
B95: Tail: Broad recession compresses all segments. Precedent: 2008–09 saw VMC rev -26% peak-to-trough. Current balance sheet (2.3x net debt/EBITDA) is much stronger.
B97: G. VMC Sensitivity to Macro Factors
B98: Factor | C98: Sensitivity | D98: Transmission Channel | E98: Lag | F98: Direction | G98: Magnitude
B99: Federal Infrastructure Spend (IIJA) | C99: High | D99: Direct: ~40% of VMC volumes tied to public highway/bridge projects | E99: 6–12 mo | F99: Positive | G99: +1% public spend = +0.4% revenue
B100: Private Nonresidential Constr. | C100: High | D100: Direct: commercial, industrial, manufacturing construction drives ~35% of volumes | E100: 3–6 mo | F100: Positive | G100: R-sq = 91%; strongest single predictor
B101: Housing Starts | C101: Moderate | D101: Indirect: residential is ~20% of volumes; VMC's Sun Belt exposure amplifies vs. national data | E101: 0–3 mo | F101: Positive | G101: +10% starts = +2% revenue
B102: Interest Rates / Mortgage Rate | C102: Low | D102: Indirect: affects housing + municipal bond-funded projects; offset by federal funding insensitivity | E102: 6–18 mo | F102: Negative | G102: r = 0.12 vs. price; near-zero direct link
B103: Diesel / Energy Costs | C103: Low–Moderate | D103: Cost-side: diesel ~8% of COGS; +$0.10/gal = ~$6M EBITDA drag; partially passed through via ASP surcharges | E103: Immediate | F103: Negative | G103: +$1/gal = ~$60M EBITDA headwind
B104: GDP Growth Rate | C104: Moderate | D104: Broad: construction spend is ~4–5% of GDP; recession risk compresses all segments simultaneously | E104: 0–6 mo | F104: Positive | G104: 2008–09: GDP -2.5% drove VMC rev -26%
B106: Analyst Summary
B107: VMC is a direct play on U.S. construction capex. Over 20 years, highway spending and private nonresidential construction explain 85–91% of revenue variance. Housing, mortgage rates, and diesel are secondary. The IIJA disbursement cycle (2025–27 peak) is the single most important macro catalyst. In the base case, VMC revenues grow 2–5% driven by steady public-sector disbursement. The bull case requires both IIJA acceleration and private capex growth, which we assign 40% probability given the legislated spending timeline.
B109: E3. Normalized Index (2005 = 100)
B110: Year | C110: VMC Price | D110: VMC Revenue | E110: Hwy & Street | F110: Public Constr | G110: Pvt Nonres | H110: Hsg Starts | I110: Mortgage Rate | J110: Diesel Price
B111: =B55 -> 2005 | C111: =C55/C$55*100 -> 100 | D111: =D55/D$55*100 -> 100 | E111: =E55/E$55*100 -> 100 | F111: =F55/F$55*100 -> 100 | G111: =G55/G$55*100 -> 100 | H111: =H55/H$55*100 -> 100 | I111: =I55/I$55*100 -> 100 | J111: =J55/J$55*100 -> 100
B112: =B56 -> 2006 | C112: =C56/C$55*100 -> 119.65015 | D112: =D56/D$55*100 -> 106.8756 | E112: =E56/E$55*100 -> 108.02721 | F112: =F56/F$55*100 -> 109.78351 | G112: =G56/G$55*100 -> 112.60771 | H112: =H56/H$55*100 -> 87.088975 | I112: =I56/I$55*100 -> 109.19932 | J112: =J56/J$55*100 -> 112.91667
B113: =B57 -> 2007 | C113: =C57/C$55*100 -> 107.01166 | D113: =D57/D$55*100 -> 106.42789 | E113: =E57/E$55*100 -> 112.92517 | F113: =F57/F$55*100 -> 116.23647 | G113: =G57/G$55*100 -> 117.09751 | H113: =H57/H$55*100 -> 65.522244 | I113: =I57/I$55*100 -> 108.00681 | J113: =J57/J$55*100 -> 120
B114: =B58 -> 2008 | C114: =C58/C$55*100 -> 73.994169 | D114: =D58/D$55*100 -> 110.42533 | E114: =E58/E$55*100 -> 118.63946 | F114: =F58/F$55*100 -> 121.14904 | G114: =G58/G$55*100 -> 112.51701 | H114: =H58/H$55*100 -> 43.810445 | I114: =I58/I$55*100 -> 102.72572 | J114: =J58/J$55*100 -> 158.33333
B115: =B59 -> 2009 | C115: =C59/C$55*100 -> 62.755102 | D115: =D59/D$55*100 -> 81.387912 | E115: =E59/E$55*100 -> 117.68707 | F115: =F59/F$55*100 -> 123.81349 | G115: =G59/G$55*100 -> 88.752834 | H115: =H59/H$55*100 -> 26.789168 | I115: =I59/I$55*100 -> 85.860307 | J115: =J59/J$55*100 -> 102.91667
B116: =B60 -> 2010 | C116: =C60/C$55*100 -> 57.813411 | D116: =D60/D$55*100 -> 76.974736 | E116: =E60/E$55*100 -> 118.09524 | F116: =F60/F$55*100 -> 116.94421 | G116: =G60/G$55*100 -> 84.399093 | H116: =H60/H$55*100 -> 28.384913 | I116: =I60/I$55*100 -> 79.897785 | J116: =J60/J$55*100 -> 124.58333
B117: =B61 -> 2011 | C117: =C61/C$55*100 -> 51.690962 | D117: =D61/D$55*100 -> 77.454429 | E117: =E61/E$55*100 -> 108.29932 | F117: =F61/F$55*100 -> 107.91007 | G117: =G61/G$55*100 -> 89.070295 | H117: =H61/H$55*100 -> 29.448743 | I117: =I61/I$55*100 -> 75.809199 | J117: =J61/J$55*100 -> 160
B118: =B62 -> 2012 | C118: =C62/C$55*100 -> 78.19242 | D118: =D62/D$55*100 -> 82.731052 | E118: =E62/E$55*100 -> 107.07483 | F118: =F62/F$55*100 -> 108.49292 | G118: =G62/G$55*100 -> 96.417234 | H118: =H62/H$55*100 -> 37.765957 | I118: =I62/I$55*100 -> 62.350937 | J118: =J62/J$55*100 -> 165.41667
...

Sheet 6. Mutliple_Valuation
B1: SHEET 6: MULTIPLE VALUATION
B2: A. Valuation Framework & Multiple Selection
B3: Multiple | C3: Role | D3: Rationale
B4: EV / EBITDA | C4: Primary | D4: Best proxy for operating cash flow; normalizes D&A across asset-heavy quarrying peers with different reserve lives
B5: EV / Revenue | C5: Secondary | D5: Captures pricing power and margin differences; less volatile than earnings; useful for cross-border peers (CRH, CX)
B6: P / E | C6: Cross-check | D6: Widely followed but distorted by D&A, interest costs, and one-offs; used as market sentiment gauge only
B7: EV / EBIT | C7: Excluded | D7: Penalizes high-D&A operators; reserve depletion and quarry amortization inflate D&A beyond economic depreciation
B9: B. Peer Group Selection & Justification
B10: Criteria: (1) U.S. construction aggregates/materials as primary business, (2) Publicly traded with comparable financial disclosure, (3) Revenue >$2B to ensure scale comparability, (4) Aggregates or cement as core segment — excludes diversified industrials with minor materials exposure.
B12: Ticker | C12: Company | D12: Revenue ($mm) | E12: EBITDA Margin | F12: Selection Rationale | G12: Inclusion | H12: Adjustment
B13: VMC | C13: Vulcan Materials Co | D13: 7941.1 | E13: 0.29 | F13: Subject company; #2 U.S. crushed stone | G13: Subject | H13: —
B14: MLM | C14: Martin Marietta Materials | D14: 6150 | E14: 0.35 | F14: Closest comp; #1 crushed stone; duopoly with VMC | G14: Core Peer | H14: —
B15: CRH | C15: CRH plc | D15: 37447 | E15: 0.2 | F15: Global diversified; U.S. via Oldcastle; larger scale | G15: Core Peer | H15: Discount for non-U.S. mix
B16: CX | C16: CEMEX SAB de CV | D16: 16132 | E16: 0.14 | F16: Global cement/aggregates; Mexico-heavy | G16: Extended Peer | H16: Discount for EM risk
B17: EXP | C17: Eagle Materials Inc | D17: 2261 | E17: 0.34 | F17: Smaller; cement + gypsum; highest ROIC | G17: Extended Peer | H17: Premium for margin quality
B18: KNF | C18: Knife River Corp | D18: 3146 | E18: 0.16 | F18: Recently spun off; NW/Mountain; contracting mix | G18: Extended Peer | H18: Discount for limited history
B20: C. Current Peer Multiples (LTM)
B21: Ticker | C21: Mkt Cap ($mm) | D21: Net Debt ($mm) | E21: EV ($mm) | F21: Revenue ($mm) | G21: EBITDA ($mm) | H21: EV / EBITDA | I21: EV / Revenue | J21: Trailing P/E | K21: Forward P/E
B22: VMC | C22: 38649 | D22: 4190 | E22: =C22+D22 -> 42839 | F22: 7941 | G22: 2276 | H22: 18.8 | I22: 5.4 | J22: 31.71 | K22: 27.55
B23: MLM | C23: 39834 | D23: 5558 | E23: =C23+D23 -> 45392 | F23: 6150 | G23: 2130 | H23: 21.3 | I23: 7.4 | J23: 34.31 | K23: 27.17
B24: CRH | C24: 76145 | D24: 14091 | E24: =C24+D24 -> 90236 | F24: 37447 | G24: 7479 | H24: 12.1 | I24: 2.4 | J24: 18.23 | K24: 17.01
B25: CX | C25: 17323 | D25: 4804 | E25: =C25+D25 -> 22127 | F25: 16132 | G25: 2296 | H25: 9,6x | I25: 1.5 | J25: 37 | K25: 13.59
B26: EXP | C26: 6729 | D26: 1218 | E26: =C26+D26 -> 7947 | F26: 2261 | G26: 765 | H26: 10.4 | I26: 3.5 | J26: 13.08 | K26: 13.48
B27: KNF | C27: 4970 | D27: 1042 | E27: =C27+D27 -> 6012 | F27: 3146 | G27: 491 | H27: 12.2 | I27: 1.9 | J27: 29.31 | K27: 25.38
B29: Min | H29: =MIN(H22:H27) -> 10.4 | I29: =MIN(I22:I27) -> 1.5 | J29: =MIN(J22:J27) -> 13.08 | K29: =MIN(K22:K27) -> 13.48
B30: Max | H30: =MAX(H23:H27) -> 21.3 | I30: =MAX(I23:I27) -> 7.4 | J30: =MAX(J23:J27) -> 37 | K30: =MAX(K23:K27) -> 27.17
B31: Peer Mean (ex-VMC) | H31: =AVERAGE(H23:H27) -> 14 | I31: =AVERAGE(I23:I27) -> 3.34 | J31: =AVERAGE(J23:J27) -> 26.386 | K31: =AVERAGE(K23:K27) -> 19.326
B32: Peer Median (ex-VMC) | H32: =MEDIAN(H23:H27) -> 12.15 | I32: =MEDIAN(I23:I27) -> 2.4 | J32: =MEDIAN(J23:J27) -> 29.31 | K32: =MEDIAN(K23:K27) -> 17.01
B35: D. VMC Historical EV/EBITDA (FY2021–FY2025)
B36: Period | C36: Share Price ($) | D36: Shares (mm) | E36: Mkt Cap ($mm) | F36: Net Debt ($mm) | G36: EV ($mm) | H36: EBITDA ($mm) | I36: EV / EBITDA
B37: FY2025 | C37: 296 | D37: 131 | E37: 38649 | F37: ='9. Standardlized_Income'!D31-'9. Standardlized_Income'!D8 -> 4189.6 | G37: =E37+F37 -> 42838.6 | H37: ='2. Financial_Analyst'!G10 -> 2275.9 | I37: =G37/H37 -> 18.822708
B38: FY2024 | C38: 243.17 | D38: 132 | E38: =C38*D38 -> 32098.44 | F38: ='9. Standardlized_Income'!E31-'9. Standardlized_Income'!E8 -> 4768.1 | G38: =E38+F38 -> 36866.54 | H38: ='2. Financial_Analyst'!F10 -> 2028.3 | I38: =G38/H38 -> 18.176078
B39: FY2023 | C39: 223.99 | D39: 133 | E39: =C39*D39 -> 29790.67 | F39: ='9. Standardlized_Income'!F31-'9. Standardlized_Income'!F8 -> 2975.8 | G39: =E39+F39 -> 32766.47 | H39: ='2. Financial_Analyst'!E10 -> 1939.2 | I39: =G39/H39 -> 16.896901
B40: FY2022 | C40: 173.55 | D40: 133 | E40: =C40*D40 -> 23082.15 | F40: ='9. Standardlized_Income'!G31-'9. Standardlized_Income'!G8 -> 3871.4 | G40: =E40+F40 -> 26953.55 | H40: ='2. Financial_Analyst'!D10 -> 1617 | I40: =G40/H40 -> 16.668862
B41: FY2021 | C41: 204.79 | D41: 133 | E41: =C41*D41 -> 27237.07 | F41: ='9. Standardlized_Income'!H31-'9. Standardlized_Income'!H8 -> 3740.9 | G41: =E41+F41 -> 30977.97 | H41: ='2. Financial_Analyst'!C10 -> 1434.7 | I41: =G41/H41 -> 21.59195
B43: 5-year average | I43: =AVERAGE(I37:I41) -> 18.4313
B44: 5-year median | I44: =MEDIAN(I37:I41) -> 18.176078
B46: F. Target Price Derivation
B47: Key Assumptions | C47: Value | D47: Note
B48: Analysis Date | C48: 46115
B49: VMC Share Price ($) | C49: ='1. Share_Price_Analysis'!C815 -> 295.98 | D49: Approx. closing price ~Mar 20, 2026
B50: Shares Outstanding (mm) | C50: 130.58 | D50: Per CNBC, ~Mar 2026
B51: VMC Mkt Cap ($mm) | C51: =C49*C50 -> 38649.068
B52: VMC Net Debt ($mm) | C52: =D22 -> 4190
B53: VMC Enterprise Value ($mm) | C53: =C51+C52 -> 42839.068
B54: VMC LTM EBITDA ($mm) | C54: ='2. Financial_Analyst'!G10 -> 2275.9
B55: VMC LTM Revenue ($mm) | C55: ='2. Financial_Analyst'!G5 -> 7941.1
B56: VMC LTM Net Income ($mm) | C56: ='2. Financial_Analyst'!G12 -> 1076.7
B58: Multiple-based valuation
B59: Method | C59: Multiple | D59: Base ($mm) | E59: Implied EV ($mm) | F59: – Net Debt ($mm) | G59: Equity ($mm) | H59: Price ($)
B60: EV/EBITDA - Peer | C60: =H32 -> 12.15 | D60: =C54 -> 2275.9 | E60: =D60*C60 -> 27652.185 | F60: =C52 -> 4190 | G60: ='6. Mutliple_Valuation'!E60-'6. Mutliple_Valuation'!F60 -> 23462.185 | H60: =G60/C50 -> 179.67671 | J60: =2.4*79 -> 189.6
B61: EV/EBITDA - 5 Year | C61: =I43 -> 18.4313 | D61: =C54 -> 2275.9 | E61: =C61*D61 -> 41947.795 | F61: =C52 -> 4190 | G61: ='6. Mutliple_Valuation'!E61-'6. Mutliple_Valuation'!F61 -> 37757.795 | H61: =G61/C50 -> 289.1545
B62: EV / Revenue - Peer Median | C62: =I32 -> 2.4 | D62: =F22 -> 7941 | E62: =C62*D62 -> 19058.4 | F62: =C52 -> 4190 | G62: ='6. Mutliple_Valuation'!E62-'6. Mutliple_Valuation'!F62 -> 14868.4 | H62: =G62/C50 -> 113.8643
B63: P/E - Peer median | C63: =K31 -> 19.326 | D63: =C56 -> 1076.7 | E63: - | F63: - | G63: =C63*D63 -> 20808.304 | H63: =D63*C63/C50 -> 159.35292
B65: Implied Price Range | C65: Low | D65: =MIN(H60:H63) -> 113.8643 | E65: High | F65: =MAX(H60:H63) -> 289.1545 | G65: Midpoint | H65: =(F65+D65)/2 -> 201.5094
B66: Weighted Target Price | C66: Wt. | D66: EV/EBITDA Peer: 30% | E66: VMC 5Y EBITDA: 60% | F66: EV/Rev: 10% | G66: P/E: 20% | H66: =H60*20%+H61*50%+10%*H62+20%*H63 -> 223.76961
B67: G. Adjustments, Premium/Discount & Conclusion
B68: Adjustment Factor | C68: Direction | D68: Magnitude | E68: Rationale
B69: Infrastructure Tailwind (IIJA) | C69: Premium | D69: +5–10% | E69: ~$550B federal infra spending (2022-26); VMC Sun Belt footprint captures outsized share
B70: Aggregates Pricing Power | C70: Premium | D70: +3–5% | E70: 10%+ YoY pricing growth; local monopolies; pricing stickiness supports margin expansion
B71: Cyclical Risk (Housing Slowdown) | C71: Discount | D71: –3–5% | E71: Mortgage rates 6.5%+; residential starts soft; ~25% revenue residential-exposed
B72: Leverage & Acquisition Risk | C72: Neutral | D72: 0 | E72: Net Debt/EBITDA ~1.8x well within IG; recent M&A on track for integration
B73: Permitting Moat / ESG | C73: Premium | D73: +2–3% | E73: Avg permit >7 yrs to obtain; creates irreplaceable local monopoly positions
B75: Net Qualitative Adjustment | C75: 0.075 | D75: Net: premiums (~15%) less discounts (~7.5%), rounded
B78: CONCLUSION — Target Price Range (as of 04/03/2026)
B79: Primary Range (EV/EBITDA methods only) | C79: =MIN(I61,I62)*(1+C76) -> 0 | D79: to | E79: =MAX(I61,I62)*(1+C76) -> 0
B80: Adjusted Low | C80: =D65*(1+C75) -> 122.40412 | D80: Adjusted High | E80: =F65*(1+C75) -> 310.84109 | F80: Target Midpoint | G80: =(E80+C80)/2 -> 216.62261
B81: Weighted Target Price | C81: =H66*(1+C75) -> 240.55233
B82: Current Price | C82: =C49 -> 295.98
B83: Upside / (Downside) Weight Price | C83: =C81/C82 - 1 -> -0.1872683
B84: Implied Rating | C84: SELL

Sheet 7. DDM_Valuation
B1: 7. Dividend Discount Model (DDM) — Vulcan Materials Company (VMC)
A3: A | B3: Model Objective & Methodology
B5: Model | C5: 3-Stage Dividend Discount Model
B6: Currency | C6: USD / share
B7: Valuation Date | C7: 46085
B8: Fiscal Year Basis | C8: December fiscal year-end (FY2021 – FY2025)
B9: Purpose | C9: DDM is used as a secondary equity valuation cross-check given VMC is not primarily valued on dividend yield. Vulcan retains ~75% of earnings for growth capex and acquisitions; the model therefore complements the DCF (FCFF/FCFE) and multiple-based approaches.
A12: B | B12: Historical Dividend & Payout Profile
B14: Table 1 — Dividend History & Payout Ratios
B15: ($mm unless noted) | C15: FY2021 | D15: FY2022 | E15: FY2023 | F15: FY2024 | G15: FY2025 | H15: 5Y Avg / CAGR
B16: DPS ($) | C16: =Sheet10!G320 -> 1.48 | D16: =Sheet10!F320 -> 1.6 | E16: =Sheet10!E320 -> 1.72 | F16: =Sheet10!D320 -> 1.84 | G16: =Sheet10!C320 -> 1.96 | H16: =(G16/C16)^(1/4)-1 -> 0.072750162
B17: DPS Growth (%) | C17: — | D17: =D16/C16-1 -> 0.081081081 | E17: =E16/D16-1 -> 0.075 | F17: =F16/E16-1 -> 0.069767442 | G17: =G16/F16-1 -> 0.065217391 | H17: =AVERAGE(D17:G17) -> 0.072766479
B18: EPS - Diluted ($) | C18: =Sheet10!G309 -> 5.05 | D18: =Sheet10!F309 -> 4.45 | E18: =Sheet10!E309 -> 7.06 | F18: =Sheet10!D309 -> 6.91 | G18: =Sheet10!C309 -> 8.15 | H18: =(G18/C18)^(1/4)-1 -> 0.12711066
B19: Net Income | C19: ='9. Standardlized_Income'!H44 -> 670.8 | D19: ='9. Standardlized_Income'!G44 -> 575.6 | E19: ='9. Standardlized_Income'!F44 -> 933.2 | F19: ='9. Standardlized_Income'!E44 -> 911.9 | G19: ='9. Standardlized_Income'!D44 -> 1076.7 | H19: =(G19/C19)^(1/4)-1 -> 0.12557753
B20: Dividends Paid | C20: ='9. Standardlized_Income'!H59 -> 196.4 | D20: ='9. Standardlized_Income'!G59 -> 212.6 | E20: ='9. Standardlized_Income'!F59 -> 228.4 | F20: ='9. Standardlized_Income'!E59 -> 244.4 | G20: ='9. Standardlized_Income'!D59 -> 259.8 | H20: =(G20/C20)^(1/4)-1 -> 0.072443486
B21: Dividend Payout Ratio (Div / NI) | C21: =C20/C19 -> 0.29278473 | D21: =D20/D19 -> 0.36935372 | E21: =E20/E19 -> 0.24474925 | F21: =F20/F19 -> 0.26801184 | G21: =G20/G19 -> 0.24129284 | H21: =AVERAGE(C21:G21) -> 0.28323848
B22: Retention Ratio (1 – Payout) | C22: =1-C21 -> 0.70721527 | D22: =1-D21 -> 0.63064628 | E22: =1-E21 -> 0.75525075 | F22: =1-F21 -> 0.73198816 | G22: =1-G21 -> 0.75870716 | H22: =AVERAGE(C22:G22) -> 0.71676152
B25: Table 2 — Cash Flow Coverage of Dividends
B26: ($mm unless noted) | C26: FY2021 | D26: FY2022 | E26: FY2023 | F26: FY2024 | G26: FY2025 | H26: 5Y Avg
B27: Net Cash from Operations | C27: ='9. Standardlized_Income'!H51 -> 1011.9 | D27: ='9. Standardlized_Income'!G51 -> 1148.2 | E27: ='9. Standardlized_Income'!F51 -> 1536.8 | F27: ='9. Standardlized_Income'!E51 -> 1409.6 | G27: ='9. Standardlized_Income'!D51 -> 1813 | H27: =AVERAGE(C27:G27) -> 1383.9
B28: Capital Expenditures | C28: ='9. Standardlized_Income'!H52 -> 451.3 | D28: ='9. Standardlized_Income'!G52 -> 612.6 | E28: ='9. Standardlized_Income'!F52 -> 872.6 | F28: ='9. Standardlized_Income'!E52 -> 603.5 | G28: ='9. Standardlized_Income'!D52 -> 677.7 | H28: =AVERAGE(C28:G28) -> 643.54
B29: Free Cash Flow (OCF – Capex) | C29: =C27-C28 -> 560.6 | D29: =D27-D28 -> 535.6 | E29: =E27-E28 -> 664.2 | F29: =F27-F28 -> 806.1 | G29: =G27-G28 -> 1135.3 | H29: =AVERAGE(C29:G29) -> 740.36
B30: Dividends Paid | C30: =C20 -> 196.4 | D30: =D20 -> 212.6 | E30: =E20 -> 228.4 | F30: =F20 -> 244.4 | G30: =G20 -> 259.8 | H30: =AVERAGE(C30:G30) -> 228.32
B31: FCF after Dividends | C31: =C29-C30 -> 364.2 | D31: =D29-D30 -> 323 | E31: =E29-E30 -> 435.8 | F31: =F29-F30 -> 561.7 | G31: =G29-G30 -> 875.5 | H31: =AVERAGE(C31:G31) -> 512.04
B33: Free Cash Flow to Equity (FCFE) | C33: =Sheet10!G436 -> 911.9 | D33: =Sheet10!F436 -> 632.8 | E33: =Sheet10!E436 -> 627.5 | F33: =Sheet10!D436 -> 2297.3 | G33: =Sheet10!C436 -> 198 | H33: =AVERAGE(C33:G33) -> 933.5
B35: Div / FCF | C35: =C30/C29 -> 0.35033892 | D35: =D30/D29 -> 0.39693801 | E35: =E30/E29 -> 0.34387233 | F35: =F30/F29 -> 0.30318819 | G35: =G30/G29 -> 0.22883819 | H35: =AVERAGE(C35:G35) -> 0.32463513
B36: Div / FCFE | C36: =IF(C33<=0,"n/m",C30/C33) -> 0.21537449 | D36: =IF(D33<=0,"n/m",D30/D33) -> 0.33596713 | E36: =IF(E33<=0,"n/m",E30/E33) -> 0.36398406 | F36: =IF(F33<=0,"n/m",F30/F33) -> 0.10638576 | G36: =IF(G33<=0,"n/m",G30/G33) -> 1.3121212 | H36: {=AVERAGE(IF(ISNUMBER(C36:G36),C36:G36))} -> 0.46676653
B37: FCF Dividend Coverage (x) | C37: =C29/C30 -> 2.8543788 | D37: =D29/D30 -> 2.519285 | E37: =E29/E30 -> 2.908056 | F37: =F29/F30 -> 3.2982815 | G37: =G29/G30 -> 4.3698999 | H37: =AVERAGE(C37:G37) -> 3.1899803
B38: FCFE Dividend Coverage (x) | C38: =IF(C33<=0,"n/m",C33/C30) -> 4.6430754 | D38: =IF(D33<=0,"n/m",D33/D30) -> 2.9764817 | E38: =IF(E33<=0,"n/m",E33/E30) -> 2.747373 | F38: =IF(F33<=0,"n/m",F33/F30) -> 9.3997545 | G38: =IF(G33<=0,"n/m",G33/G30) -> 0.76212471 | H38: {=AVERAGE(IF(ISNUMBER(C38:G38),C38:G38))} -> 4.1057619
B40: Historical Conclusion
B41: 1. VMC has delivered 17 consecutive annual dividend increases; the 5-year DPS CAGR of 7.3% reflects steady, disciplined growth well above inflation.
B42: 2. The average payout ratio of 28.3% is deliberately conservative — VMC retains ~72% of earnings to fund organic growth capex and bolt-on acquisitions (e.g., Wake Stone Corp. in FY2025).
B43: 3. Free cash flow comfortably covers dividends at 3.2x on average; even in FY2025 (heavy acquisition year), FCF coverage remained 4.4x, confirming strong dividend sustainability.
B44: 4. FCFE coverage is volatile (0.8x–9.4x) due to lumpy M&A-driven financing flows — this is structural for an aggregates roll-up, not a credit concern.
B45: 5. Given the low payout and growth orientation, a DDM will structurally undervalue VMC; the model serves as a floor valuation and cross-check against the DCF.
A47: C | B47: DDM Assumptions
B49: Cost of Equity (CAPM) | C49: Value | D49: Source / Justification | E49: Required Return Cross-Checks | F49: Value | G49: Method / Use
B50: Risk-Free Rate (Rf) | C50: 0.04 | D50: 10-Year US Treasury yield (Sheet 1) | E50: CAPM (selected) | F50: =C53 -> 0.085523129 | G50: Primary Ke used in valuation
B51: Equity Risk Premium (ERP) | C51: 0.055 | D51: Damodaran US ERP estimate, Jan 2026 | E51: Market Return Proxy (Rf + ERP) | F51: =C50+C51 -> 0.095 | G51: Cross-check assuming beta of 1.0
B52: Beta vs S&P 500 (β) | C52: ='1. Share_Price_Analysis'!C17 -> 0.82769326 | D52: 3-year weekly regression vs SPY (Sheet 1) | E52: Dividend Yield + g | F52: =D76/$C$63+$C$58 -> 0.038326779 | G52: Cross-check only; low for VMC because payout is conservative
B53: Cost of Equity (Ke = Rf + β × ERP) | C53: =C50+C51*C52 -> 0.085523129 | E53: Selected Cost of Equity | F53: =C53 -> 0.085523129 | G53: Retain CAPM as the valuation discount rate
B55: Growth & Dividend Assumptions | C55: Value | D55: Source / Justification
B56: Forecast Diluted EPS Growth Stage 1 (Yr 1–2) | C56: 0.08 | D56: Infrastructure tailwind (IIJA) + pricing power; above hist. 12.7% EPS CAGR in line with consensus
B57: Forecast Diluted EPS Growth Stage 2 (Yr 3–4) | C57: 0.06 | D57: Normalizing growth as IIJA spending peaks; approaching mid-cycle
B58: Terminal Growth Rate (g) | C58: 0.03 | D58: Long-run US nominal GDP growth proxy (~2% real + ~1% inflation)
B59: Target Payout Ratio | C59: 0.28 | D59: In line with 5-year historical average (28.3%); management guidance: modest annual increases
B60: Last Actual DPS (FY2025) | C60: =G16 -> 1.96
B61: Last Actual EPS Diluted (FY2025) | C61: =G18 -> 8.15
B62: Shares Outstanding (mm) | C62: ='6. Mutliple_Valuation'!C50 -> 130.58
B63: Current Share Price ($) | C63: ='6. Mutliple_Valuation'!C49 -> 295.98
B64: Net Debt ($mm) | C64: ='6. Mutliple_Valuation'!C52 -> 4190
B68: DDM Forecast & Valuation
C70: Base (FY25) | D70: 2026E | E70: 2027E | F70: 2028E | G70: 2029E | H70: 2030E | I70: Terminal
B71: Year (n) | C71: 0 | D71: 1 | E71: 2 | F71: 3 | G71: 4 | H71: 5 | I71: 5
B72: Stage | C72: — | D72: Stage 1 | E72: Stage 1 | F72: Stage 2 | G72: Stage 2 | H72: Stage 2 | I72: Terminal
B73: EPS Growth Rate | C73: — | D73: =$C$56 -> 0.08 | E73: =$C$56 -> 0.08 | F73: =$C$57 -> 0.06 | G73: =$C$57 -> 0.06 | H73: =$C$57 -> 0.06 | I73: =$C$58 -> 0.03
B74: Forecast EPS Diluted ($) | C74: =C61 -> 8.15 | D74: =C74*(1+D73) -> 8.802 | E74: =D74*(1+E73) -> 9.50616 | F74: =E74*(1+F73) -> 10.07653 | G74: =F74*(1+G73) -> 10.681121 | H74: =G74*(1+H73) -> 11.321989
B75: Target Payout Ratio | C75: 0.24 | D75: =C59 -> 0.28 | E75: =$C$59 -> 0.28 | F75: =$C$59 -> 0.28 | G75: =$C$59 -> 0.28 | H75: =$C$59 -> 0.28
B76: Forecast DPS ($) | C76: =C74*C75 -> 1.956 | D76: =D74*D75 -> 2.46456 | E76: =E74*E75 -> 2.6617248 | F76: =F74*F75 -> 2.8214283 | G76: =G74*G75 -> 2.990714 | H76: =H74*H75 -> 3.1701568
B77: Implied DPS Growth | C77: — | D77: =D76/C76-1 -> 0.26 | E77: =E76/D76-1 -> 0.08 | F77: =F76/E76-1 -> 0.06 | G77: =G76/F76-1 -> 0.06 | H77: =H76/G76-1 -> 0.06
B79: Discount Factor (1/(1+Ke)^n) | D79: =1/(1+$C$53)^D71 -> 0.92121483 | E79: =1/(1+$C$53)^E71 -> 0.84863675 | F79: =1/(1+$C$53)^F71 -> 0.78177676 | G79: =1/(1+$C$53)^G71 -> 0.72018434 | H79: =1/(1+$C$53)^H71 -> 0.66344449 | I79: =1/(1+$C$53)^I71 -> 0.66344449
B80: PV of Forecast DPS ($) | D80: =D76*D79 -> 2.2703892 | E80: =E76*E79 -> 2.2588375 | F80: =F76*F79 -> 2.2057271 | G80: =G76*G79 -> 2.1538654 | H80: =H76*H79 -> 2.1032231
B81: Terminal Value per Share | I81: =H76*(1+$C$58)/($C$53-$C$58) -> 58.809033
B82: PV of Terminal Value | I82: =I81*I79 -> 39.016529
B84: Valuation Summary | C84: Per Share ($)
B85: Sum of PV of Dividends (Yr 1–5) | C85: =SUM(D80:H80) -> 10.992042
B86: PV of Terminal Value | C86: =I82 -> 39.016529
B87: Implied Equity Value per Share | C87: =C85+C86 -> 50.008571
B89: Current Share Price | C89: =C63 -> 295.98
B90: Premium / (Discount) to Market | C90: =C87/C89-1 -> -0.83104071
B91: Recommendation | C91: =IF(C90>0.1,"BUY",IF(C90<-0.1,"SELL","HOLD")) -> SELL
B93: Value Composition | C93: Weight
B94: PV of Dividends (Yr 1-5) | C94: =C85/C87 -> 0.21980317
B95: PV of Terminal Value | C95: =C86/C87 -> 0.78019683
B97: Enterprise Value Bridge | C97: $mm
B98: Equity Value per Share | C98: =C87 -> 50.008571
B99: x Shares Outstanding (mm) | C99: =C62 -> 130.58
B100: Equity Value ($mm) | C100: =C98*C99 -> 6530.1192
B101: + Net Debt ($mm) | C101: =C64 -> 4190
B102: Enterprise Value ($mm) | C102: =C100+C101 -> 10720.119
A104: E | B104: Sensitivity Analysis
B106: Implied Share Price ($): Cost of Equity vs Terminal Growth Rate
B107: Ke \ g | C107: 0.015 | D107: 0.02 | E107: 0.025 | F107: 0.03 | G107: 0.035 | H107: 0.04 | I107: 0.045
B108: 0.065 | C108: =IF(C$107>=$B108,"-",$C$61*(1+$C$56)*$C$59/(1+$B108)^1+$C$61*(1+$C$56)^2*$C$59/(1+$B108)^2+$C$61*(1+$C$56)^2*(1+$C$57)*$C$59/(1+$B108)^3+$C$61*(1+$C$56)^2*(1+$C$57)^2*$C$59/(1+$B108)^4+$C$61*(1+$C$56)^2*(1+$C$57)^3*$C$59/(1+$B108)^5+($C$61*(1+$C$56)^2*(1+$C$57)^3*$C$59*(1+C$107)/($B108-C$107))/(1+$B108)^5) -> 58.606065 | D108: =IF(D$107>=$B108,"-",$C$61*(1+$C$56)*$C$59/(1+$B108)^1+$C$61*(1+$C$56)^2*$C$59/(1+$B108)^2+$C$61*(1+$C$56)^2*(1+$C$57)*$C$59/(1+$B108)^3+$C$61*(1+$C$56)^2*(1+$C$57)^2*$C$59/(1+$B108)^4+$C$61*(1+$C$56)^2*(1+$C$57)^3*$C$59/(1+$B108)^5+($C$61*(1+$C$56)^2*(1+$C$57)^3*$C$59*(1+D$107)/($B108-D$107))/(1+$B108)^5) -> 64.082145 | E108: =IF(E$107>=$B108,"-",$C$61*(1+$C$56)*$C$59/(1+$B108)^1+$C$61*(1+$C$56)^2*$C$59/(1+$B108)^2+$C$61*(1+$C$56)^2*(1+$C$57)*$C$59/(1+$B108)^3+$C$61*(1+$C$56)^2*(1+$C$57)^2*$C$59/(1+$B108)^4+$C$61*(1+$C$56)^2*(1+$C$57)^3*$C$59/(1+$B108)^5+($C$61*(1+$C$56)^2*(1+$C$57)^3*$C$59*(1+E$107)/($B108-E$107))/(1+$B108)^5) -> 70.927246 | F108: =IF(F$107>=$B108,"-",$C$61*(1+$C$56)*$C$59/(1+$B108)^1+$C$61*(1+$C$56)^2*$C$59/(1+$B108)^2+$C$61*(1+$C$56)^2*(1+$C$57)*$C$59/(1+$B108)^3+$C$61*(1+$C$56)^2*(1+$C$57)^2*$C$59/(1+$B108)^4+$C$61*(1+$C$56)^2*(1+$C$57)^3*$C$59/(1+$B108)^5+($C$61*(1+$C$56)^2*(1+$C$57)^3*$C$59*(1+F$107)/($B108-F$107))/(1+$B108)^5) -> 79.728089 | G108: =IF(G$107>=$B108,"-",$C$61*(1+$C$56)*$C$59/(1+$B108)^1+$C$61*(1+$C$56)^2*$C$59/(1+$B108)^2+$C$61*(1+$C$56)^2*(1+$C$57)*$C$59/(1+$B108)^3+$C$61*(1+$C$56)^2*(1+$C$57)^2*$C$59/(1+$B108)^4+$C$61*(1+$C$56)^2*(1+$C$57)^3*$C$59/(1+$B108)^5+($C$61*(1+$C$56)^2*(1+$C$57)^3*$C$59*(1+G$107)/($B108-G$107))/(1+$B108)^5) -> 91.462546 | H108: =IF(H$107>=$B108,"-",$C$61*(1+$C$56)*$C$59/(1+$B108)^1+$C$61*(1+$C$56)^2*$C$59/(1+$B108)^2+$C$61*(1+$C$56)^2*(1+$C$57)*$C$59/(1+$B108)^3+$C$61*(1+$C$56)^2*(1+$C$57)^2*$C$59/(1+$B108)^4+$C$61*(1+$C$56)^2*(1+$C$57)^3*$C$59/(1+$B108)^5+($C$61*(1+$C$56)^2*(1+$C$57)^3*$C$59*(1+H$107)/($B108-H$107))/(1+$B108)^5) -> 107.89079 | I108: =IF(I$107>=$B108,"-",$C$61*(1+$C$56)*$C$59/(1+$B108)^1+$C$61*(1+$C$56)^2*$C$59/(1+$B108)^2+$C$61*(1+$C$56)^2*(1+$C$57)*$C$59/(1+$B108)^3+$C$61*(1+$C$56)^2*(1+$C$57)^2*$C$59/(1+$B108)^4+$C$61*(1+$C$56)^2*(1+$C$57)^3*$C$59/(1+$B108)^5+($C$61*(1+$C$56)^2*(1+$C$57)^3*$C$59*(1+I$107)/($B108-I$107))/(1+$B108)^5) -> 132.53315
B109: 0.075 | C109: =IF(C$107>=$B109,"-",$C$61*(1+$C$56)*$C$59/(1+$B109)^1+$C$61*(1+$C$56)^2*$C$59/(1+$B109)^2+$C$61*(1+$C$56)^2*(1+$C$57)*$C$59/(1+$B109)^3+$C$61*(1+$C$56)^2*(1+$C$57)^2*$C$59/(1+$B109)^4+$C$61*(1+$C$56)^2*(1+$C$57)^3*$C$59/(1+$B109)^5+($C$61*(1+$C$56)^2*(1+$C$57)^3*$C$59*(1+C$107)/($B109-C$107))/(1+$B109)^5) -> 48.670063 | D109: =IF(D$107>=$B109,"-",$C$61*(1+$C$56)*$C$59/(1+$B109)^1+$C$61*(1+$C$56)^2*$C$59/(1+$B109)^2+$C$61*(1+$C$56)^2*(1+$C$57)*$C$59/(1+$B109)^3+$C$61*(1+$C$56)^2*(1+$C$57)^2*$C$59/(1+$B109)^4+$C$61*(1+$C$56)^2*(1+$C$57)^3*$C$59/(1+$B109)^5+($C$61*(1+$C$56)^2*(1+$C$57)^3*$C$59*(1+D$107)/($B109-D$107))/(1+$B109)^5) -> 52.266753 | E109: =IF(E$107>=$B109,"-",$C$61*(1+$C$56)*$C$59/(1+$B109)^1+$C$61*(1+$C$56)^2*$C$59/(1+$B109)^2+$C$61*(1+$C$56)^2*(1+$C$57)*$C$59/(1+$B109)^3+$C$61*(1+$C$56)^2*(1+$C$57)^2*$C$59/(1+$B109)^4+$C$61*(1+$C$56)^2*(1+$C$57)^3*$C$59/(1+$B109)^5+($C$61*(1+$C$56)^2*(1+$C$57)^3*$C$59*(1+E$107)/($B109-E$107))/(1+$B109)^5) -> 56.58278 | F109: =IF(F$107>=$B109,"-",$C$61*(1+$C$56)*$C$59/(1+$B109)^1+$C$61*(1+$C$56)^2*$C$59/(1+$B109)^2+$C$61*(1+$C$56)^2*(1+$C$57)*$C$59/(1+$B109)^3+$C$61*(1+$C$56)^2*(1+$C$57)^2*$C$59/(1+$B109)^4+$C$61*(1+$C$56)^2*(1+$C$57)^3*$C$59/(1+$B109)^5+($C$61*(1+$C$56)^2*(1+$C$57)^3*$C$59*(1+F$107)/($B109-F$107))/(1+$B109)^5) -> 61.857925 | G109: =IF(G$107>=$B109,"-",$C$61*(1+$C$56)*$C$59/(1+$B109)^1+$C$61*(1+$C$56)^2*$C$59/(1+$B109)^2+$C$61*(1+$C$56)^2*(1+$C$57)*$C$59/(1+$B109)^3+$C$61*(1+$C$56)^2*(1+$C$57)^2*$C$59/(1+$B109)^4+$C$61*(1+$C$56)^2*(1+$C$57)^3*$C$59/(1+$B109)^5+($C$61*(1+$C$56)^2*(1+$C$57)^3*$C$59*(1+G$107)/($B109-G$107))/(1+$B109)^5) -> 68.451856 | H109: =IF(H$107>=$B109,"-",$C$61*(1+$C$56)*$C$59/(1+$B109)^1+$C$61*(1+$C$56)^2*$C$59/(1+$B109)^2+$C$61*(1+$C$56)^2*(1+$C$57)*$C$59/(1+$B109)^3+$C$61*(1+$C$56)^2*(1+$C$57)^2*$C$59/(1+$B109)^4+$C$61*(1+$C$56)^2*(1+$C$57)^3*$C$59/(1+$B109)^5+($C$61*(1+$C$56)^2*(1+$C$57)^3*$C$59*(1+H$107)/($B109-H$107))/(1+$B109)^5) -> 76.929767 | I109: =IF(I$107>=$B109,"-",$C$61*(1+$C$56)*$C$59/(1+$B109)^1+$C$61*(1+$C$56)^2*$C$59/(1+$B109)^2+$C$61*(1+$C$56)^2*(1+$C$57)*$C$59/(1+$B109)^3+$C$61*(1+$C$56)^2*(1+$C$57)^2*$C$59/(1+$B109)^4+$C$61*(1+$C$56)^2*(1+$C$57)^3*$C$59/(1+$B109)^5+($C$61*(1+$C$56)^2*(1+$C$57)^3*$C$59*(1+I$107)/($B109-I$107))/(1+$B109)^5) -> 88.233648
B110: 0.085 | C110: =IF(C$107>=$B110,"-",$C$61*(1+$C$56)*$C$59/(1+$B110)^1+$C$61*(1+$C$56)^2*$C$59/(1+$B110)^2+$C$61*(1+$C$56)^2*(1+$C$57)*$C$59/(1+$B110)^3+$C$61*(1+$C$56)^2*(1+$C$57)^2*$C$59/(1+$B110)^4+$C$61*(1+$C$56)^2*(1+$C$57)^3*$C$59/(1+$B110)^5+($C$61*(1+$C$56)^2*(1+$C$57)^3*$C$59*(1+C$107)/($B110-C$107))/(1+$B110)^5) -> 41.578065 | D110: =IF(D$107>=$B110,"-",$C$61*(1+$C$56)*$C$59/(1+$B110)^1+$C$61*(1+$C$56)^2*$C$59/(1+$B110)^2+$C$61*(1+$C$56)^2*(1+$C$57)*$C$59/(1+$B110)^3+$C$61*(1+$C$56)^2*(1+$C$57)^2*$C$59/(1+$B110)^4+$C$61*(1+$C$56)^2*(1+$C$57)^3*$C$59/(1+$B110)^5+($C$61*(1+$C$56)^2*(1+$C$57)^3*$C$59*(1+D$107)/($B110-D$107))/(1+$B110)^5) -> 44.091805 | E110: =IF(E$107>=$B110,"-",$C$61*(1+$C$56)*$C$59/(1+$B110)^1+$C$61*(1+$C$56)^2*$C$59/(1+$B110)^2+$C$61*(1+$C$56)^2*(1+$C$57)*$C$59/(1+$B110)^3+$C$61*(1+$C$56)^2*(1+$C$57)^2*$C$59/(1+$B110)^4+$C$61*(1+$C$56)^2*(1+$C$57)^3*$C$59/(1+$B110)^5+($C$61*(1+$C$56)^2*(1+$C$57)^3*$C$59*(1+E$107)/($B110-E$107))/(1+$B110)^5) -> 47.024502 | F110: =IF(F$107>=$B110,"-",$C$61*(1+$C$56)*$C$59/(1+$B110)^1+$C$61*(1+$C$56)^2*$C$59/(1+$B110)^2+$C$61*(1+$C$56)^2*(1+$C$57)*$C$59/(1+$B110)^3+$C$61*(1+$C$56)^2*(1+$C$57)^2*$C$59/(1+$B110)^4+$C$61*(1+$C$56)^2*(1+$C$57)^3*$C$59/(1+$B110)^5+($C$61*(1+$C$56)^2*(1+$C$57)^3*$C$59*(1+F$107)/($B110-F$107))/(1+$B110)^5) -> 50.490417 | G110: =IF(G$107>=$B110,"-",$C$61*(1+$C$56)*$C$59/(1+$B110)^1+$C$61*(1+$C$56)^2*$C$59/(1+$B110)^2+$C$61*(1+$C$56)^2*(1+$C$57)*$C$59/(1+$B110)^3+$C$61*(1+$C$56)^2*(1+$C$57)^2*$C$59/(1+$B110)^4+$C$61*(1+$C$56)^2*(1+$C$57)^3*$C$59/(1+$B110)^5+($C$61*(1+$C$56)^2*(1+$C$57)^3*$C$59*(1+G$107)/($B110-G$107))/(1+$B110)^5) -> 54.649514 | H110: =IF(H$107>=$B110,"-",$C$61*(1+$C$56)*$C$59/(1+$B110)^1+$C$61*(1+$C$56)^2*$C$59/(1+$B110)^2+$C$61*(1+$C$56)^2*(1+$C$57)*$C$59/(1+$B110)^3+$C$61*(1+$C$56)^2*(1+$C$57)^2*$C$59/(1+$B110)^4+$C$61*(1+$C$56)^2*(1+$C$57)^3*$C$59/(1+$B110)^5+($C$61*(1+$C$56)^2*(1+$C$57)^3*$C$59*(1+H$107)/($B110-H$107))/(1+$B110)^5) -> 59.732856 | I110: =IF(I$107>=$B110,"-",$C$61*(1+$C$56)*$C$59/(1+$B110)^1+$C$61*(1+$C$56)^2*$C$59/(1+$B110)^2+$C$61*(1+$C$56)^2*(1+$C$57)*$C$59/(1+$B110)^3+$C$61*(1+$C$56)^2*(1+$C$57)^2*$C$59/(1+$B110)^4+$C$61*(1+$C$56)^2*(1+$C$57)^3*$C$59/(1+$B110)^5+($C$61*(1+$C$56)^2*(1+$C$57)^3*$C$59*(1+I$107)/($B110-I$107))/(1+$B110)^5) -> 66.087032
B111: 0.095 | C111: =IF(C$107>=$B111,"-",$C$61*(1+$C$56)*$C$59/(1+$B111)^1+$C$61*(1+$C$56)^2*$C$59/(1+$B111)^2+$C$61*(1+$C$56)^2*(1+$C$57)*$C$59/(1+$B111)^3+$C$61*(1+$C$56)^2*(1+$C$57)^2*$C$59/(1+$B111)^4+$C$61*(1+$C$56)^2*(1+$C$57)^3*$C$59/(1+$B111)^5+($C$61*(1+$C$56)^2*(1+$C$57)^3*$C$59*(1+C$107)/($B111-C$107))/(1+$B111)^5) -> 36.263358 | D111: =IF(D$107>=$B111,"-",$C$61*(1+$C$56)*$C$59/(1+$B111)^1+$C$61*(1+$C$56)^2*$C$59/(1+$B111)^2+$C$61*(1+$C$56)^2*(1+$C$57)*$C$59/(1+$B111)^3+$C$61*(1+$C$56)^2*(1+$C$57)^2*$C$59/(1+$B111)^4+$C$61*(1+$C$56)^2*(1+$C$57)^3*$C$59/(1+$B111)^5+($C$61*(1+$C$56)^2*(1+$C$57)^3*$C$59*(1+D$107)/($B111-D$107))/(1+$B111)^5) -> 38.100924 | E111: =IF(E$107>=$B111,"-",$C$61*(1+$C$56)*$C$59/(1+$B111)^1+$C$61*(1+$C$56)^2*$C$59/(1+$B111)^2+$C$61*(1+$C$56)^2*(1+$C$57)*$C$59/(1+$B111)^3+$C$61*(1+$C$56)^2*(1+$C$57)^2*$C$59/(1+$B111)^4+$C$61*(1+$C$56)^2*(1+$C$57)^3*$C$59/(1+$B111)^5+($C$61*(1+$C$56)^2*(1+$C$57)^3*$C$59*(1+E$107)/($B111-E$107))/(1+$B111)^5) -> 40.201 | F111: =IF(F$107>=$B111,"-",$C$61*(1+$C$56)*$C$59/(1+$B111)^1+$C$61*(1+$C$56)^2*$C$59/(1+$B111)^2+$C$61*(1+$C$56)^2*(1+$C$57)*$C$59/(1+$B111)^3+$C$61*(1+$C$56)^2*(1+$C$57)^2*$C$59/(1+$B111)^4+$C$61*(1+$C$56)^2*(1+$C$57)^3*$C$59/(1+$B111)^5+($C$61*(1+$C$56)^2*(1+$C$57)^3*$C$59*(1+F$107)/($B111-F$107))/(1+$B111)^5) -> 42.624164 | G111: =IF(G$107>=$B111,"-",$C$61*(1+$C$56)*$C$59/(1+$B111)^1+$C$61*(1+$C$56)^2*$C$59/(1+$B111)^2+$C$61*(1+$C$56)^2*(1+$C$57)*$C$59/(1+$B111)^3+$C$61*(1+$C$56)^2*(1+$C$57)^2*$C$59/(1+$B111)^4+$C$61*(1+$C$56)^2*(1+$C$57)^3*$C$59/(1+$B111)^5+($C$61*(1+$C$56)^2*(1+$C$57)^3*$C$59*(1+G$107)/($B111-G$107))/(1+$B111)^5) -> 45.451189 | H111: =IF(H$107>=$B111,"-",$C$61*(1+$C$56)*$C$59/(1+$B111)^1+$C$61*(1+$C$56)^2*$C$59/(1+$B111)^2+$C$61*(1+$C$56)^2*(1+$C$57)*$C$59/(1+$B111)^3+$C$61*(1+$C$56)^2*(1+$C$57)^2*$C$59/(1+$B111)^4+$C$61*(1+$C$56)^2*(1+$C$57)^3*$C$59/(1+$B111)^5+($C$61*(1+$C$56)^2*(1+$C$57)^3*$C$59*(1+H$107)/($B111-H$107))/(1+$B111)^5) -> 48.792219 | I111: =IF(I$107>=$B111,"-",$C$61*(1+$C$56)*$C$59/(1+$B111)^1+$C$61*(1+$C$56)^2*$C$59/(1+$B111)^2+$C$61*(1+$C$56)^2*(1+$C$57)*$C$59/(1+$B111)^3+$C$61*(1+$C$56)^2*(1+$C$57)^2*$C$59/(1+$B111)^4+$C$61*(1+$C$56)^2*(1+$C$57)^3*$C$59/(1+$B111)^5+($C$61*(1+$C$56)^2*(1+$C$57)^3*$C$59*(1+I$107)/($B111-I$107))/(1+$B111)^5) -> 52.801455
B112: 0.105 | C112: =IF(C$107>=$B112,"-",$C$61*(1+$C$56)*$C$59/(1+$B112)^1+$C$61*(1+$C$56)^2*$C$59/(1+$B112)^2+$C$61*(1+$C$56)^2*(1+$C$57)*$C$59/(1+$B112)^3+$C$61*(1+$C$56)^2*(1+$C$57)^2*$C$59/(1+$B112)^4+$C$61*(1+$C$56)^2*(1+$C$57)^3*$C$59/(1+$B112)^5+($C$61*(1+$C$56)^2*(1+$C$57)^3*$C$59*(1+C$107)/($B112-C$107))/(1+$B112)^5) -> 32.133334 | D112: =IF(D$107>=$B112,"-",$C$61*(1+$C$56)*$C$59/(1+$B112)^1+$C$61*(1+$C$56)^2*$C$59/(1+$B112)^2+$C$61*(1+$C$56)^2*(1+$C$57)*$C$59/(1+$B112)^3+$C$61*(1+$C$56)^2*(1+$C$57)^2*$C$59/(1+$B112)^4+$C$61*(1+$C$56)^2*(1+$C$57)^3*$C$59/(1+$B112)^5+($C$61*(1+$C$56)^2*(1+$C$57)^3*$C$59*(1+D$107)/($B112-D$107))/(1+$B112)^5) -> 33.523096 | E112: =IF(E$107>=$B112,"-",$C$61*(1+$C$56)*$C$59/(1+$B112)^1+$C$61*(1+$C$56)^2*$C$59/(1+$B112)^2+$C$61*(1+$C$56)^2*(1+$C$57)*$C$59/(1+$B112)^3+$C$61*(1+$C$56)^2*(1+$C$57)^2*$C$59/(1+$B112)^4+$C$61*(1+$C$56)^2*(1+$C$57)^3*$C$59/(1+$B112)^5+($C$61*(1+$C$56)^2*(1+$C$57)^3*$C$59*(1+E$107)/($B112-E$107))/(1+$B112)^5) -> 35.086577 | F112: =IF(F$107>=$B112,"-",$C$61*(1+$C$56)*$C$59/(1+$B112)^1+$C$61*(1+$C$56)^2*$C$59/(1+$B112)^2+$C$61*(1+$C$56)^2*(1+$C$57)*$C$59/(1+$B112)^3+$C$61*(1+$C$56)^2*(1+$C$57)^2*$C$59/(1+$B112)^4+$C$61*(1+$C$56)^2*(1+$C$57)^3*$C$59/(1+$B112)^5+($C$61*(1+$C$56)^2*(1+$C$57)^3*$C$59*(1+F$107)/($B112-F$107))/(1+$B112)^5) -> 36.858523 | G112: =IF(G$107>=$B112,"-",$C$61*(1+$C$56)*$C$59/(1+$B112)^1+$C$61*(1+$C$56)^2*$C$59/(1+$B112)^2+$C$61*(1+$C$56)^2*(1+$C$57)*$C$59/(1+$B112)^3+$C$61*(1+$C$56)^2*(1+$C$57)^2*$C$59/(1+$B112)^4+$C$61*(1+$C$56)^2*(1+$C$57)^3*$C$59/(1+$B112)^5+($C$61*(1+$C$56)^2*(1+$C$57)^3*$C$59*(1+G$107)/($B112-G$107))/(1+$B112)^5) -> 38.883603 | H112: =IF(H$107>=$B112,"-",$C$61*(1+$C$56)*$C$59/(1+$B112)^1+$C$61*(1+$C$56)^2*$C$59/(1+$B112)^2+$C$61*(1+$C$56)^2*(1+$C$57)*$C$59/(1+$B112)^3+$C$61*(1+$C$56)^2*(1+$C$57)^2*$C$59/(1+$B112)^4+$C$61*(1+$C$56)^2*(1+$C$57)^3*$C$59/(1+$B112)^5+($C$61*(1+$C$56)^2*(1+$C$57)^3*$C$59*(1+H$107)/($B112-H$107))/(1+$B112)^5) -> 41.220235 | I112: =IF(I$107>=$B112,"-",$C$61*(1+$C$56)*$C$59/(1+$B112)^1+$C$61*(1+$C$56)^2*$C$59/(1+$B112)^2+$C$61*(1+$C$56)^2*(1+$C$57)*$C$59/(1+$B112)^3+$C$61*(1+$C$56)^2*(1+$C$57)^2*$C$59/(1+$B112)^4+$C$61*(1+$C$56)^2*(1+$C$57)^3*$C$59/(1+$B112)^5+($C$61*(1+$C$56)^2*(1+$C$57)^3*$C$59*(1+I$107)/($B112-I$107))/(1+$B112)^5) -> 43.946305
B113: 0.115 | C113: =IF(C$107>=$B113,"-",$C$61*(1+$C$56)*$C$59/(1+$B113)^1+$C$61*(1+$C$56)^2*$C$59/(1+$B113)^2+$C$61*(1+$C$56)^2*(1+$C$57)*$C$59/(1+$B113)^3+$C$61*(1+$C$56)^2*(1+$C$57)^2*$C$59/(1+$B113)^4+$C$61*(1+$C$56)^2*(1+$C$57)^3*$C$59/(1+$B113)^5+($C$61*(1+$C$56)^2*(1+$C$57)^3*$C$59*(1+C$107)/($B113-C$107))/(1+$B113)^5) -> 28.832439 | D113: =IF(D$107>=$B113,"-",$C$61*(1+$C$56)*$C$59/(1+$B113)^1+$C$61*(1+$C$56)^2*$C$59/(1+$B113)^2+$C$61*(1+$C$56)^2*(1+$C$57)*$C$59/(1+$B113)^3+$C$61*(1+$C$56)^2*(1+$C$57)^2*$C$59/(1+$B113)^4+$C$61*(1+$C$56)^2*(1+$C$57)^3*$C$59/(1+$B113)^5+($C$61*(1+$C$56)^2*(1+$C$57)^3*$C$59*(1+D$107)/($B113-D$107))/(1+$B113)^5) -> 29.911952 | E113: =IF(E$107>=$B113,"-",$C$61*(1+$C$56)*$C$59/(1+$B113)^1+$C$61*(1+$C$56)^2*$C$59/(1+$B113)^2+$C$61*(1+$C$56)^2*(1+$C$57)*$C$59/(1+$B113)^3+$C$61*(1+$C$56)^2*(1+$C$57)^2*$C$59/(1+$B113)^4+$C$61*(1+$C$56)^2*(1+$C$57)^3*$C$59/(1+$B113)^5+($C$61*(1+$C$56)^2*(1+$C$57)^3*$C$59*(1+E$107)/($B113-E$107))/(1+$B113)^5) -> 31.11141 | F113: =IF(F$107>=$B113,"-",$C$61*(1+$C$56)*$C$59/(1+$B113)^1+$C$61*(1+$C$56)^2*$C$59/(1+$B113)^2+$C$61*(1+$C$56)^2*(1+$C$57)*$C$59/(1+$B113)^3+$C$61*(1+$C$56)^2*(1+$C$57)^2*$C$59/(1+$B113)^4+$C$61*(1+$C$56)^2*(1+$C$57)^3*$C$59/(1+$B113)^5+($C$61*(1+$C$56)^2*(1+$C$57)^3*$C$59*(1+F$107)/($B113-F$107))/(1+$B113)^5) -> 32.451981 | G113: =IF(G$107>=$B113,"-",$C$61*(1+$C$56)*$C$59/(1+$B113)^1+$C$61*(1+$C$56)^2*$C$59/(1+$B113)^2+$C$61*(1+$C$56)^2*(1+$C$57)*$C$59/(1+$B113)^3+$C$61*(1+$C$56)^2*(1+$C$57)^2*$C$59/(1+$B113)^4+$C$61*(1+$C$56)^2*(1+$C$57)^3*$C$59/(1+$B113)^5+($C$61*(1+$C$56)^2*(1+$C$57)^3*$C$59*(1+G$107)/($B113-G$107))/(1+$B113)^5) -> 33.960124 | H113: =IF(H$107>=$B113,"-",$C$61*(1+$C$56)*$C$59/(1+$B113)^1+$C$61*(1+$C$56)^2*$C$59/(1+$B113)^2+$C$61*(1+$C$56)^2*(1+$C$57)*$C$59/(1+$B113)^3+$C$61*(1+$C$56)^2*(1+$C$57)^2*$C$59/(1+$B113)^4+$C$61*(1+$C$56)^2*(1+$C$57)^3*$C$59/(1+$B113)^5+($C$61*(1+$C$56)^2*(1+$C$57)^3*$C$59*(1+H$107)/($B113-H$107))/(1+$B113)^5) -> 35.669352 | I113: =IF(I$107>=$B113,"-",$C$61*(1+$C$56)*$C$59/(1+$B113)^1+$C$61*(1+$C$56)^2*$C$59/(1+$B113)^2+$C$61*(1+$C$56)^2*(1+$C$57)*$C$59/(1+$B113)^3+$C$61*(1+$C$56)^2*(1+$C$57)^2*$C$59/(1+$B113)^4+$C$61*(1+$C$56)^2*(1+$C$57)^3*$C$59/(1+$B113)^5+($C$61*(1+$C$56)^2*(1+$C$57)^3*$C$59*(1+I$107)/($B113-I$107))/(1+$B113)^5) -> 37.622755
B114: 0.125 | C114: =IF(C$107>=$B114,"-",$C$61*(1+$C$56)*$C$59/(1+$B114)^1+$C$61*(1+$C$56)^2*$C$59/(1+$B114)^2+$C$61*(1+$C$56)^2*(1+$C$57)*$C$59/(1+$B114)^3+$C$61*(1+$C$56)^2*(1+$C$57)^2*$C$59/(1+$B114)^4+$C$61*(1+$C$56)^2*(1+$C$57)^3*$C$59/(1+$B114)^5+($C$61*(1+$C$56)^2*(1+$C$57)^3*$C$59*(1+C$107)/($B114-C$107))/(1+$B114)^5) -> 26.134418 | D114: =IF(D$107>=$B114,"-",$C$61*(1+$C$56)*$C$59/(1+$B114)^1+$C$61*(1+$C$56)^2*$C$59/(1+$B114)^2+$C$61*(1+$C$56)^2*(1+$C$57)*$C$59/(1+$B114)^3+$C$61*(1+$C$56)^2*(1+$C$57)^2*$C$59/(1+$B114)^4+$C$61*(1+$C$56)^2*(1+$C$57)^3*$C$59/(1+$B114)^5+($C$61*(1+$C$56)^2*(1+$C$57)^3*$C$59*(1+D$107)/($B114-D$107))/(1+$B114)^5) -> 26.991177 | E114: =IF(E$107>=$B114,"-",$C$61*(1+$C$56)*$C$59/(1+$B114)^1+$C$61*(1+$C$56)^2*$C$59/(1+$B114)^2+$C$61*(1+$C$56)^2*(1+$C$57)*$C$59/(1+$B114)^3+$C$61*(1+$C$56)^2*(1+$C$57)^2*$C$59/(1+$B114)^4+$C$61*(1+$C$56)^2*(1+$C$57)^3*$C$59/(1+$B114)^5+($C$61*(1+$C$56)^2*(1+$C$57)^3*$C$59*(1+E$107)/($B114-E$107))/(1+$B114)^5) -> 27.933611 | F114: =IF(F$107>=$B114,"-",$C$61*(1+$C$56)*$C$59/(1+$B114)^1+$C$61*(1+$C$56)^2*$C$59/(1+$B114)^2+$C$61*(1+$C$56)^2*(1+$C$57)*$C$59/(1+$B114)^3+$C$61*(1+$C$56)^2*(1+$C$57)^2*$C$59/(1+$B114)^4+$C$61*(1+$C$56)^2*(1+$C$57)^3*$C$59/(1+$B114)^5+($C$61*(1+$C$56)^2*(1+$C$57)^3*$C$59*(1+F$107)/($B114-F$107))/(1+$B114)^5) -> 28.97525 | G114: =IF(G$107>=$B114,"-",$C$61*(1+$C$56)*$C$59/(1+$B114)^1+$C$61*(1+$C$56)^2*$C$59/(1+$B114)^2+$C$61*(1+$C$56)^2*(1+$C$57)*$C$59/(1+$B114)^3+$C$61*(1+$C$56)^2*(1+$C$57)^2*$C$59/(1+$B114)^4+$C$61*(1+$C$56)^2*(1+$C$57)^3*$C$59/(1+$B114)^5+($C$61*(1+$C$56)^2*(1+$C$57)^3*$C$59*(1+G$107)/($B114-G$107))/(1+$B114)^5) -> 30.132626 | H114: =IF(H$107>=$B114,"-",$C$61*(1+$C$56)*$C$59/(1+$B114)^1+$C$61*(1+$C$56)^2*$C$59/(1+$B114)^2+$C$61*(1+$C$56)^2*(1+$C$57)*$C$59/(1+$B114)^3+$C$61*(1+$C$56)^2*(1+$C$57)^2*$C$59/(1+$B114)^4+$C$61*(1+$C$56)^2*(1+$C$57)^3*$C$59/(1+$B114)^5+($C$61*(1+$C$56)^2*(1+$C$57)^3*$C$59*(1+H$107)/($B114-H$107))/(1+$B114)^5) -> 31.426164 | I114: =IF(I$107>=$B114,"-",$C$61*(1+$C$56)*$C$59/(1+$B114)^1+$C$61*(1+$C$56)^2*$C$59/(1+$B114)^2+$C$61*(1+$C$56)^2*(1+$C$57)*$C$59/(1+$B114)^3+$C$61*(1+$C$56)^2*(1+$C$57)^2*$C$59/(1+$B114)^4+$C$61*(1+$C$56)^2*(1+$C$57)^3*$C$59/(1+$B114)^5+($C$61*(1+$C$56)^2*(1+$C$57)^3*$C$59*(1+I$107)/($B114-I$107))/(1+$B114)^5) -> 32.881395

Sheet 8. DCF Analysis
A1: 8. DCF Analysis | Normalized Equity Research Case
A2: Base case uses FY2024-FY2025 normalized operating assumptions with fixed base-case revenue growth; bear and bull cases flex the revenue path.
A4: Selected Operating Assumptions | E4: Valuation Inputs | J4: Valuation Bridge
A5: Case basis | B5: Normalized FY2024-FY2025 | E5: Risk-free rate | F5: ='DCF-WACC '!$C$4 -> 0.04 | J5: FCFF Valuation | K5: =SUM(B55:F55) -> 5771.6649 | M5: FCFE Valuation | N5: =SUM(B57:F57) -> 4918.8272
A6: Cost of revenues % | B6: =AVERAGE('DCF_Forecast Revenue'!$H$49:'DCF_Forecast Revenue'!$I$49) -> 0.72829863 | E6: Equity risk premium | F6: ='DCF-WACC '!$C$5 -> 0.055 | J6: Terminal Value | K6: =F45*(1+$B$15)/($F$10-$B$15) -> 40555.92 | M6: Terminal Value | N6: =F46*(1+$B$15)/($F$8-$B$15) -> 27226.971
A7: SG&A % | B7: =AVERAGE('DCF_Forecast Revenue'!$H$53:'DCF_Forecast Revenue'!$I$53) -> 0.071317739 | E7: Beta | F7: ='DCF-WACC '!$C$6 -> 0.83 | J7: PV of Terminal Value | K7: =K6*F54 -> 28724.842 | M7: PV of Terminal Value | N7: =N6*F56 -> 18053.031
A8: Other operating % | B8: =AVERAGE('DCF_Forecast Revenue'!$H$55:'DCF_Forecast Revenue'!$I$55) -> 0.010112557 | E8: Cost of equity (Ke) | F8: ='DCF-WACC '!$C$3 -> 0.08565 | J8: Enterprise Value | K8: =K5+K7 -> 34496.507 | M8: Equity Value | N8: =N5+N7 -> 22971.859
A9: D&A % | B9: =AVERAGE('DCF_Forecast Revenue'!$H$59:'DCF_Forecast Revenue'!$I$59) -> 0.089743094 | E9: Pre-tax cost of debt | F9: ='DCF_Forecast Revenue'!$R$51 -> 0.046278038 | J9: Less Current Net Debt | K9: =$F$13 -> 4190 | M9: Implied Price / Share | N9: =N8/$F$11 -> 175.92172
A10: Capex % | B10: =AVERAGE('DCF_Forecast Revenue'!$H$160:'DCF_Forecast Revenue'!$I$160) -> 0.083350685 | E10: Selected WACC | F10: ='DCF-WACC '!$C$15 -> 0.071418944 | J10: Equity Value | K10: =K8-K9 -> 30306.507 | M10: Upside / (Downside) | N10: =N9/$F$12-1 -> -0.40562969
A11: Tax rate | B11: =AVERAGE('DCF_Forecast Revenue'!$H$67:'DCF_Forecast Revenue'!$I$67) -> 0.21031365 | E11: Shares outstanding (mm) | F11: ='6. Mutliple_Valuation'!$C$50 -> 130.58 | J11: Implied Price / Share | K11: =K10/$F$11 -> 232.09149 | M11: FCFE vs FCFF Price Gap | N11: =N9-K11 -> -56.16977
A12: DSO (days) | B12: =AVERAGE('DCF_Forecast Revenue'!$H$140:'DCF_Forecast Revenue'!$I$140) -> 42.35469 | E12: Current share price | F12: ='6. Mutliple_Valuation'!$C$49 -> 295.98 | J12: Upside / (Downside) | K12: =K11/$F$12-1 -> -0.21585414
A13: DIO (days) | B13: =AVERAGE('DCF_Forecast Revenue'!$H$141:'DCF_Forecast Revenue'!$I$141) -> 44.502016 | E13: Current net debt ($mm) | F13: ='6. Mutliple_Valuation'!$C$52 -> 4190
A14: DPO (days) | B14: =AVERAGE('DCF_Forecast Revenue'!$H$142:'DCF_Forecast Revenue'!$I$142) -> 27.586927 | E14: Gross debt used in FCFE ($mm) | F14: ='DCF_Forecast Revenue'!$I$168 -> 4372.9
A15: Terminal growth (g) | B15: ='DCF_Forecast Revenue'!$R$56 -> 0.03 | E15: Beginning cash ($mm) | F15: ='DCF_Forecast Revenue'!$I$73 -> 183.3
A16: Revenue case shown below | B16: Base | E16: DDM implied price | F16: ='7. DDM_Valuation'!$C$87 -> 50.008571 | J16: Scenario Analysis (Bear / Base / Bull)
E17: Capital structure | F17: Stable debt; no sponsor-style sweep | J17: Metric | K17: Bear | L17: Base | M17: Bull
J18: 2030 Revenue | K18: =AA73 -> 8721.1604 | L18: =AA85 -> 10970.891 | M18: =AA97 -> 12061.311
J19: Revenue CAGR | K19: =AC70 -> 0.018916796 | L19: =AC82 -> 0.066773565 | M19: =AC94 -> 0.087183301
A20: Base Case Detailed FCFF / FCFE Forecast | J20: FCFF Implied Price | K20: =AC71 -> 189.71311 | L20: =AC83 -> 232.09149 | M20: =AC95 -> 251.74728
A21: Metric | B21: 2026E | C21: 2027E | D21: 2028E | E21: 2029E | F21: 2030E | J21: FCFE Implied Price | K21: =AC72 -> 145.35489 | L21: =AC84 -> 175.92172 | M21: =AC96 -> 190.06818
A22: Aggregates Revenue | B22: ='DCF_Forecast Revenue'!$I$34*(1+'DCF_Forecast Revenue'!$D$17) -> 6235.1075 | C22: =B22*(1+'DCF_Forecast Revenue'!$E$17) -> 6671.565 | D22: =C22*(1+'DCF_Forecast Revenue'!$F$17) -> 7105.2168 | E22: =D22*(1+'DCF_Forecast Revenue'!$G$17) -> 7531.5298 | F22: =E22*(1+'DCF_Forecast Revenue'!$H$17) -> 7945.7639
A23: Asphalt Revenue | B23: ='DCF_Forecast Revenue'!$I$36*(1+'DCF_Forecast Revenue'!$D$11) -> 1385.008 | C23: =B23*(1+'DCF_Forecast Revenue'!$E$11) -> 1481.9586 | D23: =C23*(1+'DCF_Forecast Revenue'!$F$11) -> 1578.2859 | E23: =D23*(1+'DCF_Forecast Revenue'!$G$11) -> 1680.8744 | F23: =E23*(1+'DCF_Forecast Revenue'!$H$11) -> 1781.7269
A24: Concrete / RMX Revenue | B24: ='DCF_Forecast Revenue'!$I$38*(1+'DCF_Forecast Revenue'!$D$24) -> 931.26 | C24: =B24*(1+'DCF_Forecast Revenue'!$E$24) -> 1015.0734 | D24: =C24*(1+'DCF_Forecast Revenue'!$F$24) -> 1096.2793 | E24: =D24*(1+'DCF_Forecast Revenue'!$G$24) -> 1173.0188 | F24: =E24*(1+'DCF_Forecast Revenue'!$H$24) -> 1243.4 | J24: Documentation Notes
A25: Total Revenue | B25: =SUM(B22:B24) -> 8551.3755 | C25: =SUM(C22:C24) -> 9168.597 | D25: =SUM(D22:D24) -> 9779.7819 | E25: =SUM(E22:E24) -> 10385.423 | F25: =SUM(F22:F24) -> 10970.891 | J25: Operating assumptions are normalized to FY2024-FY2025 to reflect the current business mix after recent portfolio changes.
A26: YoY Growth | B26: =B25/'DCF_Forecast Revenue'!$I$47-1 -> 0.076850247 | C26: =C25/B25-1 -> 0.072178036 | D26: =D25/C25-1 -> 0.066660679 | E26: =E25/D25-1 -> 0.061927878 | F26: =F25/E25-1 -> 0.05637399 | J26: This avoids understating value by blending current forecasts with older, less representative cost and capital-intensity years.
A27: Cost of Revenues | B27: =B25*$B$6 -> 6227.9551 | C27: =C25*$B$6 -> 6677.4766 | D27: =D25*$B$6 -> 7122.6018 | E27: =E25*$B$6 -> 7563.6894 | F27: =F25*$B$6 -> 7990.0847 | J27: FCFF is the primary valuation anchor; FCFE and DDM remain secondary cross-checks for an equity research report.
A28: Gross Profit | B28: =B25-B27 -> 2323.4204 | C28: =C25-C27 -> 2491.1204 | D28: =D25-D27 -> 2657.1801 | E28: =E25-E27 -> 2821.7337 | F28: =F25-F27 -> 2980.806
A29: SG&A | B29: =B25*$B$7 -> 609.86476 | C29: =C25*$B$7 -> 653.8836 | D29: =D25*$B$7 -> 697.47193 | E29: =E25*$B$7 -> 740.66489 | F29: =F25*$B$7 -> 782.41912
A30: Other Operating Expense | B30: =B25*$B$8 -> 86.476275 | C30: =C25*$B$8 -> 92.717963 | D30: =D25*$B$8 -> 98.898605 | E30: =E25*$B$8 -> 105.02319 | F30: =F25*$B$8 -> 110.94376
A31: EBIT | B31: =B28-B29-B30 -> 1627.0794 | C31: =C28-C29-C30 -> 1744.5188 | D31: =D28-D29-D30 -> 1860.8096 | E31: =E28-E29-E30 -> 1976.0456 | F31: =F28-F29-F30 -> 2087.4432
A32: Interest Expense | B32: =$F$14*$F$9 -> 202.36923 | C32: =$F$14*$F$9 -> 202.36923 | D32: =$F$14*$F$9 -> 202.36923 | E32: =$F$14*$F$9 -> 202.36923 | F32: =$F$14*$F$9 -> 202.36923
A33: Pre-Tax Income | B33: =B31-B32 -> 1424.7102 | C33: =C31-C32 -> 1542.1496 | D33: =D31-D32 -> 1658.4404 | E33: =E31-E32 -> 1773.6764 | F33: =F31-F32 -> 1885.0739
A34: Taxes | B34: =B33*$B$11 -> 299.636 | C34: =C33*$B$11 -> 324.33511 | D34: =D33*$B$11 -> 348.79265 | E34: =E33*$B$11 -> 373.02835 | F34: =F33*$B$11 -> 396.45678
A35: Net Income | B35: =B33-B34 -> 1125.0742 | C35: =C33-C34 -> 1217.8145 | D35: =D33-D34 -> 1309.6477 | E35: =E33-E34 -> 1400.648 | F35: =F33-F34 -> 1488.6171
A36: Depreciation & Amortization | B36: =B25*$B$9 -> 767.42689 | C36: =C25*$B$9 -> 822.81826 | D36: =D25*$B$9 -> 877.66788 | E36: =E25*$B$9 -> 932.01999 | F36: =F25*$B$9 -> 984.56168
A37: EBITDA | B37: =B31+B36 -> 2394.5063 | C37: =C31+C36 -> 2567.337 | D37: =D31+D36 -> 2738.4775 | E37: =E31+E36 -> 2908.0656 | F37: =F31+F36 -> 3072.0048
A38: Accounts Receivable | B38: =B25*$B$12/365 -> 992.30373 | C38: =C25*$B$12/365 -> 1063.9263 | D38: =D25*$B$12/365 -> 1134.8483 | E38: =E25*$B$12/365 -> 1205.1271 | F38: =F25*$B$12/365 -> 1273.0649
A39: Inventory | B39: =B27*$B$13/365 -> 759.33303 | C39: =C27*$B$13/365 -> 814.14019 | D39: =D27*$B$13/365 -> 868.41133 | E39: =E27*$B$13/365 -> 922.1902 | F39: =F27*$B$13/365 -> 974.17774
A40: Accounts Payable | B40: =B27*$B$14/365 -> 470.71272 | C40: =C27*$B$14/365 -> 504.68784 | D40: =D27*$B$14/365 -> 538.33067 | E40: =E27*$B$14/365 -> 571.66835 | F40: =F27*$B$14/365 -> 603.89557
A41: Net Working Capital | B41: =B38+B39-B40 -> 1280.924 | C41: =C38+C39-C40 -> 1373.3786 | D41: =D38+D39-D40 -> 1464.929 | E41: =E38+E39-E40 -> 1555.6489 | F41: =F38+F39-F40 -> 1643.347
A42: Change in NWC | B42: =B41-'DCF_Forecast Revenue'!$I$149 -> 151.22404 | C42: =C41-B41 -> 92.454581 | D42: =D41-C41 -> 91.550352 | E42: =E41-D41 -> 90.719942 | F42: =F41-E41 -> 87.698136
A43: Capital Expenditures | B43: =B25*$B$10 -> 712.763 | C43: =C25*$B$10 -> 764.20884 | D43: =D25*$B$10 -> 815.15152 | E43: =E25*$B$10 -> 865.63212 | F43: =F25*$B$10 -> 914.43126
A44: Dividends Paid | B44: =-'7. DDM_Valuation'!$D$76*$F$11 -> -321.82224 | C44: =-'7. DDM_Valuation'!$E$76*$F$11 -> -347.56802 | D44: =-'7. DDM_Valuation'!$F$76*$F$11 -> -368.42211 | E44: =-'7. DDM_Valuation'!$G$76*$F$11 -> -390.52743 | F44: =-'7. DDM_Valuation'!$H$76*$F$11 -> -413.95908
A45: FCFF | B45: =B31*(1-$B$11)+B36-B43-B42 -> 1188.3222 | C45: =C31*(1-$B$11)+C36-C43-C42 -> 1343.7775 | D45: =D31*(1-$B$11)+D36-D43-D42 -> 1440.4219 | E45: =E31*(1-$B$11)+E36-E43-E42 -> 1536.1241 | F45: =F31*(1-$B$11)+F36-F43-F42 -> 1630.8576
A46: FCFE | B46: =B35+B36-B43-B42 -> 1028.514 | C46: =C35+C36-C43-C42 -> 1183.9693 | D46: =D35+D36-D43-D42 -> 1280.6137 | E46: =E35+E36-E43-E42 -> 1376.3159 | F46: =F35+F36-F43-F42 -> 1471.0494
A47: Beginning Cash | B47: =$F$15 -> 183.3 | C47: =B48 -> 889.99177 | D47: =C48 -> 1726.393 | E47: =D48 -> 2638.5847 | F47: =E48 -> 3624.3732
A48: Ending Cash | B48: =B47+B46+B44 -> 889.99177 | C48: =C47+C46+C44 -> 1726.393 | D48: =D47+D46+D44 -> 2638.5847 | E48: =E47+E46+E44 -> 3624.3732 | F48: =F47+F46+F44 -> 4681.4635
A49: Gross Debt | B49: =$F$14 -> 4372.9 | C49: =$F$14 -> 4372.9 | D49: =$F$14 -> 4372.9 | E49: =$F$14 -> 4372.9 | F49: =$F$14 -> 4372.9
A50: Net Debt / (Cash) | B50: =B49-B48 -> 3482.9082 | C50: =C49-C48 -> 2646.507 | D50: =D49-D48 -> 1734.3153 | E50: =E49-E48 -> 748.52685 | F50: =F49-F48 -> -308.5635
A53: Discount Period | B53: 1 | C53: 2 | D53: 3 | E53: 4 | F53: 5
A54: FCFF Discount Factor | B54: =1/(1+$F$10)^B53 -> 0.93334172 | C54: =1/(1+$F$10)^C53 -> 0.87112677 | D54: =1/(1+$F$10)^D53 -> 0.81305895 | E54: =1/(1+$F$10)^E53 -> 0.75886184 | F54: =1/(1+$F$10)^F53 -> 0.70827742
A55: PV of FCFF | B55: =B45*B54 -> 1109.1107 | C55: =C45*C54 -> 1170.6006 | D55: =D45*D54 -> 1171.148 | E55: =E45*E54 -> 1165.706 | F55: =F45*F54 -> 1155.0996
A56: FCFE Discount Factor | B56: =1/(1+$F$8)^B53 -> 0.92110717 | C56: =1/(1+$F$8)^C53 -> 0.84843842 | D56: =1/(1+$F$8)^D53 -> 0.78150271 | E56: =1/(1+$F$8)^E53 -> 0.71984775 | F56: =1/(1+$F$8)^F53 -> 0.66305693
A57: PV of FCFE | B57: =B46*B56 -> 947.37163 | C57: =C46*C56 -> 1004.525 | D57: =D46*D56 -> 1000.8031 | E57: =E46*E56 -> 990.73793 | F57: =F46*F56 -> 975.38951
A60: FCFF Sensitivity: WACC vs Terminal Growth | H60: FCFE Sensitivity: Ke vs Terminal Growth
B62: 0.025 | C62: 0.03 | D62: 0.035 | E62: 0.0375 | F62: 0.04 | I62: 0.025 | J62: 0.03 | K62: 0.035 | L62: 0.0375 | M62: 0.04
A63: 0.065 | B63: =(SUMPRODUCT($B$45:$F$45,1/(1+$A63)^$B$53:$F$53)+$F$45*(1+B$62)/($A63-B$62)/(1+$A63)^5-$F$13)/$F$11 -> 246.51286 | C63: =(SUMPRODUCT($B$45:$F$45,1/(1+$A63)^$B$53:$F$53)+$F$45*(1+C$62)/($A63-C$62)/(1+$A63)^5-$F$13)/$F$11 -> 281.18518 | D63: =(SUMPRODUCT($B$45:$F$45,1/(1+$A63)^$B$53:$F$53)+$F$45*(1+D$62)/($A63-D$62)/(1+$A63)^5-$F$13)/$F$11 -> 327.41494 | E63: =(SUMPRODUCT($B$45:$F$45,1/(1+$A63)^$B$53:$F$53)+$F$45*(1+E$62)/($A63-E$62)/(1+$A63)^5-$F$13)/$F$11 -> 356.83388 | F63: =(SUMPRODUCT($B$45:$F$45,1/(1+$A63)^$B$53:$F$53)+$F$45*(1+F$62)/($A63-F$62)/(1+$A63)^5-$F$13)/$F$11 -> 392.13661 | H63: 0.075 | I63: =(SUMPRODUCT($B$46:$F$46,1/(1+$H63)^$B$53:$F$53)+$F$46*(1+I$62)/($H63-I$62)/(1+$H63)^5)/$F$11 -> 199.67197 | J63: =(SUMPRODUCT($B$46:$F$46,1/(1+$H63)^$B$53:$F$53)+$F$46*(1+J$62)/($H63-J$62)/(1+$H63)^5)/$F$11 -> 218.41778 | K63: =(SUMPRODUCT($B$46:$F$46,1/(1+$H63)^$B$53:$F$53)+$F$46*(1+K$62)/($H63-K$62)/(1+$H63)^5)/$F$11 -> 241.85004 | L63: =(SUMPRODUCT($B$46:$F$46,1/(1+$H63)^$B$53:$F$53)+$F$46*(1+L$62)/($H63-L$62)/(1+$H63)^5)/$F$11 -> 255.9094 | M63: =(SUMPRODUCT($B$46:$F$46,1/(1+$H63)^$B$53:$F$53)+$F$46*(1+M$62)/($H63-M$62)/(1+$H63)^5)/$F$11 -> 271.97724
A64: 0.07 | B64: =(SUMPRODUCT($B$45:$F$45,1/(1+$A64)^$B$53:$F$53)+$F$45*(1+B$62)/($A64-B$62)/(1+$A64)^5-$F$13)/$F$11 -> 215.1195 | C64: =(SUMPRODUCT($B$45:$F$45,1/(1+$A64)^$B$53:$F$53)+$F$45*(1+C$62)/($A64-C$62)/(1+$A64)^5-$F$13)/$F$11 -> 241.58632 | D64: =(SUMPRODUCT($B$45:$F$45,1/(1+$A64)^$B$53:$F$53)+$F$45*(1+D$62)/($A64-D$62)/(1+$A64)^5-$F$13)/$F$11 -> 275.61509 | E64: =(SUMPRODUCT($B$45:$F$45,1/(1+$A64)^$B$53:$F$53)+$F$45*(1+E$62)/($A64-E$62)/(1+$A64)^5-$F$13)/$F$11 -> 296.55587 | F64: =(SUMPRODUCT($B$45:$F$45,1/(1+$A64)^$B$53:$F$53)+$F$45*(1+F$62)/($A64-F$62)/(1+$A64)^5-$F$13)/$F$11 -> 320.98678 | H64: 0.08 | I64: =(SUMPRODUCT($B$46:$F$46,1/(1+$H64)^$B$53:$F$53)+$F$46*(1+I$62)/($H64-I$62)/(1+$H64)^5)/$F$11 -> 181.1532 | J64: =(SUMPRODUCT($B$46:$F$46,1/(1+$H64)^$B$53:$F$53)+$F$46*(1+J$62)/($H64-J$62)/(1+$H64)^5)/$F$11 -> 196.20862 | K64: =(SUMPRODUCT($B$46:$F$46,1/(1+$H64)^$B$53:$F$53)+$F$46*(1+K$62)/($H64-K$62)/(1+$H64)^5)/$F$11 -> 214.60969 | L64: =(SUMPRODUCT($B$46:$F$46,1/(1+$H64)^$B$53:$F$53)+$F$46*(1+L$62)/($H64-L$62)/(1+$H64)^5)/$F$11 -> 225.43385 | M64: =(SUMPRODUCT($B$46:$F$46,1/(1+$H64)^$B$53:$F$53)+$F$46*(1+M$62)/($H64-M$62)/(1+$H64)^5)/$F$11 -> 237.61102
A65: 0.075 | B65: =(SUMPRODUCT($B$45:$F$45,1/(1+$A65)^$B$53:$F$53)+$F$45*(1+B$62)/($A65-B$62)/(1+$A65)^5-$F$13)/$F$11 -> 190.01153 | C65: =(SUMPRODUCT($B$45:$F$45,1/(1+$A65)^$B$53:$F$53)+$F$45*(1+C$62)/($A65-C$62)/(1+$A65)^5-$F$13)/$F$11 -> 210.7938 | D65: =(SUMPRODUCT($B$45:$F$45,1/(1+$A65)^$B$53:$F$53)+$F$45*(1+D$62)/($A65-D$62)/(1+$A65)^5-$F$13)/$F$11 -> 236.77164 | E65: =(SUMPRODUCT($B$45:$F$45,1/(1+$A65)^$B$53:$F$53)+$F$45*(1+E$62)/($A65-E$62)/(1+$A65)^5-$F$13)/$F$11 -> 252.35834 | F65: =(SUMPRODUCT($B$45:$F$45,1/(1+$A65)^$B$53:$F$53)+$F$45*(1+F$62)/($A65-F$62)/(1+$A65)^5-$F$13)/$F$11 -> 270.17172 | H65: 0.085 | I65: =(SUMPRODUCT($B$46:$F$46,1/(1+$H65)^$B$53:$F$53)+$F$46*(1+I$62)/($H65-I$62)/(1+$H65)^5)/$F$11 -> 165.72657 | J65: =(SUMPRODUCT($B$46:$F$46,1/(1+$H65)^$B$53:$F$53)+$F$46*(1+J$62)/($H65-J$62)/(1+$H65)^5)/$F$11 -> 178.04308 | K65: =(SUMPRODUCT($B$46:$F$46,1/(1+$H65)^$B$53:$F$53)+$F$46*(1+K$62)/($H65-K$62)/(1+$H65)^5)/$F$11 -> 192.8229 | L65: =(SUMPRODUCT($B$46:$F$46,1/(1+$H65)^$B$53:$F$53)+$F$46*(1+L$62)/($H65-L$62)/(1+$H65)^5)/$F$11 -> 201.37963 | M65: =(SUMPRODUCT($B$46:$F$46,1/(1+$H65)^$B$53:$F$53)+$F$46*(1+M$62)/($H65-M$62)/(1+$H65)^5)/$F$11 -> 210.88711
A66: 0.08 | B66: =(SUMPRODUCT($B$45:$F$45,1/(1+$A66)^$B$53:$F$53)+$F$45*(1+B$62)/($A66-B$62)/(1+$A66)^5-$F$13)/$F$11 -> 169.47461 | C66: =(SUMPRODUCT($B$45:$F$45,1/(1+$A66)^$B$53:$F$53)+$F$45*(1+C$62)/($A66-C$62)/(1+$A66)^5-$F$13)/$F$11 -> 186.16559 | D66: =(SUMPRODUCT($B$45:$F$45,1/(1+$A66)^$B$53:$F$53)+$F$45*(1+D$62)/($A66-D$62)/(1+$A66)^5-$F$13)/$F$11 -> 206.56567 | E66: =(SUMPRODUCT($B$45:$F$45,1/(1+$A66)^$B$53:$F$53)+$F$45*(1+E$62)/($A66-E$62)/(1+$A66)^5-$F$13)/$F$11 -> 218.56571 | F66: =(SUMPRODUCT($B$45:$F$45,1/(1+$A66)^$B$53:$F$53)+$F$45*(1+F$62)/($A66-F$62)/(1+$A66)^5-$F$13)/$F$11 -> 232.06577 | H66: 0.09 | I66: =(SUMPRODUCT($B$46:$F$46,1/(1+$H66)^$B$53:$F$53)+$F$46*(1+I$62)/($H66-I$62)/(1+$H66)^5)/$F$11 -> 152.6784 | J66: =(SUMPRODUCT($B$46:$F$46,1/(1+$H66)^$B$53:$F$53)+$F$46*(1+J$62)/($H66-J$62)/(1+$H66)^5)/$F$11 -> 162.91016 | K66: =(SUMPRODUCT($B$46:$F$46,1/(1+$H66)^$B$53:$F$53)+$F$46*(1+K$62)/($H66-K$62)/(1+$H66)^5)/$F$11 -> 175.00223 | L66: =(SUMPRODUCT($B$46:$F$46,1/(1+$H66)^$B$53:$F$53)+$F$46*(1+L$62)/($H66-L$62)/(1+$H66)^5)/$F$11 -> 181.91198 | M66: =(SUMPRODUCT($B$46:$F$46,1/(1+$H66)^$B$53:$F$53)+$F$46*(1+M$62)/($H66-M$62)/(1+$H66)^5)/$F$11 -> 189.51271
A67: 0.085 | B67: =(SUMPRODUCT($B$45:$F$45,1/(1+$A67)^$B$53:$F$53)+$F$45*(1+B$62)/($A67-B$62)/(1+$A67)^5-$F$13)/$F$11 -> 152.36587 | C67: =(SUMPRODUCT($B$45:$F$45,1/(1+$A67)^$B$53:$F$53)+$F$45*(1+C$62)/($A67-C$62)/(1+$A67)^5-$F$13)/$F$11 -> 166.02039 | D67: =(SUMPRODUCT($B$45:$F$45,1/(1+$A67)^$B$53:$F$53)+$F$45*(1+D$62)/($A67-D$62)/(1+$A67)^5-$F$13)/$F$11 -> 182.40581 | E67: =(SUMPRODUCT($B$45:$F$45,1/(1+$A67)^$B$53:$F$53)+$F$45*(1+E$62)/($A67-E$62)/(1+$A67)^5-$F$13)/$F$11 -> 191.89211 | F67: =(SUMPRODUCT($B$45:$F$45,1/(1+$A67)^$B$53:$F$53)+$F$45*(1+F$62)/($A67-F$62)/(1+$A67)^5-$F$13)/$F$11 -> 202.43245 | H67: 0.095 | I67: =(SUMPRODUCT($B$46:$F$46,1/(1+$H67)^$B$53:$F$53)+$F$46*(1+I$62)/($H67-I$62)/(1+$H67)^5)/$F$11 -> 141.49891 | J67: =(SUMPRODUCT($B$46:$F$46,1/(1+$H67)^$B$53:$F$53)+$F$46*(1+J$62)/($H67-J$62)/(1+$H67)^5)/$F$11 -> 150.1099 | K67: =(SUMPRODUCT($B$46:$F$46,1/(1+$H67)^$B$53:$F$53)+$F$46*(1+K$62)/($H67-K$62)/(1+$H67)^5)/$F$11 -> 160.15604 | L67: =(SUMPRODUCT($B$46:$F$46,1/(1+$H67)^$B$53:$F$53)+$F$46*(1+L$62)/($H67-L$62)/(1+$H67)^5)/$F$11 -> 165.8343 | M67: =(SUMPRODUCT($B$46:$F$46,1/(1+$H67)^$B$53:$F$53)+$F$46*(1+M$62)/($H67-M$62)/(1+$H67)^5)/$F$11 -> 172.02876
W70: ='DCF_Forecast Revenue'!$I$34*(1+'DCF_Forecast Revenue'!$D$18) -> 5945.1025 | X70: =W70*(1+'DCF_Forecast Revenue'!$E$18) -> 6093.7301 | Y70: =X70*(1+'DCF_Forecast Revenue'!$F$18) -> 6215.6047 | Z70: =Y70*(1+'DCF_Forecast Revenue'!$G$18) -> 6339.9168 | AA70: =Z70*(1+'DCF_Forecast Revenue'!$H$18) -> 6466.7151 | AC70: =(AA73/'DCF_Forecast Revenue'!$I$47)^(1/5)-1 -> 0.018916796
W71: ='DCF_Forecast Revenue'!$I$36*(1+'DCF_Forecast Revenue'!$D$12) -> 1307.344 | X71: =W71*(1+'DCF_Forecast Revenue'!$E$12) -> 1320.4174 | Y71: =X71*(1+'DCF_Forecast Revenue'!$F$12) -> 1327.0195 | Z71: =Y71*(1+'DCF_Forecast Revenue'!$G$12) -> 1333.6546 | AA71: =Z71*(1+'DCF_Forecast Revenue'!$H$12) -> 1333.6546 | AC71: =(SUMPRODUCT(W77:AA77,$B$54:$F$54)+AA77*(1+$B$15)/($F$10-$B$15)*$F$54-$F$13)/$F$11 -> 189.71311
W72: ='DCF_Forecast Revenue'!$I$38*(1+'DCF_Forecast Revenue'!$D$25) -> 871.998 | X72: =W72*(1+'DCF_Forecast Revenue'!$E$25) -> 893.79795 | Y72: =X72*(1+'DCF_Forecast Revenue'!$F$25) -> 911.67391 | Z72: =Y72*(1+'DCF_Forecast Revenue'!$G$25) -> 920.79065 | AA72: =Z72*(1+'DCF_Forecast Revenue'!$H$25) -> 920.79065 | AC72: =(SUMPRODUCT(W78:AA78,$B$56:$F$56)+AA78*(1+$B$15)/($F$8-$B$15)*$F$56)/$F$11 -> 145.35489
W73: =SUM(W70:W72) -> 8124.4445 | X73: =SUM(X70:X72) -> 8307.9455 | Y73: =SUM(Y70:Y72) -> 8454.2981 | Z73: =SUM(Z70:Z72) -> 8594.362 | AA73: =SUM(AA70:AA72) -> 8721.1604
W74: =W73-W73*$B$6-W73*$B$7-W73*$B$8 -> 1545.8468 | X74: =X73-X73*$B$6-X73*$B$7-X73*$B$8 -> 1580.7617 | Y74: =Y73-Y73*$B$6-Y73*$B$7-Y73*$B$8 -> 1608.6084 | Z74: =Z73-Z73*$B$6-Z73*$B$7-Z73*$B$8 -> 1635.2585 | AA74: =AA73-AA73*$B$6-AA73*$B$7-AA73*$B$8 -> 1659.3845
W75: =W73*$B$12/365+(W73*$B$6)*$B$13/365-(W73*$B$6)*$B$14/365 -> 1216.9734 | X75: =X73*$B$12/365+(X73*$B$6)*$B$13/365-(X73*$B$6)*$B$14/365 -> 1244.4603 | Y75: =Y73*$B$12/365+(Y73*$B$6)*$B$13/365-(Y73*$B$6)*$B$14/365 -> 1266.3827 | Z75: =Z73*$B$12/365+(Z73*$B$6)*$B$13/365-(Z73*$B$6)*$B$14/365 -> 1287.3631 | AA75: =AA73*$B$12/365+(AA73*$B$6)*$B$13/365-(AA73*$B$6)*$B$14/365 -> 1306.3564
W76: =W75-'DCF_Forecast Revenue'!$I$149 -> 87.273369 | X76: =X75-W75 -> 27.486897 | Y76: =Y75-X75 -> 21.922394 | Z76: =Z75-Y75 -> 20.980397 | AA76: =AA75-Z75 -> 18.993323
W77: =W74*(1-$B$11)+W73*$B$9-W73*$B$10-W76 -> 1185.3955 | X77: =X74*(1-$B$11)+X73*$B$9-X73*$B$10-X76 -> 1273.9268 | Y77: =Y74*(1-$B$11)+Y73*$B$9-Y73*$B$10-Y76 -> 1302.417 | Z77: =Z74*(1-$B$11)+Z73*$B$9-Z73*$B$10-Z76 -> 1325.2996 | AA77: =AA74*(1-$B$11)+AA73*$B$9-AA73*$B$10-AA76 -> 1347.1492
W78: =(W74-$F$14*$F$9)*(1-$B$11)+W73*$B$9-W73*$B$10-W76 -> 1025.5873 | X78: =(X74-$F$14*$F$9)*(1-$B$11)+X73*$B$9-X73*$B$10-X76 -> 1114.1186 | Y78: =(Y74-$F$14*$F$9)*(1-$B$11)+Y73*$B$9-Y73*$B$10-Y76 -> 1142.6088 | Z78: =(Z74-$F$14*$F$9)*(1-$B$11)+Z73*$B$9-Z73*$B$10-Z76 -> 1165.4914 | AA78: =(AA74-$F$14*$F$9)*(1-$B$11)+AA73*$B$9-AA73*$B$10-AA76 -> 1187.341
W82: ='DCF_Forecast Revenue'!$I$34*(1+'DCF_Forecast Revenue'!$D$17) -> 6235.1075 | X82: =W82*(1+'DCF_Forecast Revenue'!$E$17) -> 6671.565 | Y82: =X82*(1+'DCF_Forecast Revenue'!$F$17) -> 7105.2168 | Z82: =Y82*(1+'DCF_Forecast Revenue'!$G$17) -> 7531.5298 | AA82: =Z82*(1+'DCF_Forecast Revenue'!$H$17) -> 7945.7639 | AC82: =(AA85/'DCF_Forecast Revenue'!$I$47)^(1/5)-1 -> 0.066773565
W83: ='DCF_Forecast Revenue'!$I$36*(1+'DCF_Forecast Revenue'!$D$11) -> 1385.008 | X83: =W83*(1+'DCF_Forecast Revenue'!$E$11) -> 1481.9586 | Y83: =X83*(1+'DCF_Forecast Revenue'!$F$11) -> 1578.2859 | Z83: =Y83*(1+'DCF_Forecast Revenue'!$G$11) -> 1680.8744 | AA83: =Z83*(1+'DCF_Forecast Revenue'!$H$11) -> 1781.7269 | AC83: =(SUMPRODUCT(W89:AA89,$B$54:$F$54)+AA89*(1+$B$15)/($F$10-$B$15)*$F$54-$F$13)/$F$11 -> 232.09149
W84: ='DCF_Forecast Revenue'!$I$38*(1+'DCF_Forecast Revenue'!$D$24) -> 931.26 | X84: =W84*(1+'DCF_Forecast Revenue'!$E$24) -> 1015.0734 | Y84: =X84*(1+'DCF_Forecast Revenue'!$F$24) -> 1096.2793 | Z84: =Y84*(1+'DCF_Forecast Revenue'!$G$24) -> 1173.0188 | AA84: =Z84*(1+'DCF_Forecast Revenue'!$H$24) -> 1243.4 | AC84: =(SUMPRODUCT(W90:AA90,$B$56:$F$56)+AA90*(1+$B$15)/($F$8-$B$15)*$F$56)/$F$11 -> 175.92172
W85: =SUM(W82:W84) -> 8551.3755 | X85: =SUM(X82:X84) -> 9168.597 | Y85: =SUM(Y82:Y84) -> 9779.7819 | Z85: =SUM(Z82:Z84) -> 10385.423 | AA85: =SUM(AA82:AA84) -> 10970.891
W86: =W85-W85*$B$6-W85*$B$7-W85*$B$8 -> 1627.0794 | X86: =X85-X85*$B$6-X85*$B$7-X85*$B$8 -> 1744.5188 | Y86: =Y85-Y85*$B$6-Y85*$B$7-Y85*$B$8 -> 1860.8096 | Z86: =Z85-Z85*$B$6-Z85*$B$7-Z85*$B$8 -> 1976.0456 | AA86: =AA85-AA85*$B$6-AA85*$B$7-AA85*$B$8 -> 2087.4432
W87: =W85*$B$12/365+(W85*$B$6)*$B$13/365-(W85*$B$6)*$B$14/365 -> 1280.924 | X87: =X85*$B$12/365+(X85*$B$6)*$B$13/365-(X85*$B$6)*$B$14/365 -> 1373.3786 | Y87: =Y85*$B$12/365+(Y85*$B$6)*$B$13/365-(Y85*$B$6)*$B$14/365 -> 1464.929 | Z87: =Z85*$B$12/365+(Z85*$B$6)*$B$13/365-(Z85*$B$6)*$B$14/365 -> 1555.6489 | AA87: =AA85*$B$12/365+(AA85*$B$6)*$B$13/365-(AA85*$B$6)*$B$14/365 -> 1643.347
W88: =W87-'DCF_Forecast Revenue'!$I$149 -> 151.22404 | X88: =X87-W87 -> 92.454581 | Y88: =Y87-X87 -> 91.550352 | Z88: =Z87-Y87 -> 90.719942 | AA88: =AA87-Z87 -> 87.698136
W89: =W86*(1-$B$11)+W85*$B$9-W85*$B$10-W88 -> 1188.3222 | X89: =X86*(1-$B$11)+X85*$B$9-X85*$B$10-X88 -> 1343.7775 | Y89: =Y86*(1-$B$11)+Y85*$B$9-Y85*$B$10-Y88 -> 1440.4219 | Z89: =Z86*(1-$B$11)+Z85*$B$9-Z85*$B$10-Z88 -> 1536.1241 | AA89: =AA86*(1-$B$11)+AA85*$B$9-AA85*$B$10-AA88 -> 1630.8576
W90: =(W86-$F$14*$F$9)*(1-$B$11)+W85*$B$9-W85*$B$10-W88 -> 1028.514 | X90: =(X86-$F$14*$F$9)*(1-$B$11)+X85*$B$9-X85*$B$10-X88 -> 1183.9693 | Y90: =(Y86-$F$14*$F$9)*(1-$B$11)+Y85*$B$9-Y85*$B$10-Y88 -> 1280.6137 | Z90: =(Z86-$F$14*$F$9)*(1-$B$11)+Z85*$B$9-Z85*$B$10-Z88 -> 1376.3159 | AA90: =(AA86-$F$14*$F$9)*(1-$B$11)+AA85*$B$9-AA85*$B$10-AA88 -> 1471.0494
W94: ='DCF_Forecast Revenue'!$I$34*(1+'DCF_Forecast Revenue'!$D$19) -> 6322.109 | X94: =W94*(1+'DCF_Forecast Revenue'!$E$19) -> 6891.0988 | Y94: =X94*(1+'DCF_Forecast Revenue'!$F$19) -> 7442.3867 | Z94: =Y94*(1+'DCF_Forecast Revenue'!$G$19) -> 8037.7777 | AA94: =Z94*(1+'DCF_Forecast Revenue'!$H$19) -> 8600.4221 | AC94: =(AA97/'DCF_Forecast Revenue'!$I$47)^(1/5)-1 -> 0.087183301
W95: ='DCF_Forecast Revenue'!$I$36*(1+'DCF_Forecast Revenue'!$D$13) -> 1410.896 | X95: =W95*(1+'DCF_Forecast Revenue'!$E$13) -> 1530.8222 | Y95: =X95*(1+'DCF_Forecast Revenue'!$F$13) -> 1653.2879 | Z95: =Y95*(1+'DCF_Forecast Revenue'!$G$13) -> 1777.2845 | AA95: =Z95*(1+'DCF_Forecast Revenue'!$H$13) -> 1901.6944 | AC95: =(SUMPRODUCT(W101:AA101,$B$54:$F$54)+AA101*(1+$B$15)/($F$10-$B$15)*$F$54-$F$13)/$F$11 -> 251.74728
W96: ='DCF_Forecast Revenue'!$I$38*(1+'DCF_Forecast Revenue'!$D$26) -> 973.59 | X96: =W96*(1+'DCF_Forecast Revenue'!$E$26) -> 1109.8926 | Y96: =X96*(1+'DCF_Forecast Revenue'!$F$26) -> 1254.1786 | Z96: =Y96*(1+'DCF_Forecast Revenue'!$G$26) -> 1404.6801 | AA96: =Z96*(1+'DCF_Forecast Revenue'!$H$26) -> 1559.1949 | AC96: =(SUMPRODUCT(W102:AA102,$B$56:$F$56)+AA102*(1+$B$15)/($F$8-$B$15)*$F$56)/$F$11 -> 190.06818
W97: =SUM(W94:W96) -> 8706.595 | X97: =SUM(X94:X96) -> 9531.8136 | Y97: =SUM(Y94:Y96) -> 10349.853 | Z97: =SUM(Z94:Z96) -> 11219.742 | AA97: =SUM(AA94:AA96) -> 12061.311
W98: =W97-W97*$B$6-W97*$B$7-W97*$B$8 -> 1656.6132 | X98: =X97-X97*$B$6-X97*$B$7-X97*$B$8 -> 1813.6284 | Y98: =Y97-Y97*$B$6-Y97*$B$7-Y97*$B$8 -> 1969.2777 | Z98: =Z97-Z97*$B$6-Z97*$B$7-Z97*$B$8 -> 2134.7924 | AA98: =AA97-AA97*$B$6-AA97*$B$7-AA97*$B$8 -> 2294.9187
W99: =W97*$B$12/365+(W97*$B$6)*$B$13/365-(W97*$B$6)*$B$14/365 -> 1304.1746 | X99: =X97*$B$12/365+(X97*$B$6)*$B$13/365-(X97*$B$6)*$B$14/365 -> 1427.7854 | Y99: =Y97*$B$12/365+(Y97*$B$6)*$B$13/365-(Y97*$B$6)*$B$14/365 -> 1550.3209 | Z99: =Z97*$B$12/365+(Z97*$B$6)*$B$13/365-(Z97*$B$6)*$B$14/365 -> 1680.6229 | AA99: =AA97*$B$12/365+(AA97*$B$6)*$B$13/365-(AA97*$B$6)*$B$14/365 -> 1806.6829
W100: =W99-'DCF_Forecast Revenue'!$I$149 -> 174.47461 | X100: =X99-W99 -> 123.61079 | Y100: =Y99-X99 -> 122.53546 | Z100: =Z99-Y99 -> 130.30204 | AA100: =AA99-Z99 -> 126.05997
W101: =W98*(1-$B$11)+W97*$B$9-W97*$B$10-W100 -> 1189.3863 | X101: =X98*(1-$B$11)+X97*$B$9-X97*$B$10-X100 -> 1369.518 | Y101: =Y98*(1-$B$11)+Y97*$B$9-Y97*$B$10-Y100 -> 1498.7367 | Z101: =Z98*(1-$B$11)+Z97*$B$9-Z97*$B$10-Z100 -> 1627.2355 | AA101: =AA98*(1-$B$11)+AA97*$B$9-AA97*$B$10-AA100 -> 1763.3068
W102: =(W98-$F$14*$F$9)*(1-$B$11)+W97*$B$9-W97*$B$10-W100 -> 1029.5781 | X102: =(X98-$F$14*$F$9)*(1-$B$11)+X97*$B$9-X97*$B$10-X100 -> 1209.7098 | Y102: =(Y98-$F$14*$F$9)*(1-$B$11)+Y97*$B$9-Y97*$B$10-Y100 -> 1338.9285 | Z102: =(Z98-$F$14*$F$9)*(1-$B$11)+Z97*$B$9-Z97*$B$10-Z100 -> 1467.4273 | AA102: =(AA98-$F$14*$F$9)*(1-$B$11)+AA97*$B$9-AA97*$B$10-AA100 -> 1603.4986

Sheet 9. Standardlized_Income
F3: =SUM(D8:D11) -> 1859.4
B4: Line Item | D4: Vulcan | J4: MLM | L4: KNF | M4: CRG | N4: CRH | P4: CX | R4: EXP
B5: Period | D5: FY2025 | E5: FY2024 | F5: FY2023 | G5: FY2022 | H5: FY2021 | J5: FY2025 | L5: FY2025 | N5: FY2025 | P5: FY2025 | R5: FY2025
B7: BALANCE SHEET
B8: Cash & Short-Term Investments | D8: 183.3 | E8: 559.7 | F8: 931.1 | G8: 161.4 | H8: 235 | J8: 67 | L8: 123.42 | N8: 4096 | P8: 1976.07 | R8: 20.4
B9: Trade Receivables | D9: 887.7 | E9: 892.3 | F9: 889.7 | G9: 845.6 | H9: 783.2 | J9: 708 | L9: 150.65 | N9: 5178 | P9: 1769.5 | R9: 212.33
B10: Inventories | D10: 680.5 | E10: 681.8 | F10: 615.6 | G10: 579.3 | H10: 521.3 | J10: 1078 | L10: 435.71 | N10: 5251 | P10: 1522.35 | R10: 415.18
B11: Other Current Assets | D11: 107.9 | E11: 131.9 | F11: 88.5 | G11: 116 | H11: 101.6 | J11: 95 | L11: 46.23 | N11: 61 | P11: 0 | R11: 10.73
B12: Total Current Assets | D12: 2567.9 | E12: 2265.7 | F12: 2524.9 | G12: 1902 | H12: 1696.6 | J12: 3193 | L12: 960.92 | N12: 15254 | P12: 6096.77 | R12: 668.66
B13: PP&E, Net | D13: 8670.1 | E13: 8987.9 | F13: 6729.4 | G13: 6623.9 | H13: 6238.2 | J13: 10657 | L13: 2081.52 | N13: 26408 | P13: 12168.49 | R13: 1822.3
B14: Goodwill | D14: 3780.9 | E14: 3788.1 | F14: 3531.7 | G14: 3689.6 | H14: 3696.7 | J14: 3614 | L14: 519.67 | N14: 13099 | P14: 7169.51 | R14: 469.89
B15: Other Intangibles, Net | D15: 1489 | E15: 1714.7 | F15: 1460.7 | G15: 1702.1 | H15: 1749 | J15: 459 | L15: 32.68 | N15: 2048 | P15: 1990.31 | R15: 125.86
B16: Other Non-Current Assets | D16: 158.8 | E16: 317.1 | F16: 267.7 | G16: 285.2 | H16: 268 | J16: 788 | L16: 0 | N16: 1018 | P16: 536.48 | R16: 37.8
B17: Total Assets | D17: 16700.4 | E17: 17104.8 | F17: 14545.7 | G17: 14234.6 | H17: 13682.6 | J17: 18711 | L17: 3650.11 | N17: 58329 | P17: 28965.51 | R17: 3264.59
B19: Trade Payables | D19: 438.5 | E19: 407 | F19: 390.4 | G19: 454.5 | H19: 365.5 | J19: 389 | L19: 145.58 | N19: 3263 | P19: 3107.89 | R19: 129.9
B20: Short-Term Debt & Current Maturities | D20: 6.2 | E20: 411.2 | F20: 13 | G20: 122.8 | H20: 40.6 | J20: 45 | L20: 11.71 | N20: 1291 | P20: 1454.44 | R20: 15
... B31: Total Debt (ST + LT) | D31: 4372.9 | E31: 5327.8 | F31: 3906.9 | G31: 4032.8 | H31: 3975.9 | J31: 5625 | L31: 1165.54 | N31: 18187 | P31: 6779.99 | R31: 1238.32
B33: INCOME STATEMENT
B34: Revenue | D34: 7941.1 | E34: 7417.7 | F34: 7781.9 | G34: 7315.2 | H34: 5552.2 | J34: 6150 | L34: 3146.01 | N34: 37447 | P34: 16131.88 | R34: 2260.51
B35: Cost of Revenues | D35: 5766.5 | E35: 5418.1 | F35: 5833.4 | G35: 5757.5 | H35: 4178.8 | J35: 4261 | L35: 2568.68 | N35: 23919 | P35: 10821.37 | R35: 1587.37
B36: Gross Profit | D36: 2174.6 | E36: 1999.6 | F36: 1948.5 | G36: 1557.7 | H36: 1373.4 | J36: 1889 | L36: 577.33 | N36: 13528 | P36: 5310.51 | R36: 673.14
B37: SG&A Expenses | D37: 564.1 | E37: 531.1 | F37: 542.8 | G37: 515.1 | H37: 417.6 | J37: 443 | L37: 280.65 | N37: 8205 | P37: 3521.37 | R37: 73.94
B38: Other Operating Expense/(Income) | D38: 83.1 | E38: 72.4 | F38: 83.5 | G38: 13.1 | H38: -15.9 | J38: -47 | L38: -0.8 | N38: 0 | P38: 784.29 | R38: -6.42
B39: EBIT (Operating Profit) | D39: 1527.4 | E39: 1396.1 | F39: 1322.2 | G39: 1029.5 | H39: 971.7 | J39: 1493 | L39: 297.47 | N39: 5323 | P39: 1004.85 | R39: 605.62
B40: Interest Expense | D40: 239.7 | E40: 191.2 | F40: 196.1 | G40: 169.2 | H40: 149.3 | J40: 230 | L40: 81.94 | N40: 810 | P40: 300.78 | R40: 40.24
B41: Other Non-Operating Items | D41: 91.6 | E41: 66.9 | F41: 140.8 | G41: 15.8 | H41: 130.8 | J41: 9 | L41: 5.77 | N41: 263 | P41: -173.61 | R41: -14.39
B42: Pre-Tax Income | D42: 1390.1 | E42: 1172.1 | F42: 1245.1 | G42: 788.1 | H42: 873.8 | J42: 1226 | L42: 213.21 | N42: 4805 | P42: 789.35 | R42: 591.49
B43: Income Taxes | D43: 307.5 | E43: 251.4 | F43: 299.4 | G43: 193 | H43: 200.1 | J43: 236 | L43: 56.14 | N43: 1041 | P43: 385.01 | R43: 128.07
B44: Net Income | D44: 1076.7 | E44: 911.9 | F44: 933.2 | G44: 575.6 | H44: 670.8 | J44: 1137 | L44: 157.07 | N44: 3753 | P44: 960.16 | R44: 463.42
B46: EBITDA | D46: 2275.9 | E46: 2028.3 | F46: 1939.2 | G46: 1617 | H46: 1434.7 | J46: 2130 | L46: 491.21 | N46: 7479 | P46: 2295.78 | R46: 764.52
B47: Depreciation & Amortization | D47: 748.5 | E47: 632.2 | F47: 617 | G47: 587.5 | H47: 463 | J47: 637 | L47: 193.74 | N47: 2156 | P47: 1290.93 | R47: 158.9
B48: Effective Tax Rate | D48: 0.22120711 | E48: 0.21448682 | F48: 0.24046261 | G48: 0.24489278 | H48: 0.22899977 | J48: =J43/J42 -> 0.19249592 | L48: =L43/L42 -> 0.26330848 | N48: =N43/N42 -> 0.21664932 | P48: =P43/P42 -> 0.48775575 | R48: =R43/R42 -> 0.21652099
B50: CASH FLOW STATEMENT
B51: Net Cash from Operating Activities | D51: 1813 | E51: 1409.6 | F51: 1536.8 | G51: 1148.2 | H51: 1011.9 | J51: 1785 | L51: 278.48 | N51: 5625 | P51: 2057.69 | R51: 548.55
B52: Capital Expenditures | D52: 677.7 | E52: 603.5 | F52: 872.6 | G52: 612.6 | H52: 451.3 | J52: 807 | L52: 348.04 | N52: 2713 | P52: 1325.28 | R52: 195.28
B53: Free Cash Flow | D53: 1135.3 | E53: 806.1 | F53: 664.2 | G53: 535.6 | H53: 560.6 | J53: 978 | L53: -69.57 | N53: 2912 | P53: 732.41 | R53: 353.27
B55: Acquisitions, Net | D55: 113.9 | E55: -2266 | F55: 614.5 | G55: -479.2 | H55: -1639.4 | J55: -647 | L55: -609.99 | N55: -3332 | P55: 964.83 | R55: -174.85
B56: Other Investing Activities | D56: 10.5 | E56: -0.1 | F56: 0 | G56: 0.1 | H56: 0.1 | J56: -134 | L56: -3.1 | N56: 290 | P56: -6.93 | R56: 0
B57: Net Cash from Investing Activities | D57: -529.2 | E57: -2814.9 | F57: -163.5 | G57: -1053 | H57: -1874.1 | J57: -1588 | L57: -913.66 | N57: -6045 | P57: -263.46 | R57: -370.13
B59: Dividends Paid | D59: 259.8 | E59: 244.4 | F59: 228.4 | G59: 212.6 | H59: 196.4 | J59: 197 | L59: 0 | N59: 996 | P59: 127.47 | R59: 33.72
B60: Share Buybacks/(Issuances) | D60: -438.4 | E60: -68.8 | F60: -200 | G60: 0 | H60: 0 | J60: -450 | L60: -2.65 | N60: -1181 | P60: 994.5 | R60: -291.91
B61: Debt Issuance/(Reduction), Net | D61: -961.4 | E61: 1436.5 | F61: -131.3 | G61: 58.5 | H61: 134.8 | J61: -118 | L61: 491.19 | N61: 2736 | P61: -434.03 | R61: 143.75
B62: Other Financing Activities | D62: -35.6 | E62: -66.4 | F62: -25.9 | G62: -21.1 | H62: -32.7 | J62: -35 | L62: -11.07 | N62: 9 | P62: -1222.11 | R62: -11.06
B63: Net Cash from Financing Activities | D63: -1695.2 | E63: 1056.9 | F63: -585.6 | G63: -175.2 | H63: -94.3 | J63: -800 | L63: 477.47 | N63: 596 | P63: -789.16 | R63: -192.94
B64: Finished Goods Inventory | D64: 557.7 | E64: 534.6 | F64: 494.4 | G64: 439.3 | H64: 418 | J64: 1378 | L64: 304.28 | N64: 2596 | P64: 0 | R64: 91.1
... B67: Full Time Employees | D67: 11172 | E67: 11436 | F67: 10382 | G67: 11397 | H67: 11437 | J67: 9600 | L67: 5298 | N67: 83032 | P67: 39462 | R67: 2500

Sheet DCF_Forecast Revenue
B1: Assumption model
B2: Scenario Selector
B3: 1 | C3: 2
B4: 2
B5: 3
L7: Year | M7: Aggregates | N7: Asphalt | O7: Concrete | P7: Calcium | Q7: Total Revenue
B8: REVENUE GROWTH ASSUMPTIONS BY ASPHALT (by Segment, Multi-Stage) | L8: 2021 | M8: 4,000.7 | N8: 777.8 | O8: 766.8 | P8: 6.9 | Q8: 5,552.2
B9: Revenue Growth | D9: FY2026F | E9: FY2027F | F9: FY2028F | G9: FY2029F | H9: FY2030F | L9: 2022 | M9: 4,731.1* | N9: 990.2 | O9: 1,593.9 | P9: included in Aggregates* | Q9: 7,315.2
B10: Active (auto-selected via CHOOSE) | D10: =CHOOSE($C$3,D11,D12,D13) -> 0.01 | E10: =CHOOSE($C$3,E11,E12,E13) -> 0.01 | F10: =CHOOSE($C$3,F11,F12,F13) -> 0.005 | G10: =CHOOSE($C$3,G11,G12,G13) -> 0.005 | H10: =CHOOSE($C$3,H11,H12,H13) -> 0 | L10: 2023 | M10: 5,391.9* | N10: 1,140.7 | O10: 1,249.3 | P10: included in Aggregates* | Q10: 7,781.9
B11: Base Case | D11: 0.07 | E11: 0.07 | F11: 0.065 | G11: 0.065 | H11: 0.06 | L11: 2024 | M11: 5,518.6 | N11: 1,245.6 | O11: 653.5 | P11: included in Aggregates | Q11: 7,417.7
B12: Downside Case | D12: 0.01 | E12: 0.01 | F12: 0.005 | G12: 0.005 | H12: 0 | L12: 2025 | M12: 5,800.1 | N12: 1,294.4 | O12: 846.6 | P12: included in Aggregates | Q12: 7,941.1
B13: Upside Case | D13: 0.09 | E13: 0.085 | F13: 0.08 | G13: 0.075 | H13: 0.07
B14: REVENUE GROWTH ASSUMPTIONS BY AGGREGATES (by Segment, Multi-Stage)
B15: Revenue Growth | D15: FY2026F | E15: FY2027F | F15: FY2028F | G15: FY2029F | H15: FY2030F
B16: Active (auto-selected via CHOOSE) | D16: =CHOOSE($C$3,D17,D18,D19) -> 0.025 | E16: =CHOOSE($C$3,E17,E18,E19) -> 0.025 | F16: =CHOOSE($C$3,F17,F18,F19) -> 0.02 | G16: =CHOOSE($C$3,G17,G18,G19) -> 0.02 | H16: =CHOOSE($C$3,H17,H18,H19) -> 0.02
B17: Base Case | D17: 0.075 | E17: 0.07 | F17: 0.065 | G17: 0.06 | H17: 0.055
B18: Downside Case | D18: 0.025 | E18: 0.025 | F18: 0.02 | G18: 0.02 | H18: 0.02
B19: Upside Case | D19: 0.09 | E19: 0.09 | F19: 0.08 | G19: 0.08 | H19: 0.07
B21: REVENUE GROWTH ASSUMPTIONS BY CONCRETE (by Segment, Multi-Stage)
B22: Revenue Growth | D22: FY2026F | E22: FY2027F | F22: FY2028F | G22: FY2029F | H22: FY2030F
B23: Active (auto-selected via CHOOSE) | D23: =CHOOSE($C$3,D24,D25,D26) -> 0.03 | E23: =CHOOSE($C$3,E24,E25,E26) -> 0.025 | F23: =CHOOSE($C$3,F24,F25,F26) -> 0.02 | G23: =CHOOSE($C$3,G24,G25,G26) -> 0.01 | H23: =CHOOSE($C$3,H24,H25,H26) -> 0
B24: Base Case | D24: 0.1 | E24: 0.09 | F24: 0.08 | G24: 0.07 | H24: 0.06
B25: Downside Case | D25: 0.03 | E25: 0.025 | F25: 0.02 | G25: 0.01 | H25: 0
B26: Upside Case | D26: 0.15 | E26: 0.14 | F26: 0.13 | G26: 0.12 | H26: 0.11
K28: =I38/I41 -> 0.10660992
B32: REVENUE BUILD BY SEGMENT
B33: ($mm unless noted) | E33: FY2021A | F33: FY2022A | G33: FY2023A | H33: FY2024A | I33: FY2025A | J33: FY2026E | K33: FY2027E | L33: FY2028E | M33: FY2029E | N33: FY2030E
B34: Aggregates Revenue | C34: Crushed stone, sand & gravel | E34: 4000.7 | F34: 4731.1 | G34: 5391.9 | H34: 5518.5 | I34: 5800.1 | J34: =I34*(1+J35) -> 5945.1025 | K34: =J34*(1+K35) -> 6093.7301 | L34: =K34*(1+L35) -> 6215.6047 | M34: =L34*(1+M35) -> 6339.9168 | N34: =M34*(1+N35) -> 6466.7151 | Q34: Year | R34: 2021 | S34: 2022 | T34: 2023 | U34: 2024 | V34: 2025
B35: YoY Growth | C35: Vol × Price; infra + private | F35: =F34/E34-1 -> 0.18256805 | G35: =G34/F34-1 -> 0.13967154 | H35: =H34/G34-1 -> 0.023479664 | I35: =I34/H34-1 -> 0.051028359 | J35: =D16 -> 0.025 | K35: =E16 -> 0.025 | L35: =F16 -> 0.02 | M35: =G16 -> 0.02 | N35: =H16 -> 0.02 | Q35: Income Statement
B36: Asphalt Revenue | C36: Liquid asphalt + mix plant | E36: 777.8 | F36: 990.2 | G36: 1140.7 | H36: 1245.6 | I36: 1294.4 | J36: =I36*(1+J37) -> 1307.344 | K36: =J36*(1+K37) -> 1320.4174 | L36: =K36*(1+L37) -> 1327.0195 | M36: =L36*(1+M37) -> 1333.6546 | N36: =M36*(1+N37) -> 1333.6546 | Q36: Revenue | R36: 5552.2 | S36: 7315.2 | T36: 7781.9 | U36: 7417.7 | V36: 7941.1
B37: YoY Growth | C37: Linked to road-paving spend | F37: =F36/E36-1 -> 0.27307791 | G37: =G36/F36-1 -> 0.1519895 | H37: =H36/G36-1 -> 0.091961077 | I37: =I36/H36-1 -> 0.039177906 | J37: =D10 -> 0.01 | K37: =E10 -> 0.01 | L37: =F10 -> 0.005 | M37: =G10 -> 0.005 | N37: =H10 -> 0 | Q37: Cost of Revenues | R37: 4178.8 | S37: 5757.5 | T37: 5833.4 | U37: 5418.1 | V37: 5766.5
B38: Concrete / RMX Revenue | C38: Ready-mix (divested FY2024) | E38: 766.8 | F38: 1593.9 | G38: 1249.3 | H38: 653.5 | I38: 846.6 | J38: =I38*(1+J39) -> 871.998 | K38: =J38*(1+K39) -> 893.79795 | L38: =K38*(1+L39) -> 911.67391 | M38: =L38*(1+M39) -> 920.79065 | N38: =M38*(1+N39) -> 920.79065 | Q38: Gross Profit | R38: 1373.4 | S38: 1557.7 | T38: 1948.5 | U38: 1999.6 | V38: 2174.6
B39: YoY Growth | F39: =(F38-E38)/E38 -> 1.0786385 | G39: =(G38-F38)/F38 -> -0.21619926 | H39: =(H38-G38)/G38 -> -0.47690707 | I39: =(I38-H38)/H38 -> 0.29548585 | J39: =D23 -> 0.03 | K39: =E23 -> 0.025 | L39: =F23 -> 0.02 | M39: =G23 -> 0.01 | N39: =H23 -> 0 | Q39: SG&A | R39: 417.6 | S39: 515.1 | T39: 542.8 | U39: 531.1 | V39: 564.1
Q40: Other Operating (Income) / Expense | R40: -15.9 | S40: 13.1 | T40: 83.5 | U40: 72.4 | V40: 83.1
B41: Total Revenue | E41: =E34+E36+E38 -> 5545.3 | F41: =F34+F36+F38 -> 7315.2 | G41: =G34+G36+G38 -> 7781.9 | H41: =H34+H36+H38 -> 7417.6 | I41: =I34+I36+I38 -> 7941.1 | J41: =J34+J36+J38 -> 8124.4445 | K41: =K34+K36+K38 -> 8307.9455 | L41: =L34+L36+L38 -> 8454.2981 | ... N41: =N34+N36+N38 -> 8721.1604 | Q41: EBITDA | R41: 1434.7 | S41: 1617 | T41: 1939.2 | U41: 2028.3 | V41: 2275.9
B42: YoY Growth | E42: 0.08556157 | F42: =F41/E41-1 -> 0.31917119 | G42: =G41/F41-1 -> 0.063798666 | H42: =H41/G41-1 -> -0.04681376 | I42: =I41/H41-1 -> 0.070575388 | J42: =J41/I41-1 -> 0.023088048 | K42: =K41/J41-1 -> 0.022586277 | L42: =L41/K41-1 -> 0.017615986 | M42: =M41/L41-1 -> 0.016567186 | N42: =N41/M41-1 -> 0.014753665 | Q42: EBIT | R42: 971.7 | S42: 1029.5 | T42: 1322.2 | U42: 1396.1 | V42: 1527.4
Q43: Net Income | R43: 670.8 | S43: 575.6 | T43: 933.2 | U43: 911.9 | V43: 1076.7
B45: INCOME STATEMENT | O45: =1-K49 -> 0.26459715 | P45: MODEL ASSUMPTIONS
E46: FY2021 | F46: FY2022 | G46: FY2023 | H46: FY2024 | I46: FY2025 | J46: FY2026E | K46: FY2027E | L46: FY2028E | M46: FY2029E | N46: FY2030E | Q46: Assumption | R46: Value | S46: Source
B47: Revenue | E47: =E41 -> 5545.3 | F47: =F41 -> 7315.2 | G47: =G41 -> 7781.9 | H47: =H41 -> 7417.6 | I47: =I41 -> 7941.1 | J47: =J41 -> 8124.4445 | K47: =K41 -> 8307.9455 | L47: =L41 -> 8454.2981 | ... N47: =N41 -> 8721.1604 | Q47: Effective Tax Rate | R47: =AVERAGE($E$67:$I$67) -> 0.21774036 | S47: 5Y avg actual (FY21-25)
B48: Cost of Revenues | E48: =Sheet10!G228 -> 4178.8 | F48: =Sheet10!F228 -> 5757.5 | G48: =Sheet10!E228 -> 5833.4 | H48: =Sheet10!D228 -> 5418.1 | I48: =Sheet10!C228 -> 5766.5 | J48: =J47*AVERAGE($G$49:$I$49) -> 5974.7396 | K48: =K47*AVERAGE($G$49:$I$49) -> 6109.6867 | L48: =L47*AVERAGE($G$49:$I$49) -> 6217.3149 | M48: =M47*AVERAGE($G$49:$I$49) -> 6320.3183 | N48: =N47*AVERAGE($G$49:$I$49) -> 6413.5662 | Q48: D&A % of Revenue | R48: =AVERAGE($E$59:$I$59) -> 0.084515819 | S48: 5Y avg actual (info only)
B49: % of Revenue | E49: =E48/E47 -> 0.7535751 | F49: =F48/F47 -> 0.78705982 | G49: =G48/G47 -> 0.74961128 | H49: =H48/H47 -> 0.73043842 | I49: =I48/I47 -> 0.72615884 | J49: =J48/J47 -> 0.73540285 | K49: =K48/K47 -> 0.73540285 | L49: =L48/L47 -> 0.73540285 | ... N49: =N48/N47 -> 0.73540285 | O49: =AVERAGE(E49:J49) -> 0.74704105 | Q49: SG&A % of Revenue | R49: =AVERAGE($E$53:$I$53) -> 0.071621825 | S49: 5Y avg actual (FY21-25)
B50: Gross Profit | E50: =E47-E48 -> 1366.5 | F50: =F47-F48 -> 1557.7 | G50: =G47-G48 -> 1948.5 | H50: =H47-H48 -> 1999.5 | I50: =I47-I48 -> 2174.6 | J50: =J47-J48 -> 2149.7049 | K50: =K47-K48 -> 2198.2587 | L50: =L47-L48 -> 2236.9832 | ... N50: =N47-N48 -> 2307.5942 | Q50: Capex % of Revenue | R50: =AVERAGE($E$160:$I$160) -> 0.088792208 | S50: 5Y avg actual (FY21-25)
B51: % of Revenue | E51: =1-E49 -> 0.2464249 | F51: =1-F49 -> 0.21294018 | G51: =1-G49 -> 0.25038872 | H51: =1-H49 -> 0.26956158 | I51: =1-I49 -> 0.27384116 | J51: =1-J49 -> 0.26459715 | K51: =1-K49 -> 0.26459715 | L51: =1-L49 -> 0.26459715 | ... N51: =1-N49 -> 0.26459715 | Q51: Interest Rate on Debt | R51: =AVERAGE($F$63/$F$166,$G$63/$G$166,$H$63/$H$166,$I$63/$I$166) -> 0.046278038 | S51: Avg interest / opening debt (FY22-25)
B52: SG&A | E52: =Sheet10!G230 -> 417.6 | F52: =Sheet10!F230 -> 515.1 | G52: =Sheet10!E230 -> 542.8 | H52: =Sheet10!D230 -> 531.1 | I52: =Sheet10!C230 -> 564.1 | J52: =J47*$R$49 -> 581.88754 | K52: =K47*$R$49 -> 595.03021 | L52: =L47*$R$49 -> 605.51226 | M52: =M47*$R$49 -> 615.54389 | N52: =N47*$R$49 -> 624.62542 | Q52: Total Debt ($M) | R52: =I168 -> 4372.9 | S52: FY2025 closing debt from debt schedule
B53: % of Revenue | E53: =E52/E47 -> 0.075307017 | F53: =F52/F47 -> 0.070415026 | G53: =G52/G47 -> 0.069751603 | H53: =H52/H47 -> 0.071599978 | I53: =I52/I47 -> 0.071035499 | J53: =J52/J47 -> 0.071621825 | K53: =K52/K47 -> 0.071621825 | L53: =L52/L47 -> 0.071621825 | ... N53: =N52/N47 -> 0.071621825 | Q53: DSO (days) | R53: =AVERAGE($E$140:$I$140) -> 46.760102 | S53: 5Y avg actual (FY21-25)
B54: Other Operating (Income) / Expense | E54: =Sheet10!G231 -> -15.9 | F54: =Sheet10!F231 -> 13.1 | G54: =Sheet10!E231 -> 83.5 | H54: =Sheet10!D231 -> 72.4 | I54: =Sheet10!C231 -> 83.1 | J54: =J47*AVERAGE($G$55:$I$55) -> 83.831111 | K54: =K47*AVERAGE($G$55:$I$55) -> 85.724544 | L54: =L47*AVERAGE($G$55:$I$55) -> 87.234666 | M54: =M47*AVERAGE($G$55:$I$55) -> 88.679899 | N54: =N47*AVERAGE($G$55:$I$55) -> 89.988253 | Q54: DIO (days) | R54: =AVERAGE($E$141:$I$141) -> 41.956181 | S54: 5Y avg actual (FY21-25)
B55: % of Revenue | E55: =E54/E47 -> -0.002867293 | F55: =F54/F47 -> 0.0017907918 | G55: =G54/G47 -> 0.010730027 | H55: =H54/H47 -> 0.0097605695 | I55: =I54/I47 -> 0.010464545 | J55: =J54/J47 -> 0.010318381 | K55: =K54/K47 -> 0.010318381 | L55: =L54/L47 -> 0.010318381 | ... N55: =N54/N47 -> 0.010318381 | Q55: DPO (days) | R55: =AVERAGE($E$142:$I$142) -> 28.067917 | S55: 5Y avg actual (FY21-25)
B56: EBIT | E56: =E50-E52-E54 -> 964.8 | F56: =F50-F52-F54 -> 1029.5 | G56: =G50-G52-G54 -> 1322.2 | H56: =H50-H52-H54 -> 1396 | I56: =I50-I52-I54 -> 1527.4 | J56: =J50-J52-J54 -> 1483.9862 | K56: =K50-K52-K54 -> 1517.504 | L56: =L50-L52-L54 -> 1544.2363 | ... N56: =N50-N52-N54 -> 1592.9805 | Q56: Terminal Growth Rate (g) | R56: 0.03 | S56: Scenario-linked
B57: % of Revenue | E57: =E56/E47 -> 0.17398518 | F57: =F56/F47 -> 0.14073436 | G57: =G56/G47 -> 0.16990709 | H57: =H56/H47 -> 0.18820104 | I57: =I56/I47 -> 0.19234111 | J57: =J56/J47 -> 0.18265695 | K57: =K56/K47 -> 0.18265695 | L57: =L56/L47 -> 0.18265695 | ... N57: =N56/N47 -> 0.18265695 | Q57: WACC | R57: ='DCF-WACC '!C15 -> 0.071418944 | S57: From DCF-Summary
B58: Depreciation & Amortization | E58: =Sheet10!G333 -> 463 | F58: =Sheet10!F333 -> 587.5 | G58: =Sheet10!E333 -> 617 | H58: =Sheet10!D333 -> 632.2 | I58: =Sheet10!C333 -> 748.5 | J58: =J157 -> 790.17113 | K58: =K157 -> 783.90235 | L58: =L157 -> 779.68983 | M58: =M157 -> 777.04557 | N58: =N157 -> 775.77573 | Q58: Cost of Equity (Ke) | R58: ='DCF-WACC '!C3 -> 0.08565 | S58: From DCF-Summary
B59: % of Revenue | E59: =E58/E47 -> 0.08349413 | F59: =F58/F47 -> 0.080312227 | G59: =G58/G47 -> 0.07928655 | H59: =H58/H47 -> 0.085229724 | I59: =I58/I47 -> 0.094256463 | J59: =J58/J47 -> 0.09725848 | K59: =K58/K47 -> 0.094355741 | L59: =L58/L47 -> 0.092224076 | ... N59: =N58/N47 -> 0.08895327 | O59: =AVERAGE(E59:J59) -> 0.086639596
B60: EBITDA | E60: =E56+E58 -> 1427.8 | F60: =F56+F58 -> 1617 | G60: =G56+G58 -> 1939.2 | H60: =H56+H58 -> 2028.2 | I60: =I56+I58 -> 2275.9 | J60: =J56+J58 -> 2274.1574 | K60: =K56+K58 -> 2301.4063 | L60: =L56+L58 -> 2323.9261 | ... N60: =N56+N58 -> 2368.7563 | O60: =AVERAGE(E60:I60) -> 1857.62 | Q60: Risk-Free Rate (Rf) | R60: 0.04 | S60: 10Y UST
B61: % EBITDA Margin | E61: =E60/E47 -> 0.25747931 | F61: =F60/F47 -> 0.22104659 | G61: =G60/G47 -> 0.24919364 | H61: =H60/H47 -> 0.27343076 | I61: =I60/I47 -> 0.28659757 | J61: =J60/J47 -> 0.27991543 | K61: =K60/K47 -> 0.27701269 | L61: =L60/L47 -> 0.27488102 | ... N61: =N60/N47 -> 0.27161022 | Q61: Equity Beta (β) | R61: 0.8277 | S61: Regression
Q62: Equity Risk Premium | R62: 0.055 | S62: Market consensus
B63: Interest Expense | E63: =Sheet10!G367 -> 149.3 | F63: =Sheet10!F367 -> 169.2 | G63: =Sheet10!E367 -> 196.1 | H63: =Sheet10!D367 -> 191.2 | I63: =Sheet10!C367 -> 239.7 | J63: =J166*$R$51 -> 202.36923 | K63: =K166*$R$51 -> 202.36923 | L63: =L166*$R$51 -> 202.36923 | M63: =M166*$R$51 -> 202.36923 | N63: =N166*$R$51 -> 202.36923 | Q63: Pre-Tax Cost of Debt (Kd) | R63: 0.0494 | S63: Weighted avg
B64: Other Non-Operating Items | E64: =SUM(Sheet10!G245,Sheet10!G246) -> 130.8 | F64: =SUM(Sheet10!F245,Sheet10!F246) -> 15.8 | G64: =SUM(Sheet10!E245,Sheet10!E246) -> 140.8 | H64: =SUM(Sheet10!D245,Sheet10!D246) -> 66.9 | I64: =SUM(Sheet10!C245,Sheet10!C246) -> 91.6 | J64: =0 -> 0 | K64: =0 -> 0 | L64: =0 -> 0 | M64: =0 -> 0 | N64: =0 -> 0 | Q64: Net Debt ($M) | R64: 4190 | S64: From 6. Multiple Valuation
B65: Pre-Tax Income | E65: =E56-E63+E64 -> 946.3 | F65: =F56-F63+F64 -> 876.1 | G65: =G56-G63+G64 -> 1266.9 | H65: =H56-H63+H64 -> 1271.7 | I65: =I56-I63+I64 -> 1379.3 | J65: =J56-J63+J64 -> 1281.617 | K65: =K56-K63+K64 -> 1315.1347 | L65: =L56-L63+L64 -> 1341.8671 | ... N65: =N56-N63+N64 -> 1390.6113 | Q65: Shares Outstanding (M) | R65: 130.58 | S65: From 6. Multiple Valuation
B66: Income Taxes | E66: =Sheet10!G260 -> 200.1 | F66: =Sheet10!F260 -> 193 | G66: =Sheet10!E260 -> 299.4 | H66: =Sheet10!D260 -> 251.4 | I66: =Sheet10!C260 -> 307.5 | J66: =J65*$R$47 -> 279.05975 | K66: =K65*$R$47 -> 286.35792 | L66: =L65*$R$47 -> 292.17862 | M66: =M65*$R$47 -> 297.74922 | N66: =N65*$R$47 -> 302.79221 | Q66: Current Share Price ($) | R66: 295.98 | S66: From 6. Multiple Valuation
B67: Effective Tax Rate | E67: =E66/E65 -> 0.21145514 | F67: =F66/F65 -> 0.22029449 | G67: =G66/G65 -> 0.23632489 | H67: =H66/H65 -> 0.19768813 | I67: =I66/I65 -> 0.22293917 | J67: =J66/J65 -> 0.21774036 | K67: =K66/K65 -> 0.21774036 | L67: =L66/L65 -> 0.21774036 | ... N67: =N66/N65 -> 0.21774036
B68: Net Income | E68: =E65-E66 -> 746.2 | F68: =F65-F66 -> 683.1 | G68: =G65-G66 -> 967.5 | H68: =H65-H66 -> 1020.3 | I68: =I65-I66 -> 1071.8 | J68: =J65-J66 -> 1002.5573 | K68: =K65-K66 -> 1028.7768 | L68: =L65-L66 -> 1049.6884 | ... N68: =N65-N66 -> 1087.8191
B69: % Net Margin | E69: =E68/E47 -> 0.13456441 | F69: =F68/F47 -> 0.093380906 | G69: =G68/G47 -> 0.12432696 | H69: =H68/H47 -> 0.13755123 | I69: =I68/I47 -> 0.13496871 | J69: =J68/J47 -> 0.1234001 | K69: =K68/K47 -> 0.12383047 | L69: =L68/L47 -> 0.12416033 | ... N69: =N68/N47 -> 0.1247333
B71: BALANCE SHEET
B72: ($mm unless noted) | E72: FY2021 | F72: FY2022 | G72: FY2023 | H72: FY2024 | I72: FY2025 | J72: FY2026E | K72: FY2027E | L72: FY2028E | M72: FY2029E | N72: FY2030E
B73: Cash & ST Investments | E73: =Sheet10!G8 -> 235 | F73: =Sheet10!F8 -> 161.4 | G73: =Sheet10!E8 -> 931.1 | H73: =Sheet10!D8 -> 559.7 | I73: =Sheet10!C8 -> 183.3 | J73: =J130 -> 794.35817 | K73: =K130 -> 1493.1455 | L73: =L130 -> 2180.5813 | M73: =M130 -> 2851.8257 | N73: =N130 -> 3507.2982
B74: Accounts Receivable | E74: =SUM(Sheet10!G11,Sheet10!G14) -> 838.7 | F74: =SUM(Sheet10!F11,Sheet10!F14) -> 1045.3 | G74: =SUM(Sheet10!E11,Sheet10!E14) -> 889.7 | H74: =SUM(Sheet10!D11,Sheet10!D14) -> 892.3 | I74: =SUM(Sheet10!C11,Sheet10!C14) -> 887.7 | J74: =J47*$R$53/365 -> 1040.8215 | K74: =K47*$R$53/365 -> 1064.3298 | L74: =L47*$R$53/365 -> 1083.079 | M74: =M47*$R$53/365 -> 1101.0226 | N74: =N47*$R$53/365 -> 1117.2667
B75: Inventory | E75: =Sheet10!G15 -> 521.3 | F75: =Sheet10!F15 -> 579.3 | G75: =Sheet10!E15 -> 615.6 | H75: =Sheet10!D15 -> 681.8 | I75: =Sheet10!C15 -> 680.5 | J75: =J48*$R$54/365 -> 686.787 | K75: =K48*$R$54/365 -> 702.29896 | L75: =L48*$R$54/365 -> 714.67065 | M75: =M48*$R$54/365 -> 726.51073 | N75: =N48*$R$54/365 -> 737.22943
B76: Asset Held for Sale | E76: =Sheet10!G20 -> 0 | F76: =Sheet10!F20 -> 0 | G76: =Sheet10!E20 -> 0 | H76: =Sheet10!D20 -> 0 | I76: =Sheet10!C20 -> 708.5 | J76: =I76 -> 708.5 | K76: =J76 -> 708.5 | L76: =K76 -> 708.5 | M76: =L76 -> 708.5 | N76: =M76 -> 708.5 | O76: -
B77: Other Current Assets | E77: =Sheet10!G21 -> 101.6 | F77: =Sheet10!F21 -> 116 | G77: =Sheet10!E21 -> 88.5 | H77: =Sheet10!D21 -> 131.9 | I77: =Sheet10!C21 -> 107.9 | J77: =I77 -> 107.9 | K77: =J77 -> 107.9 | L77: =K77 -> 107.9 | M77: =L77 -> 107.9 | N77: =M77 -> 107.9
B78: Total Current Assets | E78: =SUM(E73:E77) -> 1696.6 | F78: =SUM(F73:F77) -> 1902 | G78: =SUM(G73:G77) -> 2524.9 | H78: =SUM(H73:H77) -> 2265.7 | I78: =SUM(I73:I77) -> 2567.9 | J78: =SUM(J73:J77) -> 3338.3667 | K78: =SUM(K73:K77) -> 4076.1742 | L78: =SUM(L73:L77) -> 4794.731 | ... N78: =SUM(N73:N77) -> 6178.1943
B80: Long-Term Investment | E80: =Sheet10!G26 -> 34.1 | F80: =Sheet10!F26 -> 31.8 | G80: =Sheet10!E26 -> 31.3 | H80: =Sheet10!D26 -> 31.3 | I80: =Sheet10!C26 -> 33.7 | J80: =I80 -> 33.7 | K80: =J80 -> 33.7 | L80: =K80 -> 33.7 | M80: =L80 -> 33.7 | N80: =M80 -> 33.7
B81: Net Property, Plant & Equipment | E81: =E159 -> 6238.2 | F81: =F159 -> 6623.9 | G81: =G159 -> 6729.4 | H81: =H159 -> 8987.9 | I81: =I159 -> 8670.1 | J81: =J159 -> 8601.3162 | K81: =K159 -> 8555.0947 | L81: =L159 -> 8526.0807 | ... N81: =N159 -> 8510.7429
B82: Goodwill | E82: =Sheet10!G58 -> 3696.7 | F82: =Sheet10!F58 -> 3689.6 | G82: =Sheet10!E58 -> 3531.7 | H82: =Sheet10!D58 -> 3788.1 | I82: =Sheet10!C58 -> 3780.9 | J82: =I82 -> 3780.9 | K82: =J82 -> 3780.9 | L82: =K82 -> 3780.9 | M82: =L82 -> 3780.9 | N82: =M82 -> 3780.9
B83: Other Intangibles, net | E83: =Sheet10!G59 -> 1749 | F83: =Sheet10!F59 -> 1702.1 | G83: =Sheet10!E59 -> 1460.7 | H83: =Sheet10!D59 -> 1714.7 | I83: =Sheet10!C59 -> 1489 | J83: =I83 -> 1489 | K83: =J83 -> 1489 | L83: =K83 -> 1489 | M83: =L83 -> 1489 | N83: =M83 -> 1489
B84: Other Non-Current Assets | E84: =Sheet10!G55 -> 268 | F84: =Sheet10!F55 -> 285.2 | G84: =Sheet10!E55 -> 267.7 | H84: =Sheet10!D55 -> 317.1 | I84: =Sheet10!C55 -> 158.8 | J84: =I84 -> 158.8 | K84: =J84 -> 158.8 | L84: =K84 -> 158.8 | M84: =L84 -> 158.8 | N84: =M84 -> 158.8
B85: Total Assets | E85: =SUM(E78,E80:E84) -> 13682.6 | F85: =SUM(F78,F80:F84) -> 14234.6 | G85: =SUM(G78,G80:G84) -> 14545.7 | H85: =SUM(H78,H80:H84) -> 17104.8 | I85: =SUM(I78,I80:I84) -> 16700.4 | J85: =SUM(J78,J80:J84) -> 17402.083 | K85: =SUM(K78,K80:K84) -> 18093.669 | L85: =SUM(L78,L80:L84) -> 18783.212 | ... N85: =SUM(N78,N80:N84) -> 20151.337
B87: Accounts Payable | E87: =Sheet10!G67 -> 365.5 | F87: =Sheet10!F67 -> 454.5 | G87: =Sheet10!E67 -> 390.4 | H87: =Sheet10!D67 -> 407 | I87: =Sheet10!C67 -> 438.5 | J87: =J48*$R$55/365 -> 459.44792 | K87: =K48*$R$55/365 -> 469.82514 | L87: =L48*$R$55/365 -> 478.10158 | M87: =M48*$R$55/365 -> 486.02237 | N87: =N48*$R$55/365 -> 493.19298
B88: Accured Expenses - Short term | E88: =Sheet10!G68 -> 120.5 | F88: =Sheet10!F68 -> 112.7 | G88: =Sheet10!E68 -> 135.8 | H88: =Sheet10!D68 -> 124 | I88: =Sheet10!C68 -> 130.7 | J88: =I88 -> 130.7 | K88: =J88 -> 130.7 | L88: =K88 -> 130.7 | M88: =L88 -> 130.7 | N88: =M88 -> 130.7
B89: Short-Term Debt | E89: =E170 -> 40.6 | F89: =F170 -> 122.8 | G89: =G170 -> 13 | H89: =H170 -> 411.2 | I89: =I170 -> 6.2 | J89: =J170 -> 6.2 | K89: =K170 -> 6.2 | L89: =L170 -> 6.2 | ... N89: =N170 -> 6.2
B90: Other Current Liabilities | E90: =SUM(Sheet10!G74,Sheet10!G76) -> 193.5 | F90: =SUM(Sheet10!F74,Sheet10!F76) -> 218.5 | G90: =SUM(Sheet10!E74,Sheet10!E76) -> 211.1 | H90: =SUM(Sheet10!D74,Sheet10!D76) -> 247.6 | I90: =SUM(Sheet10!C74,Sheet10!C76) -> 336.2 | J90: =I90 -> 336.2 | K90: =J90 -> 336.2 | L90: =K90 -> 336.2 | M90: =L90 -> 336.2 | N90: =M90 -> 336.2 | O90: =AVERAGE(E90:I90) -> 241.38
B91: Operating Lease Liabilities - Current | E91: =Sheet10!G75 -> 49.2 | F91: =Sheet10!F75 -> 48.1 | G91: =Sheet10!E75 -> 47.3 | H91: =Sheet10!D75 -> 49.3 | I91: =Sheet10!C75 -> 44.5 | J91: =I91 -> 44.5 | K91: =J91 -> 44.5 | L91: =K91 -> 44.5 | M91: =L91 -> 44.5 | N91: =M91 -> 44.5
B92: Total Current Liabilities | E92: =SUM(E87:E91) -> 769.3 | F92: =SUM(F87:F91) -> 956.6 | G92: =SUM(G87:G91) -> 797.6 | H92: =SUM(H87:H91) -> 1239.1 | I92: =SUM(I87:I91) -> 956.1 | J92: =SUM(J87:J91) -> 977.04792 | K92: =SUM(K87:K91) -> 987.42514 | L92: =SUM(L87:L91) -> 995.70158 | ... N92: =SUM(N87:N91) -> 1010.793
B94: Long-Term Debt | E94: =E171 -> 3935.3 | F94: =F171 -> 3910 | G94: =G171 -> 3893.9 | H94: =H171 -> 4916.6 | I94: =I171 -> 4366.7 | J94: =J171 -> 4366.7 | K94: =K171 -> 4366.7 | L94: =L171 -> 4366.7 | ... N94: =N171 -> 4366.7
B95: Deferred Tax Liabilities | E95: =Sheet10!G84 -> 1005.9 | F95: =Sheet10!F84 -> 1072.8 | G95: =Sheet10!E84 -> 1028.9 | H95: =Sheet10!D84 -> 1336.5 | I95: =Sheet10!C84 -> 1358.3 | J95: =I95 -> 1358.3 | K95: =J95 -> 1358.3 | L95: =K95 -> 1358.3 | M95: =L95 -> 1358.3 | N95: =M95 -> 1358.3
B96: Other Non-Current Liabilities | E96: =SUM(Sheet10!G86,Sheet10!G87) -> 1404.4 | F96: =SUM(Sheet10!F86,Sheet10!F87) -> 1343 | G96: =SUM(Sheet10!E86,Sheet10!E87) -> 1317.4 | H96: =SUM(Sheet10!D86,Sheet10!D87) -> 1470.1 | I96: =SUM(Sheet10!C86,Sheet10!C87) -> 1470.4 | J96: =I96 -> 1470.4 | K96: =J96 -> 1470.4 | L96: =K96 -> 1470.4 | M96: =L96 -> 1470.4 | N96: =M96 -> 1470.4
B97: Total Non-current Liabilities | E97: =SUM(E94:E96) -> 6345.6 | F97: =SUM(F94:F96) -> 6325.8 | G97: =SUM(G94:G96) -> 6240.2 | H97: =SUM(H94:H96) -> 7723.2 | I97: =SUM(I94:I96) -> 7195.4 | J97: =SUM(J94:J96) -> 7195.4 | K97: =SUM(K94:K96) -> 7195.4 | L97: =SUM(L94:L96) -> 7195.4 | ... N97: =SUM(N94:N96) -> 7195.4
B98: Total Liabilities | E98: =E92+E97 -> 7114.9 | F98: =F92+F97 -> 7282.4 | G98: =G92+G97 -> 7037.8 | H98: =H92+H97 -> 8962.3 | I98: =I92+I97 -> 8151.5 | J98: =J92+J97 -> 8172.4479 | K98: =K92+K97 -> 8182.8251 | L98: =L92+L97 -> 8191.1016 | ... N98: =N92+N97 -> 8206.193
Q99: 8548.9
B100: Common Equity Attribute to Parent | E100: =Sheet10!G98 -> 6545 | F100: =Sheet10!F98 -> 6928.6 | G100: =Sheet10!E98 -> 7483.4 | H100: =Sheet10!D98 -> 8118.6 | I100: =Sheet10!C98 -> 8525.1 | J100: =I100+J68+J123+J125 -> 9205.835 | K100: =J100+K68+K123+K125 -> 9887.0438 | L100: =K100+L68+L123+L125 -> 10568.31 | M100: =L100+M68+M123+M125 -> 11247.484 | N100: =M100+N68+N123+N125 -> 11921.344 | Q100: 8142.5
B101: % EBITDA
B102: Minority Interest | E102: =Sheet10!G108 -> 22.7 | F102: =Sheet10!F108 -> 23.6 | G102: =Sheet10!E108 -> 24.5 | H102: =Sheet10!D108 -> 23.9 | I102: =Sheet10!C108 -> 23.8 | J102: =I102 -> 23.8 | K102: =J102 -> 23.8 | L102: =K102 -> 23.8 | M102: =L102 -> 23.8 | N102: =M102 -> 23.8
B103: % EBITDA
B104: Total Shareholders' Equity | E104: =E100+E102 -> 6567.7 | F104: =F100+F102 -> 6952.2 | G104: =G100+G102 -> 7507.9 | H104: =H100+H102 -> 8142.5 | I104: =I100+I102 -> 8548.9 | J104: =J100+J102 -> 9229.635 | K104: =K100+K102 -> 9910.8438 | L104: =L100+L102 -> 10592.11 | ... N104: =N100+N102 -> 11945.144 | Q104: 7507.9
B105: Total Liabilities & Equity | E105: =E98+E104 -> 13682.6 | F105: =F98+F104 -> 14234.6 | G105: =G98+G104 -> 14545.7 | H105: =H98+H104 -> 17104.8 | I105: =I98+I104 -> 16700.4 | J105: =J98+J104 -> 17402.083 | K105: =K98+K104 -> 18093.669 | L105: =L98+L104 -> 18783.212 | ... N105: =N98+N104 -> 20151.337 | Q105: 6952.2
B106: Balance Check (TA − TL&E) | E106: =E85-E105 -> 0 | F106: =F85-F105 -> 0 | G106: =G85-G105 -> 0 | H106: =H85-H105 -> 0 | I106: =I85-I105 -> 0 | J106: =J85-J105 -> 0 | K106: =K85-K105 -> 0 | L106: =L85-L105 -> 0 | ... N106: =N85-N105 -> 0 | Q106: 6567.7
B107: Debt / Equity | E107: =(E89+E94)/E104 -> 0.60537174 | F107: =(F89+F94)/F104 -> 0.58007537 | G107: =(G89+G94)/G104 -> 0.52037187 | H107: =(H89+H94)/H104 -> 0.65431993 | I107: =(I89+I94)/I104 -> 0.5115161 | J107: =(J89+J94)/J104 -> 0.47378905 | K107: =(K89+K94)/K104 -> 0.44122378 | L107: =(L89+L94)/L104 -> 0.41284503 | ... N107: =(N89+N94)/N104 -> 0.36608181
B109: CASH FLOW STATEMENT
B110: ($mm unless noted) | E110: FY2021 | F110: FY2022 | G110: FY2023 | H110: FY2024 | I110: FY2025 | J110: FY2026E | K110: FY2027E | L110: FY2028E | M110: FY2029E | N110: FY2030E
B111: CASH FROM OPERATIONS
B112: Net Income | E112: =E68 -> 746.2 | F112: =F68 -> 683.1 | G112: =G68 -> 967.5 | H112: =H68 -> 1020.3 | I112: =I68 -> 1071.8 | J112: =J68 -> 1002.5573 | K112: =K68 -> 1028.7768 | L112: =L68 -> 1049.6884 | ... N112: =N68 -> 1087.8191
...

Sheet DCF-WACC 
B3: Cost of Equity (CAPM) | C3: =C4+C5*C6 -> 0.08565
B4: Risk-Free Rate (Rf) | C4: 0.04
B5: Equity Risk Premium (ERP) | C5: 0.055
B6: Beta vs S&P 500 (β) | C6: 0.83
B9: Cost of Debt | C9: Value
B10: Risk-Free Ratee (Rf) | C10: 0.04
B13: Market Valuation | C13: 38649.068
B14: Total Debt | C14: 4372.9
B15: WACC | C15: =(C13-C14)/(C13+C14)*C3+(C14/(C13+C14))*(1-'DCF_Forecast Revenue'!R47)*'DCF-WACC '!C10 -> 0.071418944

Sheet Sheet10
B4: 5 Years of Vulcan Statement | K4: MLM TICKET | O4: KNF Ticket | R4: CRH | U4: CX Ticket | X4: EXP Ticket
B5: Balance Sheet - Standardized (Currency: Standardized) | K5: Balance Sheet - Standardized (Currency: Standardized) - MLM Ticket | O5: Balance Sheet - Standardized (Currency: Standardized) - KNF Ticket | R5: Balance Sheet - Standardized (Currency: Standardized) - CRH Ticket | U5: Balance Sheet - Standardized (Currency: Standardized) - CX Ticket | X5: Balance Sheet - Standardized (Currency: Standardized) - EXP Ticket
B6: Field Name | C6: 31-12-2025 | D6: 31-12-2024 | E6: 31-12-2023 | F6: 31-12-2022 | G6: 31-12-2021 | K6: Field Name | L6: 31-12-2025 | O6: Field Name | P6: 31-12-2025 | R6: Field Name | S6: 31-12-2025 | U6: Field Name | V6: 31-12-2025 | X6: Field Name | Y6: 31-03-2025
B7: Current Assets | K7: Current Assets | O7: Current Assets | R7: Current Assets | U7: Current Assets | X7: Current Assets
B8: Cash & Short-Term Investments | C8: 183.3 | D8: 559.7 | E8: 931.1 | F8: 161.4 | G8: 235 | K8: Cash & Short-Term Investments | L8: 67 | O8: Cash & Short-Term Investments | P8: 123.42 | R8: Cash & Short-Term Investments | S8: 4096 | U8: Cash & Short-Term Investments | V8: 1976.07 | X8: Cash & Short-Term Investments | Y8: 20.4
B9: Cash & Cash Equivalents | C9: 183.3 | D9: 559.7 | E9: 931.1 | F9: 161.4 | G9: 235 | K9: Cash & Cash Equivalents | L9: 67 | O9: Cash & Cash Equivalents | P9: 123.42 | R9: Cash & Cash Equivalents | S9: 4096 | U9: Cash & Cash Equivalents | V9: 1822.36 | X9: Cash & Cash Equivalents | Y9: 20.4
B10: Loans & Receivables - Net - Short-Term | C10: 887.7 | D10: 892.3 | E10: 889.7 | F10: 1045.3 | G10: 838.7 | K10: Loans & Receivables - Net - Short-Term | L10: 723 | O10: Loans & Receivables - Net - Short-Term | P10: 355.56 | R10: Loans & Receivables - Net - Short-Term | S10: 5452 | U10: Short-Term Investments - Total | V10: 153.71 | X10: Loans & Receivables - Net - Short-Term | Y10: 222.35
B11: Trade Accounts & Trade Notes Receivable - Net | C11: 887.7 | D11: 892.3 | E11: 889.7 | F11: 845.6 | G11: 783.2 | K11: Trade Accounts & Trade Notes Receivable - Net | L11: 708 | O11: Trade Accounts & Trade Notes Receivable - Net | P11: 150.65 | R11: Trade Accounts & Trade Notes Receivable - Net | S11: 5178 | U11: Financial Assets - Short-Term | V11: 153.71 | X11: Trade Accounts & Trade Notes Receivable - Net | Y11: 212.33
B12: Trade Accounts & Trade Notes Receivable - Gross | C12: 898.2 | D12: 905.5 | E12: 903.3 | F12: 856.5 | G12: 793.5 | K12: Trade Accounts & Trade Notes Receivable - Gross | L12: 715 | O12: Trade Accounts & Trade Notes Receivable - Gross | P12: 155.84 | R12: Trade Accounts & Trade Notes Receivable - Gross | S12: 5315 | U12: Loans & Receivables - Net - Short-Term | V12: 2556.68 | X12: Trade Accounts & Trade Notes Receivable - Gross | Y12: 218.73
B13: Provision - Trade Accounts & Trade Notes Receivable | C13: 10.5 | D13: 13.2 | E13: 13.6 | F13: 10.9 | G13: 10.3 | K13: Provision - Trade Accounts & Trade Notes Receivable | L13: 7 | O13: Provision - Trade Accounts & Trade Notes Receivable | P13: 5.19 | R13: Provision - Trade Accounts & Trade Notes Receivable | S13: 137 | U13: Trade Accounts & Trade Notes Receivable - Net | V13: 1769.5 | X13: Provision - Trade Accounts & Trade Notes Receivable | Y13: 6.4
B14: Receivables - Other - Total | F14: 199.7 | G14: 55.5 | K14: Receivables - Other - Total | L14: 15 | O14: Receivables - Other - Total | P14: 204.91 | R14: Income Tax - Receivables - Short-Term | S14: 274 | U14: Receivables - Other - Total | V14: 787.18 | X14: Income Tax - Receivables - Short-Term | Y14: 10.02
B15: Inventories - Total | C15: 680.5 | D15: 681.8 | E15: 615.6 | F15: 579.3 | G15: 521.3 | K15: Inventories - Total | L15: 1078 | O15: Inventories - Total | P15: 435.71 | R15: Inventories - Total | S15: 5251 | U15: Inventories - Total | V15: 1522.35 | X15: Inventories - Total | Y15: 415.18
B16: Inventories - Raw Materials | C16: 36.7 | D16: 69.7 | E16: 51.2 | F16: 63.4 | G16: 59.9 | K16: Inventories - Raw Materials | L16: 49 | O16: Inventories - Raw Materials | P16: 131.43 | R16: Inventories - Raw Materials | S16: 2295 | U16: Inventories - Raw Materials | V16: 1522.35 | X16: Inventories - Raw Materials | Y16: 164.68
B17: Inventories - Work in Progress | C17: 5.4 | D17: 9 | E17: 6.5 | F17: 6 | G17: 4.2 | K17: Inventories - Work in Progress | L17: 14 | O17: Inventories - Finished Goods | P17: 304.28 | R17: Inventories - Work in Progress | S17: 360 | U17: Assets Held for Sale/Discontinued Operations - Short-Term | V17: 41.67 | X17: Inventories - Finished Goods | Y17: 91.1
B18: Inventories - Finished Goods | C18: 557.7 | D18: 534.6 | E18: 494.4 | F18: 439.3 | G18: 418 | K18: Inventories - Finished Goods | L18: 1378 | O18: Prepaid Expenses - Short-Term | P18: 46.23 | R18: Inventories - Finished Goods | S18: 2596 | U18: Total Current Assets | V18: 6096.77 | X18: Inventories - Other - Total | Y18: 159.39
B19: Inventories - Other - Total | C19: 80.7 | D19: 68.5 | E19: 63.5 | F19: 70.6 | G19: 39.2 | K19: Inventories - Other - Total | L19: -363 | O19: Total Current Assets | P19: 960.92 | R19: Prepaid Expenses - Short-Term | S19: 394 | U19: Non-Current Assets | X19: Prepaid Expenses - Short-Term | Y19: 10.73
B20: Assets Held for Sale/Discontinued Operations - Short-Term | C20: 708.5 | K20: Assets Held for Sale/Discontinued Operations - Short-Term | L20: 1230 | O20: Non-Current Assets | R20: Other Current Assets - Total | S20: 61 | U20: Investments - Long-Term | V20: 83.65 | X20: Total Current Assets | Y20: 668.66
B21: Other Current Assets - Total | C21: 107.9 | D21: 131.9 | E21: 88.5 | F21: 116 | G21: 101.6 | K21: Other Current Assets - Total | L21: 95 | O21: Investments - Long-Term | P21: 55.32 | R21: Restricted Accounts - Short-Term | S21: 51 | U21: Financial Assets - Long-Term | V21: 83.65 | X21: Non-Current Assets
B22: Restricted Accounts - Short-Term | C22: 6.1 | D22: 41.1 | E22: 18.1 | F22: 0.1 | G22: 6.5 | K22: Other Current Assets | L22: 95 | O22: Investments - Available for Sale/Held to Maturity - Long-Term | P22: 55.32 | R22: Other Current Assets | S22: 10 | U22: Investments in Associates, Joint Ventures and Unconsolidated Subsidiaries | V22: 792.14 | X22: Investments in Associates, Joint Ventures and Unconsolidated Subsidiaries | Y22: 140.09
B23: Other Current Assets | C23: 101.8 | D23: 90.8 | E23: 70.4 | F23: 115.9 | G23: 95.1 | K23: Total Current Assets | L23: 3193 | O23: Property, Plant & Equipment - Net - Total | P23: 2081.52 | R23: Total Current Assets | S23: 15254 | U23: Receivables & Loans - Long-Term | V23: 128.17 | X23: Property, Plant & Equipment - Net - Total | Y23: 1822.3
B24: Total Current Assets | C24: 2567.9 | D24: 2265.7 | E24: 2524.9 | F24: 1902 | G24: 1696.6 | K24: Non-Current Assets | O24: Property, Plant & Equipment - excluding Assets Leased Out - Net - Total | P24: 2081.52 | R24: Non-Current Assets | U24: Loans - Long-Term | V24: 128.17 | X24: Property, Plant & Equipment - excluding Assets Leased Out - Net - Total | Y24: 1822.3
B25: Non-Current Assets | K25: Property, Plant & Equipment - Net - Total | L25: 10657 | O25: Property, Plant & Equipment - Gross - Total | P25: 3561.83 | R25: Investments in Associates, Joint Ventures and Unconsolidated Subsidiaries | S25: 502 | U25: Property, Plant & Equipment - Net - Total | V25: 12168.49 | X25: Property, Plant & Equipment - Gross - Total | Y25: 3452.44
B26: Investments - Long-Term | C26: 33.7 | D26: 31.3 | E26: 31.3 | F26: 31.8 | G26: 34.1 | K26: Property, Plant & Equipment - excluding Assets Leased Out - Net - Total | L26: 10657 | O26: Property, Plant & Equipment - excluding Assets Leased Out - Gross | P26: 3561.83 | R26: Property, Plant & Equipment - Net - Total | S26: 26408 | U26: Property, Plant & Equipment - excluding Assets Leased Out - Net - Total | V26: 12168.49 | X26: Property, Plant & Equipment - excluding Assets Leased Out - Gross | Y26: 3452.44
B27: Investments - Available for Sale/Held to Maturity - Long-Term | C27: 33.7 | D27: 31.3 | E27: 31.3 | F27: 31.8 | G27: 34.1 | K27: Property, Plant & Equipment - Gross - Total | L27: 15697 | O27: Land & Buildings - Gross | P27: 521.44 | R27: Property, Plant & Equipment - excluding Assets Leased Out - Net - Total | S27: 26408 | U27: Land & Buildings - Net | V27: 4962.54 | X27: Land & Buildings - Gross | Y27: 677.42
B28: Property, Plant & Equipment - Net - Total | C28: 8670.1 | D28: 8987.9 | E28: 6729.4 | F28: 6623.9 | G28: 6238.2 | K28: Property, Plant & Equipment - excluding Assets Leased Out - Gross | L28: 15697 | O28: Land/Improvements - Gross | P28: 229.55 | R28: Property, Plant & Equipment - Gross - Total | S28: 44016 | U28: Land/Improvements - Net | V28: 3631 | X28: Land/Improvements - Gross | Y28: 364.55
B29: Property, Plant & Equipment - excluding Assets Leased Out - Net - Total | C29: 8443.7 | D29: 8752.3 | E29: 6558.1 | F29: 6458 | G29: 6055.7 | K29: Land & Buildings - Gross | L29: 2122 | O29: Buildings - Gross | P29: 291.89 | R29: Property, Plant & Equipment - excluding Assets Leased Out - Gross | S29: 44016 | U29: Buildings - Net | V29: 1331.54 | X29: Buildings - Gross | Y29: 312.87
B30: Land & Buildings - Net | C30: 6168.4 | D30: 6109.2 | E30: 4497 | F30: 4214.4 | G30: 3814.6 | K30: Land/Improvements - Gross | L30: 1929 | O30: Plant, Machinery & Equipment - Gross | P30: 2050.25 | R30: Land & Buildings - Gross | S30: 12988 | U30: Plant, Machinery & Equipment - Net | V30: 4739.22 | X30: Plant, Machinery & Equipment - Gross | Y30: 2567.54
B31: Land/Improvements - Net | C31: 5887.4 | D31: 5804.8 | E31: 4292.6 | F31: 3991.1 | G31: 3631.7 | K31: Buildings - Gross | L31: 193 | O31: Construction in Progress - Gross | P31: 90.07 | R31: Plant, Machinery & Equipment - Gross | S31: 25842 | U31: Construction in Progress - Net | V31: 1199.72 | X31: Construction in Progress - Gross | Y31: 178.17
B32: Buildings - Net | C32: 281 | D32: 304.4 | E32: 204.4 | F32: 223.3 | G32: 182.9 | K32: Plant, Machinery & Equipment - Gross | L32: 5992 | O32: Right of Use Tangible Assets - Total - Gross | P32: 52.59 | R32: Construction in Progress - Gross | S32: 2974 | U32: Right of Use Tangible Assets - Total - Net | V32: 1114.39 | X32: Right of Use Tangible Assets - Total - Gross | Y32: 29.31
B33: Plant, Machinery & Equipment - Net | C33: 7576.3 | D33: 7717.2 | E33: 6785.5 | F33: 6454.2 | G33: 6109.2 | K33: Construction in Progress - Gross | L33: 319 | O33: Right of Use Tangible Assets - Operating Lease - Gross | P33: 52.59 | R33: Right of Use Tangible Assets - Total - Gross | S33: 2212 | U33: Right of Use Tangible Assets - Capital/Finance Lease - Net | V33: 1114.39 | X33: Right of Use Tangible Assets - Operating Lease - Gross | Y33: 29.31
B34: Construction in Progress - Net | C34: 498.3 | D34: 400.1 | E34: 319.4 | F34: 378.7 | G34: 301.8 | K34: Right of Use Tangible Assets - Total - Gross | L34: 735 | O34: Property, Plant & Equipment - Other - Gross | P34: 847.47 | R34: Right of Use Tangible Assets - Operating Lease - Gross | S34: 1471 | U34: Property, Plant & Equipment - Other - Net | V34: 152.62 | X34: Property, Plant & Equipment - Accumulated Depreciation & Impairment - Total | Y34: 1630.15
B35: Right of Use Tangible Assets - Total - Net | C35: 556.8 | D35: 581.1 | E35: 574 | F35: 665.8 | G35: 727.7 | K35: Right of Use Tangible Assets - Operating Lease - Gross | L35: 367 | O35: Property, Plant & Equipment - Accumulated Depreciation & Impairment - Total | P35: 1480.31 | R35: Right of Use Tangible Assets - Capital/Finance Lease - Gross | S35: 741 | U35: Other Non-Current Assets - Total | V35: 536.48 | X35: Property, Plant & Equipment - excluding Assets Leased Out - Accumulated Depreciation & Impairment - Total | Y35: 1630.15
B36: Right of Use Tangible Assets - Operating Lease - Net | C36: 521.5 | D36: 526.4 | E36: 511.7 | F36: 572.6 | G36: 691.4 | K36: Right of Use Tangible Assets - Capital/Finance Lease - Gross | L36: 368 | O36: Property, Plant & Equipment - excluding Assets Leased Out - Accumulated Depreciation & Impairment - Total | P36: 1480.31 | R36: Property, Plant & Equipment - Accumulated Depreciation & Impairment - Total | S36: 17608 | U36: Deferred Tax - Asset - Long-Term | V36: 536.48 | X36: Other Non-Current Assets - Total | Y36: 37.8
B37: Right of Use Tangible Assets - Capital/Finance Lease - Net | C37: 35.3 | D37: 54.7 | E37: 62.3 | F37: 93.2 | G37: 36.3 | K37: Property, Plant & Equipment - Other - Gross | L37: 6529 | O37: Intangible Assets - Total - Net | P37: 552.35 | R37: Property, Plant & Equipment - excluding Assets Leased Out - Accumulated Depreciation & Impairment - Total | S37: 17608 | U37: Intangible Assets - Total - Net | V37: 9159.82 | X37: Other Non-Current Assets | Y37: 37.8
... B40: Property, Plant & Equipment - excluding Assets Leased Out - Gross | C40: 15178.9 | D40: 15190 | E40: 12471.6 | F40: 11971.8 | G40: 11215.5 | K40: Property, Plant & Equipment - excluding Assets Leased Out - Accumulated Depreciation & Impairment - Total | L40: 5040 | O40: Brands, Patents, Trademarks, Marketing & Artistic Intangibles - Net | P40: 6.8 | R40: Intangible Assets - Total - Net | S40: 15147 | U40: Total Non-Current Assets | V40: 22868.74 | X40: Intangible Assets - excluding Goodwill - Net - Total | Y40: 125.86
B41: Land & Buildings - Gross | C41: 6168.4 | D41: 6109.2 | E41: 4497 | F41: 4214.4 | G41: 3814.6 | K41: Assets Held for Sale/Discontinued Operations - Long-Term | L41: 0 | O41: Intangible Assets - Other - Net | P41: 25.88 | R41: Goodwill/Cost in Excess of Assets Purchased - Net | S41: 13099 | U41: Total Assets | X41: Brands, Patents, Trademarks, Marketing & Artistic Intangibles - Net | Y41: 1.4
B42: Land/Improvements - Gross | C42: 5887.4 | D42: 5804.8 | E42: 4292.6 | F42: 3991.1 | G42: 3631.7 | K42: Other Non-Current Assets - Total | L42: 788 | O42: Total Non-Current Assets | P42: 2689.19 | R42: Intangible Assets - excluding Goodwill - Net - Total | S42: 2048 | U42: Total Assets | V42: 28965.51 | X42: Licenses, Franchises, Copyrights, Property Rights, Prototypes, Contract Based, Models & Designs - Net | Y42: 108.06
B43: Buildings - Gross | C43: 281 | D43: 304.4 | E43: 204.4 | F43: 223.3 | G43: 182.9 | K43: Other Non-Current Assets | L43: 788 | O43: Total Assets | R43: Total Non-Current Assets | S43: 43075 | U43: Current Liabilities | X43: Intangible Assets - Other - Net | Y43: 16.4
B44: Plant, Machinery & Equipment - Gross | C44: 7576.3 | D44: 7717.2 | E44: 6785.5 | F44: 6454.2 | G44: 6109.2 | K44: Intangible Assets - Total - Net | L44: 4073 | O44: Total Assets | P44: 3650.11 | R44: Total Assets | U44: Trade Accounts Payable & Accruals - Short-Term | V44: 3477.3 | X44: Intangible Assets - Gross - Total | Y44: 700.56
B45: Construction in Progress - Gross | C45: 498.3 | D45: 400.1 | E45: 319.4 | F45: 378.7 | G45: 301.8 | K45: Goodwill/Cost in Excess of Assets Purchased - Net | L45: 3614 | O45: Current Liabilities | R45: Total Assets | S45: 58329 | U45: Trade Accounts & Trade Notes Payable - Short-Term | V45: 3107.89 | X45: Goodwill/Cost in Excess of Assets Purchased - Gross | Y45: 469.89
B46: Right of Use Tangible Assets - Total - Gross | C46: 709.5 | D46: 727.9 | E46: 698.4 | F46: 758.6 | G46: 807.4 | K46: Intangible Assets - excluding Goodwill - Net - Total | L46: 459 | O46: Trade Accounts Payable & Accruals - Short-Term | P46: 309.22 | R46: Current Liabilities | U46: Accrued Expenses - Short-Term | V46: 369.41 | X46: Intangible Assets - excluding Goodwill - Gross | Y46: 230.66
B47: Right of Use Tangible Assets - Operating Lease - Gross | C47: 674.2 | D47: 673.2 | E47: 636.1 | F47: 665.4 | G47: 771.1 | K47: Brands, Patents, Trademarks, Marketing & Artistic Intangibles - Net | L47: 12 | O47: Trade Accounts & Trade Notes Payable - Short-Term | P47: 145.58 | R47: Trade Accounts Payable & Accruals - Short-Term | S47: 5459 | U47: Short-Term Debt & Current Portion of Long-Term Debt | V47: 1454.44 | X47: Brands, Patents, Trademarks, Marketing & Artistic Intangibles - Gross | Y47: 2.4
B48: Right of Use Tangible Assets - Capital/Finance Lease - Gross | C48: 35.3 | D48: 54.7 | E48: 62.3 | F48: 93.2 | G48: 36.3 | K48: Licenses, Franchises, Copyrights, Property Rights, Prototypes, Contract Based, Models & Designs - Net | L48: 44 | O48: Accrued Expenses - Short-Term | P48: 163.64 | R48: Trade Accounts & Trade Notes Payable - Short-Term | S48: 3263 | U48: Current Portion of Long-Term Debt including Capitalized Leases | V48: 1454.44 | X48: Licenses, Franchises, Copyrights, Property Rights, Prototypes, Contract Based, Models & Designs - Gross | Y48: 197.5
